Workbook

Sheet Análisis general
B1: Análisis del terremoto — resumen general | J1: Indicadores clave
B3: Departamento | C3: N.º de municipios | D3: Puntos totales | E3: Indice de Pobreza - 2025 | G3: Indicador | H3: Cifras | J3: Indicador | K3: Valor
B4: Antioquia | C4: 99 | D4: 241 | E4: 9.5 | G4: Magnitud y epicentro | H4: 7,4 - San José del Palmar(Chocó) | J4: Departamentos afectados | K4: 25
B5: Atlántico | C5: 1 | D5: 13 | E5: 8.2 | G5: Viviendas destruidas | H5: 26558 | J5: Municipios afectados | K5: 432
B6: Bogotá D.C. | C6: 1 | D6: 94 | E6: 2.2 | G6: Viviendas averiadas | H6: 127266 | J6: Puntos totales | K6: 3366
B7: Bolívar | C7: 3 | D7: 14 | E7: 17 | G7: edificios colapsados | H7: 197 | J7: Viviendas afectadas | K7: 153824
B8: Boyacá | C8: 2 | D8: 2 | E8: 6.4 | G8: Centros de salud | H8: 300
B9: Caldas | C9: 27 | D9: 654 | E9: 7.9 | G9: vías afectadas | H9: 403
B10: Caquetá | C10: 1 | D10: 1 | E10: 15 | G10: Centros educativos | H10: 3074
B11: Cauca | C11: 39 | D11: 93 | E11: 13
B12: Cesar | C12: 4 | D12: 7 | E12: 14.8 | G12: Fallecidos | H12: 304
B13: Chocó | C13: 27 | D13: 227 | E13: 30.8 | G13: Heridos | H13: 4400
B14: Córdoba | C14: 1 | D14: 3 | E14: 19.8 | G14: Desaparecidos | H14: 426
B15: Cundinamarca | C15: 58 | D15: 96 | E15: 4.1 | G15: Rescatados | H15: 357
B16: Huila | C16: 23 | D16: 71 | E16: 9.7
B17: La Guajira | C17: 1 | D17: 2 | E17: 40.1
B18: Magdalena | C18: 1 | D18: 3 | E18: 17.6
B19: Meta | C19: 3 | D19: 6 | E19: 12.3
B20: Nariño | C20: 17 | D20: 47 | E20: 13.2
B21: Norte de Santander | C21: 7 | D21: 11 | E21: 13.3
B22: Putumayo | C22: 1 | D22: 1 | E22: 13.6
B23: Quindío | C23: 12 | D23: 294 | E23: 6.7
B24: Risaralda | C24: 14 | D24: 353 | E24: 4.9
B25: Santander | C25: 5 | D25: 32 | E25: 6.9
B26: Sucre | C26: 2 | D26: 5 | E26: 25.4
B27: Tolima | C27: 42 | D27: 129 | E27: 12.2
... B29: Total general | C29: 432 | D29: 3366 | E29: 6300

Sheet Municipios completos
A1: Código DIVIPOLA | B1: Departamento | C1: Clasificación | D1: Priorizacion | E1: Priorizacion 3 (IPM peso 0.5, escala 0-9) | F1: Priorizacion 4 (sin Cruce_Proyectos, escala 0-9) | G1: Municipio | H1: Colegios CPE | I1: CPE | J1: Olimpiadas Nacional | K1: Colegios Olimpiadas | L1: Minculturas | M1: Asociacion turistica | N1: Puntos | O1: Edificación colapsada | P1: Edificación con daño | Q1: Vivienda afectada | R1: Hospital o centro de salud | S1: Escuela o colegio | T1: Patrimonio o templo | U1: Servicio público | V1: Vía afectada | W1: Deslizamiento | X1: Albergue o punto de atención | Y1: Punto de ayuda o acopio | Z1: Novedad o noticia | AA1: Toque de queda o restricción | AB1: Otro | AC1: Puente | AD1: Incendio | AE1: Saqueo | AF1: Robo | AG1: PRUEBA | AH1: Afectados Familia | AI1: Afectados Personas | AJ1: Indice de Pobreza - 2018 | AK1: ayudas | AL1: tipo de ayuda | AM1: Descripción / Tipo de afectación | AO1: Municipio (normalizado) | AP1: Departamento (normalizado) | AQ1: ¿Nombre ambiguo? | AR1: Clave de cruce | AS1: Cruce_Proyectos | AT1: Total_Daños | AU1: Daño_Norm (0-3) | AV1: Ayuda_Norm_Inv (0-3) | AX1: Umbrales de Daño (cuartiles) | AZ1: Ayuda_Norm_Bin (0/3) | BA1: Priorizacion 2 | BB1: IPM_Departamento (2025) | BC1: IPM_Norm (0-3) | BD1: Priorizacion 3 (IPM peso 0.5, escala 0-9) | BE1: Priorizacion 4 (sin Cruce_Proyectos, escala 0-9) | BF1: Umbrales de IPM (cuartiles)
A2: 66075 | B2: Cauca | C2: Sin clasificación oficial | D2: =AS2+AU2+AV2 -> 6 | E2: =BD2 -> 6.4285714 | F2: =BE2 -> 9 | G2: Balboa | H2: =IFERROR(IF($AQ2,INDEX(cpe!$C$2:$C$307,MATCH($AR2,cpe!$F$2:$F$307,0)),INDEX(cpe!$C$2:$C$307,MATCH($AR2,cpe!$D$2:$D$307,0))),"#N/D") -> #N/D | I2: =IFERROR(IF($AQ2,INDEX(cpe!$B$2:$B$307,MATCH($AR2,cpe!$F$2:$F$307,0)),INDEX(cpe!$B$2:$B$307,MATCH($AR2,cpe!$D$2:$D$307,0))),"#N/D") -> #N/D | J2: =IF($AQ2,"#N/D",IFERROR(INDEX(Olimpiadas!$B$2:$B$61,MATCH($AO2,Olimpiadas!$C$2:$C$61,0)),"#N/D")) -> #N/D | K2: =IF($AQ2,"#N/D",IFERROR(INDEX(Olimpiadas!$A$2:$A$61,MATCH($AO2,Olimpiadas!$C$2:$C$61,0)),"#N/D")) -> #N/D | L2: =IF($AQ2,"#N/D",IFERROR(INDEX(Minculturas!$A$2:$A$48,MATCH($AO2,Minculturas!$C$2:$C$48,0)),"#N/D")) -> #N/D | M2: =IF($AQ2,"#N/D",IFERROR(INDEX(Minculturas!$B$2:$B$48,MATCH($AO2,Minculturas!$C$2:$C$48,0)),"#N/D")) -> #N/D | N2: 11 | O2: 0 | P2: 3 | Q2: 1 | R2: 1 | S2: 3 | T2: 1 | U2: 1 | V2: 1 | W2: 0 | X2: 0 | Y2: 0 | Z2: 0 | AA2: 0 | AB2: 0 | AC2: 0 | AD2: 0 | AE2: 0 | AF2: 0 | AG2: =SUM(O2:X2) -> 11 | AJ2: 31.6 | AM2: Declarado afectado; sin lugar con nombre propio publicado en este registro. | AO2: =TRIM(SUBSTITUTE(SUBSTITUTE(SUBSTITUTE(SUBSTITUTE(SUBSTITUTE(SUBSTITUTE(SUBSTITUTE(SUBSTITUTE(SUBSTITUTE(LOWER(G2),"á","a"),"é","e"),"í","i"),"ó","o"),"ú","u"),"ñ","n"),"-"," "),","," "),"."," ")) -> balboa | AP2: =TRIM(SUBSTITUTE(SUBSTITUTE(SUBSTITUTE(SUBSTITUTE(SUBSTITUTE(SUBSTITUTE(SUBSTITUTE(SUBSTITUTE(SUBSTITUTE(LOWER(B2),"á","a"),"é","e"),"í","i"),"ó","o"),"ú","u"),"ñ","n"),"-"," "),","," "),"."," ")) -> cauca | AQ2: =COUNTIF($AO$2:$AO$433,AO2)>COUNTIFS($AO$2:$AO$433,AO2,$AP$2:$AP$433,AP2) -> TRUE | AR2: =IF(AQ2,AO2&"|"&AP2,AO2) -> balboa|cauca | AS2: =(I2<>"#N/D")+(J2<>"#N/D")+(L2<>"#N/D") -> 0 | AT2: =SUM(O2:X2) -> 11 | AU2: =IF(AT2<=$AY$2,0,IF(AT2<=$AY$3,1,IF(AT2<=$AY$4,2,3))) -> 3 | AV2: =IF(Y2<=$AY$7,3,IF(Y2<=$AY$8,2,IF(Y2<=$AY$9,1,0))) -> 3 | AX2: Q2 (50%) | AY2: =_xlfn.QUARTILE.INC($Y$2:$Y$433,2) -> 0 | AZ2: =IF(Y2=0,3,0) -> 3 | BA2: =AS2+AU2+AZ2 -> 6 | BB2: =IFERROR(INDEX('Análisis general'!$E$4:$E$28,MATCH($B2,'Análisis general'!$B$4:$B$28,0)),"") -> 13 | BC2: =IF(BB2="","",IF(BB2<=$BG$2,0,IF(BB2<=$BG$3,1,IF(BB2<=$BG$4,2,3)))) -> 3 | BD2: =(AS2+AU2+AZ2+(BC2/2))*(9/10.5) -> 6.4285714 | BE2: =(AU2+AZ2+(BC2/2))*(9/7.5) -> 9
A3: 27250 | B3: Chocó | C3: Sin clasificación oficial | D3: =AS3+AU3+AV3 -> 6 | E3: =BD3 -> 6.4285714 | F3: =BE3 -> 9 | G3: El Litoral del San Juan | H3: =IFERROR(IF($AQ3,INDEX(cpe!$C$2:$C$307,MATCH($AR3,cpe!$F$2:$F$307,0)),INDEX(cpe!$C$2:$C$307,MATCH($AR3,cpe!$D$2:$D$307,0))),"#N/D") -> #N/D | I3: =IFERROR(IF($AQ3,INDEX(cpe!$B$2:$B$307,MATCH($AR3,cpe!$F$2:$F$307,0)),INDEX(cpe!$B$2:$B$307,MATCH($AR3,cpe!$D$2:$D$307,0))),"#N/D") -> #N/D | J3: =IF($AQ3,"#N/D",IFERROR(INDEX(Olimpiadas!$B$2:$B$61,MATCH($AO3,Olimpiadas!$C$2:$C$61,0)),"#N/D")) -> #N/D | K3: =IF($AQ3,"#N/D",IFERROR(INDEX(Olimpiadas!$A$2:$A$61,MATCH($AO3,Olimpiadas!$C$2:$C$61,0)),"#N/D")) -> #N/D | L3: =IF($AQ3,"#N/D",IFERROR(INDEX(Minculturas!$A$2:$A$48,MATCH($AO3,Minculturas!$C$2:$C$48,0)),"#N/D")) -> #N/D | M3: =IF($AQ3,"#N/D",IFERROR(INDEX(Minculturas!$B$2:$B$48,MATCH($AO3,Minculturas!$C$2:$C$48,0)),"#N/D")) -> #N/D | N3: 11 | O3: 0 | P3: 0 | Q3: 4 | R3: 2 | S3: 2 | T3: 0 | U3: 1 | V3: 0 | W3: 0 | X3: 0 | Y3: 0 | Z3: 2 | AA3: 0 | AB3: 0 | AC3: 0 | AD3: 0 | AE3: 0 | AF3: 0 | AG3: =SUM(O3:X3) -> 9 | AH3: 525 | AI3: 1837 | AJ3: 83.1 | AM3: Declarado afectado; sin lugar con nombre propio publicado en este registro. | AO3: =TRIM(SUBSTITUTE(SUBSTITUTE(SUBSTITUTE(SUBSTITUTE(SUBSTITUTE(SUBSTITUTE(SUBSTITUTE(SUBSTITUTE(SUBSTITUTE(LOWER(G3),"á","a"),"é","e"),"í","i"),"ó","o"),"ú","u"),"ñ","n"),"-"," "),","," "),"."," ")) -> el litoral del san juan | AP3: =TRIM(SUBSTITUTE(SUBSTITUTE(SUBSTITUTE(SUBSTITUTE(SUBSTITUTE(SUBSTITUTE(SUBSTITUTE(SUBSTITUTE(SUBSTITUTE(LOWER(B3),"á","a"),"é","e"),"í","i"),"ó","o"),"ú","u"),"ñ","n"),"-"," "),","," "),"."," ")) -> choco | AQ3: =COUNTIF($AO$2:$AO$433,AO3)>COUNTIFS($AO$2:$AO$433,AO3,$AP$2:$AP$433,AP3) -> FALSE | AR3: =IF(AQ3,AO3&"|"&AP3,AO3) -> el litoral del san juan | AS3: =(I3<>"#N/D")+(J3<>"#N/D")+(L3<>"#N/D") -> 0 | AT3: =SUM(O3:X3) -> 9 | AU3: =IF(AT3<=$AY$2,0,IF(AT3<=$AY$3,1,IF(AT3<=$AY$4,2,3))) -> 3 | AV3: =IF(Y3<=$AY$7,3,IF(Y3<=$AY$8,2,IF(Y3<=$AY$9,1,0))) -> 3 | AX3: Umbrales de Ayuda (cuartiles) | AZ3: =IF(Y3=0,3,0) -> 3 | BA3: =AS3+AU3+AZ3 -> 6 | BB3: =IFERROR(INDEX('Análisis general'!$E$4:$E$28,MATCH($B3,'Análisis general'!$B$4:$B$28,0)),"") -> 30.8 | BC3: =IF(BB3="","",IF(BB3<=$BG$2,0,IF(BB3<=$BG$3,1,IF(BB3<=$BG$4,2,3)))) -> 3 | BD3: =(AS3+AU3+AZ3+(BC3/2))*(9/10.5) -> 6.4285714 | BE3: =(AU3+AZ3+(BC3/2))*(9/7.5) -> 9
A4: 27745 | B4: Chocó | C4: Afectación alta | D4: =AS4+AU4+AV4 -> 6 | E4: =BD4 -> 6.4285714 | F4: =BE4 -> 9 | G4: Sipí | H4: #N/D | I4: #N/D | J4: #N/D | K4: =IF($AQ4,"#N/D",IFERROR(INDEX(Olimpiadas!$A$2:$A$61,MATCH($AO4,Olimpiadas!$C$2:$C$61,0)),"#N/D")) -> #N/D | L4: =IF($AQ4,"#N/D",IFERROR(INDEX(Minculturas!$A$2:$A$48,MATCH($AO4,Minculturas!$C$2:$C$48,0)),"#N/D")) -> #N/D | M4: =IF($AQ4,"#N/D",IFERROR(INDEX(Minculturas!$B$2:$B$48,MATCH($AO4,Minculturas!$C$2:$C$48,0)),"#N/D")) -> #N/D | N4: 9 | O4: 0 | P4: 3 | Q4: 2 | R4: 1 | S4: 0 | T4: 0 | U4: 2 | V4: 0 | W4: 0 | X4: 0 | Y4: 0 | Z4: 1 | AA4: 0 | AB4: 0 | AC4: 0 | AD4: 0 | AE4: 0 | AF4: 0 | AG4: =SUM(O4:X4) -> 8 | AH4: 330 | AI4: 810 | AJ4: 69.7 | AM4: Afectaciones y zona próxima al entorno del evento. | AO4: =TRIM(SUBSTITUTE(SUBSTITUTE(SUBSTITUTE(SUBSTITUTE(SUBSTITUTE(SUBSTITUTE(SUBSTITUTE(SUBSTITUTE(SUBSTITUTE(LOWER(G4),"á","a"),"é","e"),"í","i"),"ó","o"),"ú","u"),"ñ","n"),"-"," "),","," "),"."," ")) -> sipi | AP4: =TRIM(SUBSTITUTE(SUBSTITUTE(SUBSTITUTE(SUBSTITUTE(SUBSTITUTE(SUBSTITUTE(SUBSTITUTE(SUBSTITUTE(SUBSTITUTE(LOWER(B4),"á","a"),"é","e"),"í","i"),"ó","o"),"ú","u"),"ñ","n"),"-"," "),","," "),"."," ")) -> choco | AQ4: =COUNTIF($AO$2:$AO$433,AO4)>COUNTIFS($AO$2:$AO$433,AO4,$AP$2:$AP$433,AP4) -> FALSE | AR4: =IF(AQ4,AO4&"|"&AP4,AO4) -> sipi | AS4: =(I4<>"#N/D")+(J4<>"#N/D")+(L4<>"#N/D") -> 0 | AT4: =SUM(O4:X4) -> 8 | AU4: =IF(AT4<=$AY$2,0,IF(AT4<=$AY$3,1,IF(AT4<=$AY$4,2,3))) -> 3 | AV4: =IF(Y4<=$AY$7,3,IF(Y4<=$AY$8,2,IF(Y4<=$AY$9,1,0))) -> 3 | AX4: Q1 (25%) | AY4: =_xlfn.QUARTILE.INC($Y$2:$Y$433,1) -> 0 | AZ4: =IF(Y4=0,3,0) -> 3 | BA4: =AS4+AU4+AZ4 -> 6 | BB4: =IFERROR(INDEX('Análisis general'!$E$4:$E$28,MATCH($B4,'Análisis general'!$B$4:$B$28,0)),"") -> 30.8 | BC4: =IF(BB4="","",IF(BB4<=$BG$2,0,IF(BB4<=$BG$3,1,IF(BB4<=$BG$4,2,3)))) -> 3 | BD4: =(AS4+AU4+AZ4+(BC4/2))*(9/10.5) -> 6.4285714 | BE4: =(AU4+AZ4+(BC4/2))*(9/7.5) -> 9
A5: 19318 | B5: Cauca | C5: Sin clasificación oficial | D5: =AS5+AU5+AV5 -> 6 | E5: =BD5 -> 6.4285714 | F5: =BE5 -> 9 | G5: Guapi | H5: =IFERROR(IF($AQ5,INDEX(cpe!$C$2:$C$307,MATCH($AR5,cpe!$F$2:$F$307,0)),INDEX(cpe!$C$2:$C$307,MATCH($AR5,cpe!$D$2:$D$307,0))),"#N/D") -> #N/D | I5: =IFERROR(IF($AQ5,INDEX(cpe!$B$2:$B$307,MATCH($AR5,cpe!$F$2:$F$307,0)),INDEX(cpe!$B$2:$B$307,MATCH($AR5,cpe!$D$2:$D$307,0))),"#N/D") -> #N/D | J5: =IF($AQ5,"#N/D",IFERROR(INDEX(Olimpiadas!$B$2:$B$61,MATCH($AO5,Olimpiadas!$C$2:$C$61,0)),"#N/D")) -> #N/D | K5: =IF($AQ5,"#N/D",IFERROR(INDEX(Olimpiadas!$A$2:$A$61,MATCH($AO5,Olimpiadas!$C$2:$C$61,0)),"#N/D")) -> #N/D | L5: =IF($AQ5,"#N/D",IFERROR(INDEX(Minculturas!$A$2:$A$48,MATCH($AO5,Minculturas!$C$2:$C$48,0)),"#N/D")) -> #N/D | M5: =IF($AQ5,"#N/D",IFERROR(INDEX(Minculturas!$B$2:$B$48,MATCH($AO5,Minculturas!$C$2:$C$48,0)),"#N/D")) -> #N/D | N5: 6 | O5: 0 | P5: 0 | Q5: 1 | R5: 0 | S5: 5 | T5: 0 | U5: 0 | V5: 0 | W5: 0 | X5: 0 | Y5: 0 | Z5: 0 | AA5: 0 | AB5: 0 | AC5: 0 | AD5: 0 | AE5: 0 | AF5: 0 | AG5: =SUM(O5:X5) -> 6 | AJ5: 68.9 | AM5: Declarado afectado; sin lugar con nombre propio publicado en este registro. | AO5: =TRIM(SUBSTITUTE(SUBSTITUTE(SUBSTITUTE(SUBSTITUTE(SUBSTITUTE(SUBSTITUTE(SUBSTITUTE(SUBSTITUTE(SUBSTITUTE(LOWER(G5),"á","a"),"é","e"),"í","i"),"ó","o"),"ú","u"),"ñ","n"),"-"," "),","," "),"."," ")) -> guapi | AP5: =TRIM(SUBSTITUTE(SUBSTITUTE(SUBSTITUTE(SUBSTITUTE(SUBSTITUTE(SUBSTITUTE(SUBSTITUTE(SUBSTITUTE(SUBSTITUTE(LOWER(B5),"á","a"),"é","e"),"í","i"),"ó","o"),"ú","u"),"ñ","n"),"-"," "),","," "),"."," ")) -> cauca | AQ5: =COUNTIF($AO$2:$AO$433,AO5)>COUNTIFS($AO$2:$AO$433,AO5,$AP$2:$AP$433,AP5) -> FALSE | AR5: =IF(AQ5,AO5&"|"&AP5,AO5) -> guapi | AS5: =(I5<>"#N/D")+(J5<>"#N/D")+(L5<>"#N/D") -> 0 | AT5: =SUM(O5:X5) -> 6 | AU5: =IF(AT5<=$AY$2,0,IF(AT5<=$AY$3,1,IF(AT5<=$AY$4,2,3))) -> 3 | AV5: =IF(Y5<=$AY$7,3,IF(Y5<=$AY$8,2,IF(Y5<=$AY$9,1,0))) -> 3 | AX5: Q1 (25%) | AY5: =_xlfn.QUARTILE.INC($Y$2:$Y$433,1) -> 0 | AZ5: =IF(Y5=0,3,0) -> 3 | BA5: =AS5+AU5+AZ5 -> 6 | BB5: =IFERROR(INDEX('Análisis general'!$E$4:$E$28,MATCH($B5,'Análisis general'!$B$4:$B$28,0)),"") -> 13 | BC5: =IF(BB5="","",IF(BB5<=$BG$2,0,IF(BB5<=$BG$3,1,IF(BB5<=$BG$4,2,3)))) -> 3 | BD5: =(AS5+AU5+AZ5+(BC5/2))*(9/10.5) -> 6.4285714 | BE5: =(AU5+AZ5+(BC5/2))*(9/7.5) -> 9
A6: 27205 | B6: Chocó | C6: Sin clasificación oficial | D6: =AS6+AU6+AV6 -> 6 | E6: =BD6 -> 6.4285714 | F6: =BE6 -> 9 | G6: Condoto | H6: =IFERROR(IF($AQ6,INDEX(cpe!$C$2:$C$307,MATCH($AR6,cpe!$F$2:$F$307,0)),INDEX(cpe!$C$2:$C$307,MATCH($AR6,cpe!$D$2:$D$307,0))),"#N/D") -> #N/D | I6: =IFERROR(IF($AQ6,INDEX(cpe!$B$2:$B$307,MATCH($AR6,cpe!$F$2:$F$307,0)),INDEX(cpe!$B$2:$B$307,MATCH($AR6,cpe!$D$2:$D$307,0))),"#N/D") -> #N/D | J6: =IF($AQ6,"#N/D",IFERROR(INDEX(Olimpiadas!$B$2:$B$61,MATCH($AO6,Olimpiadas!$C$2:$C$61,0)),"#N/D")) -> #N/D | K6: =IF($AQ6,"#N/D",IFERROR(INDEX(Olimpiadas!$A$2:$A$61,MATCH($AO6,Olimpiadas!$C$2:$C$61,0)),"#N/D")) -> #N/D | L6: =IF($AQ6,"#N/D",IFERROR(INDEX(Minculturas!$A$2:$A$48,MATCH($AO6,Minculturas!$C$2:$C$48,0)),"#N/D")) -> #N/D | M6: =IF($AQ6,"#N/D",IFERROR(INDEX(Minculturas!$B$2:$B$48,MATCH($AO6,Minculturas!$C$2:$C$48,0)),"#N/D")) -> #N/D | N6: 5 | O6: 0 | P6: 2 | Q6: 0 | R6: 0 | S6: 0 | T6: 0 | U6: 1 | V6: 1 | W6: 0 | X6: 1 | Y6: 0 | Z6: 0 | AA6: 0 | AB6: 0 | AC6: 0 | AD6: 0 | AE6: 0 | AF6: 0 | AG6: =SUM(O6:X6) -> 5 | AH6: 998 | AI6: 2888 | AJ6: 53.2 | AM6: Declarado afectado; sin lugar con nombre propio publicado en este registro. | AO6: =TRIM(SUBSTITUTE(SUBSTITUTE(SUBSTITUTE(SUBSTITUTE(SUBSTITUTE(SUBSTITUTE(SUBSTITUTE(SUBSTITUTE(SUBSTITUTE(LOWER(G6),"á","a"),"é","e"),"í","i"),"ó","o"),"ú","u"),"ñ","n"),"-"," "),","," "),"."," ")) -> condoto | AP6: =TRIM(SUBSTITUTE(SUBSTITUTE(SUBSTITUTE(SUBSTITUTE(SUBSTITUTE(SUBSTITUTE(SUBSTITUTE(SUBSTITUTE(SUBSTITUTE(LOWER(B6),"á","a"),"é","e"),"í","i"),"ó","o"),"ú","u"),"ñ","n"),"-"," "),","," "),"."," ")) -> choco | AQ6: =COUNTIF($AO$2:$AO$433,AO6)>COUNTIFS($AO$2:$AO$433,AO6,$AP$2:$AP$433,AP6) -> FALSE | AR6: =IF(AQ6,AO6&"|"&AP6,AO6) -> condoto | AS6: =(I6<>"#N/D")+(J6<>"#N/D")+(L6<>"#N/D") -> 0 | AT6: =SUM(O6:X6) -> 5 | AU6: =IF(AT6<=$AY$2,0,IF(AT6<=$AY$3,1,IF(AT6<=$AY$4,2,3))) -> 3 | AV6: =IF(Y6<=$AY$7,3,IF(Y6<=$AY$8,2,IF(Y6<=$AY$9,1,0))) -> 3 | AX6: Q3 (75%) | AY6: =_xlfn.QUARTILE.INC($Y$2:$Y$433,3) -> 1 | AZ6: =IF(Y6=0,3,0) -> 3 | BA6: =AS6+AU6+AZ6 -> 6 | BB6: =IFERROR(INDEX('Análisis general'!$E$4:$E$28,MATCH($B6,'Análisis general'!$B$4:$B$28,0)),"") -> 30.8 | BC6: =IF(BB6="","",IF(BB6<=$BG$2,0,IF(BB6<=$BG$3,1,IF(BB6<=$BG$4,2,3)))) -> 3 | BD6: =(AS6+AU6+AZ6+(BC6/2))*(9/10.5) -> 6.4285714 | BE6: =(AU6+AZ6+(BC6/2))*(9/7.5) -> 9
A7: 27245 | B7: Chocó | C7: Sin clasificación oficial | D7: =AS7+AU7+AV7 -> 6 | E7: =BD7 -> 6.4285714 | F7: =BE7 -> 9 | G7: El Carmen de Atrato | H7: =IFERROR(IF($AQ7,INDEX(cpe!$C$2:$C$307,MATCH($AR7,cpe!$F$2:$F$307,0)),INDEX(cpe!$C$2:$C$307,MATCH($AR7,cpe!$D$2:$D$307,0))),"#N/D") -> #N/D | I7: =IFERROR(IF($AQ7,INDEX(cpe!$B$2:$B$307,MATCH($AR7,cpe!$F$2:$F$307,0)),INDEX(cpe!$B$2:$B$307,MATCH($AR7,cpe!$D$2:$D$307,0))),"#N/D") -> #N/D | J7: =IF($AQ7,"#N/D",IFERROR(INDEX(Olimpiadas!$B$2:$B$61,MATCH($AO7,Olimpiadas!$C$2:$C$61,0)),"#N/D")) -> #N/D | K7: =IF($AQ7,"#N/D",IFERROR(INDEX(Olimpiadas!$A$2:$A$61,MATCH($AO7,Olimpiadas!$C$2:$C$61,0)),"#N/D")) -> #N/D | L7: =IF($AQ7,"#N/D",IFERROR(INDEX(Minculturas!$A$2:$A$48,MATCH($AO7,Minculturas!$C$2:$C$48,0)),"#N/D")) -> #N/D | M7: =IF($AQ7,"#N/D",IFERROR(INDEX(Minculturas!$B$2:$B$48,MATCH($AO7,Minculturas!$C$2:$C$48,0)),"#N/D")) -> #N/D | N7: 5 | O7: 0 | P7: 0 | Q7: 0 | R7: 1 | S7: 0 | T7: 0 | U7: 2 | V7: 1 | W7: 0 | X7: 1 | Y7: 0 | Z7: 0 | AA7: 0 | AB7: 0 | AC7: 0 | AD7: 0 | AE7: 0 | AF7: 0 | AG7: =SUM(O7:X7) -> 5 | AH7: 202 | AI7: 246 | AJ7: 54 | AM7: Declarado afectado; sin lugar con nombre propio publicado en este registro. | AO7: =TRIM(SUBSTITUTE(SUBSTITUTE(SUBSTITUTE(SUBSTITUTE(SUBSTITUTE(SUBSTITUTE(SUBSTITUTE(SUBSTITUTE(SUBSTITUTE(LOWER(G7),"á","a"),"é","e"),"í","i"),"ó","o"),"ú","u"),"ñ","n"),"-"," "),","," "),"."," ")) -> el carmen de atrato | AP7: =TRIM(SUBSTITUTE(SUBSTITUTE(SUBSTITUTE(SUBSTITUTE(SUBSTITUTE(SUBSTITUTE(SUBSTITUTE(SUBSTITUTE(SUBSTITUTE(LOWER(B7),"á","a"),"é","e"),"í","i"),"ó","o"),"ú","u"),"ñ","n"),"-"," "),","," "),"."," ")) -> choco | AQ7: =COUNTIF($AO$2:$AO$433,AO7)>COUNTIFS($AO$2:$AO$433,AO7,$AP$2:$AP$433,AP7) -> FALSE | AR7: =IF(AQ7,AO7&"|"&AP7,AO7) -> el carmen de atrato | AS7: =(I7<>"#N/D")+(J7<>"#N/D")+(L7<>"#N/D") -> 0 | AT7: =SUM(O7:X7) -> 5 | AU7: =IF(AT7<=$AY$2,0,IF(AT7<=$AY$3,1,IF(AT7<=$AY$4,2,3))) -> 3 | AV7: =IF(Y7<=$AY$7,3,IF(Y7<=$AY$8,2,IF(Y7<=$AY$9,1,0))) -> 3 | AZ7: =IF(Y7=0,3,0) -> 3 | BA7: =AS7+AU7+AZ7 -> 6 | BB7: =IFERROR(INDEX('Análisis general'!$E$4:$E$28,MATCH($B7,'Análisis general'!$B$4:$B$28,0)),"") -> 30.8 | BC7: =IF(BB7="","",IF(BB7<=$BG$2,0,IF(BB7<=$BG$3,1,IF(BB7<=$BG$4,2,3)))) -> 3 | BD7: =(AS7+AU7+AZ7+(BC7/2))*(9/10.5) -> 6.4285714 | BE7: =(AU7+AZ7+(BC7/2))*(9/7.5) -> 9
A8: 41298 | B8: Huila | C8: Sin clasificación oficial | D8: =AS8+AU8+AV8 -> 8 | E8: =BD8 -> 8.1428571 | F8: =BE8 -> 9 | G8: Garzón | H8: =IFERROR(IF($AQ8,INDEX(cpe!$C$2:$C$307,MATCH($AR8,cpe!$F$2:$F$307,0)),INDEX(cpe!$C$2:$C$307,MATCH($AR8,cpe!$D$2:$D$307,0))),"#N/D") -> Centro Etnoeducativo No. 21 Aralia | I8: =IFERROR(IF($AQ8,INDEX(cpe!$B$2:$B$307,MATCH($AR8,cpe!$F$2:$F$307,0)),INDEX(cpe!$B$2:$B$307,MATCH($AR8,cpe!$D$2:$D$307,0))),"#N/D") -> Garzón | J8: =IF($AQ8,"#N/D",IFERROR(INDEX(Olimpiadas!$B$2:$B$61,MATCH($AO8,Olimpiadas!$C$2:$C$61,0)),"#N/D")) -> Garzón | K8: =IF($AQ8,"#N/D",IFERROR(INDEX(Olimpiadas!$A$2:$A$61,MATCH($AO8,Olimpiadas!$C$2:$C$61,0)),"#N/D")) -> INSTITUCIÓN EDUCATIVA TULIO ARBELÁEZ | L8: =IF($AQ8,"#N/D",IFERROR(INDEX(Minculturas!$A$2:$A$48,MATCH($AO8,Minculturas!$C$2:$C$48,0)),"#N/D")) -> #N/D | M8: =IF($AQ8,"#N/D",IFERROR(INDEX(Minculturas!$B$2:$B$48,MATCH($AO8,Minculturas!$C$2:$C$48,0)),"#N/D")) -> #N/D | N8: 5 | O8: 0 | P8: 1 | Q8: 0 | R8: 0 | S8: 4 | T8: 0 | U8: 0 | V8: 0 | W8: 0 | X8: 0 | Y8: 0 | Z8: 0 | AA8: 0 | AB8: 0 | AC8: 0 | AD8: 0 | AE8: 0 | AF8: 0 | AG8: =SUM(O8:X8) -> 5 | AJ8: 32 | AM8: Declarado afectado; sin lugar con nombre propio publicado en este registro. | AO8: =TRIM(SUBSTITUTE(SUBSTITUTE(SUBSTITUTE(SUBSTITUTE(SUBSTITUTE(SUBSTITUTE(SUBSTITUTE(SUBSTITUTE(SUBSTITUTE(LOWER(G8),"á","a"),"é","e"),"í","i"),"ó","o"),"ú","u"),"ñ","n"),"-"," "),","," "),"."," ")) -> garzon | AP8: =TRIM(SUBSTITUTE(SUBSTITUTE(SUBSTITUTE(SUBSTITUTE(SUBSTITUTE(SUBSTITUTE(SUBSTITUTE(SUBSTITUTE(SUBSTITUTE(LOWER(B8),"á","a"),"é","e"),"í","i"),"ó","o"),"ú","u"),"ñ","n"),"-"," "),","," "),"."," ")) -> huila | AQ8: =COUNTIF($AO$2:$AO$433,AO8)>COUNTIFS($AO$2:$AO$433,AO8,$AP$2:$AP$433,AP8) -> FALSE | AR8: =IF(AQ8,AO8&"|"&AP8,AO8) -> garzon | AS8: =(I8<>"#N/D")+(J8<>"#N/D")+(L8<>"#N/D") -> 2 | AT8: =SUM(O8:X8) -> 5 | AU8: =IF(AT8<=$AY$2,0,IF(AT8<=$AY$3,1,IF(AT8<=$AY$4,2,3))) -> 3 | AV8: =IF(Y8<=$AY$7,3,IF(Y8<=$AY$8,2,IF(Y8<=$AY$9,1,0))) -> 3 | AX8: Q2 (50%) | AY8: =_xlfn.QUARTILE.INC($AT$2:$AT$433,1) -> 0 | AZ8: =IF(Y8=0,3,0) -> 3 | BA8: =AS8+AU8+AZ8 -> 8 | BB8: =IFERROR(INDEX('Análisis general'!$E$4:$E$28,MATCH($B8,'Análisis general'!$B$4:$B$28,0)),"") -> 9.7 | BC8: =IF(BB8="","",IF(BB8<=$BG$2,0,IF(BB8<=$BG$3,1,IF(BB8<=$BG$4,2,3)))) -> 3 | BD8: =(AS8+AU8+AZ8+(BC8/2))*(9/10.5) -> 8.1428571 | BE8: =(AU8+AZ8+(BC8/2))*(9/7.5) -> 9 | BF8: Q1 (25%) | BG8: =_xlfn.QUARTILE.INC($BB$2:$BB$433,1) -> 4.9
A9: 41396 | B9: Huila | C9: Sin clasificación oficial | D9: =AS9+AU9+AV9 -> 8 | E9: =BD9 -> 8.1428571 | F9: =BE9 -> 9 | G9: La Plata | H9: =IFERROR(IF($AQ9,INDEX(cpe!$C$2:$C$307,MATCH($AR9,cpe!$F$2:$F$307,0)),INDEX(cpe!$C$2:$C$307,MATCH($AR9,cpe!$D$2:$D$307,0))),"#N/D") -> Institucion Educativa Zaragoza Tamarindo | I9: =IFERROR(IF($AQ9,INDEX(cpe!$B$2:$B$307,MATCH($AR9,cpe!$F$2:$F$307,0)),INDEX(cpe!$B$2:$B$307,MATCH($AR9,cpe!$D$2:$D$307,0))),"#N/D") -> La Plata | J9: =IF($AQ9,"#N/D",IFERROR(INDEX(Olimpiadas!$B$2:$B$61,MATCH($AO9,Olimpiadas!$C$2:$C$61,0)),"#N/D")) -> La Plata | K9: =IF($AQ9,"#N/D",IFERROR(INDEX(Olimpiadas!$A$2:$A$61,MATCH($AO9,Olimpiadas!$C$2:$C$61,0)),"#N/D")) -> INSTITUCIÓN EDUCATIVA EL CARMELO | L9: =IF($AQ9,"#N/D",IFERROR(INDEX(Minculturas!$A$2:$A$48,MATCH($AO9,Minculturas!$C$2:$C$48,0)),"#N/D")) -> #N/D | M9: =IF($AQ9,"#N/D",IFERROR(INDEX(Minculturas!$B$2:$B$48,MATCH($AO9,Minculturas!$C$2:$C$48,0)),"#N/D")) -> #N/D | N9: 5 | O9: 0 | P9: 0 | Q9: 3 | R9: 0 | S9: 2 | T9: 0 | U9: 0 | V9: 0 | W9: 0 | X9: 0 | Y9: 0 | Z9: 0 | AA9: 0 | AB9: 0 | AC9: 0 | AD9: 0 | AE9: 0 | AF9: 0 | AG9: =SUM(O9:X9) -> 5 | AH9: 16 | AI9: 39 | AJ9: 42.5 | AM9: Declarado afectado; sin lugar con nombre propio publicado en este registro. | AO9: =TRIM(SUBSTITUTE(SUBSTITUTE(SUBSTITUTE(SUBSTITUTE(SUBSTITUTE(SUBSTITUTE(SUBSTITUTE(SUBSTITUTE(SUBSTITUTE(LOWER(G9),"á","a"),"é","e"),"í","i"),"ó","o"),"ú","u"),"ñ","n"),"-"," "),","," "),"."," ")) -> la plata | AP9: =TRIM(SUBSTITUTE(SUBSTITUTE(SUBSTITUTE(SUBSTITUTE(SUBSTITUTE(SUBSTITUTE(SUBSTITUTE(SUBSTITUTE(SUBSTITUTE(LOWER(B9),"á","a"),"é","e"),"í","i"),"ó","o"),"ú","u"),"ñ","n"),"-"," "),","," "),"."," ")) -> huila | AQ9: =COUNTIF($AO$2:$AO$433,AO9)>COUNTIFS($AO$2:$AO$433,AO9,$AP$2:$AP$433,AP9) -> FALSE | AR9: =IF(AQ9,AO9&"|"&AP9,AO9) -> la plata | AS9: =(I9<>"#N/D")+(J9<>"#N/D")+(L9<>"#N/D") -> 2 | AT9: =SUM(O9:X9) -> 5 | AU9: =IF(AT9<=$AY$2,0,IF(AT9<=$AY$3,1,IF(AT9<=$AY$4,2,3))) -> 3 | AV9: =IF(Y9<=$AY$7,3,IF(Y9<=$AY$8,2,IF(Y9<=$AY$9,1,0))) -> 3 | AX9: Q3 (75%) | AY9: =_xlfn.QUARTILE.INC($AT$2:$AT$433,2) -> 1 | AZ9: =IF(Y9=0,3,0) -> 3 | BA9: =AS9+AU9+AZ9 -> 8 | BB9: =IFERROR(INDEX('Análisis general'!$E$4:$E$28,MATCH($B9,'Análisis general'!$B$4:$B$28,0)),"") -> 9.7 | BC9: =IF(BB9="","",IF(BB9<=$BG$2,0,IF(BB9<=$BG$3,1,IF(BB9<=$BG$4,2,3)))) -> 3 | BD9: =(AS9+AU9+AZ9+(BC9/2))*(9/10.5) -> 8.1428571 | BE9: =(AU9+AZ9+(BC9/2))*(9/7.5) -> 9 | BF9: Q2 (50%) | BG9: =_xlfn.QUARTILE.INC($BB$2:$BB$433,2) -> 9.5
A10: 73124 | B10: Tolima | C10: Sin clasificación oficial | D10: =AS10+AU10+AV10 -> 7 | E10: =BD10 -> 7.2857143 | F10: =BE10 -> 9 | G10: Cajamarca | H10: =IFERROR(IF($AQ10,INDEX(cpe!$C$2:$C$307,MATCH($AR10,cpe!$F$2:$F$307,0)),INDEX(cpe!$C$2:$C$307,MATCH($AR10,cpe!$D$2:$D$307,0))),"#N/D") -> Institucion Educativa Distrital Jose Eusebio Caro Colcaro | I10: =IFERROR(IF($AQ10,INDEX(cpe!$B$2:$B$307,MATCH($AR10,cpe!$F$2:$F$307,0)),INDEX(cpe!$B$2:$B$307,MATCH($AR10,cpe!$D$2:$D$307,0))),"#N/D") -> Cajamarca | J10: =IF($AQ10,"#N/D",IFERROR(INDEX(Olimpiadas!$B$2:$B$61,MATCH($AO10,Olimpiadas!$C$2:$C$61,0)),"#N/D")) -> #N/D | K10: =IF($AQ10,"#N/D",IFERROR(INDEX(Olimpiadas!$A$2:$A$61,MATCH($AO10,Olimpiadas!$C$2:$C$61,0)),"#N/D")) -> #N/D | L10: =IF($AQ10,"#N/D",IFERROR(INDEX(Minculturas!$A$2:$A$48,MATCH($AO10,Minculturas!$C$2:$C$48,0)),"#N/D")) -> #N/D | M10: =IF($AQ10,"#N/D",IFERROR(INDEX(Minculturas!$B$2:$B$48,MATCH($AO10,Minculturas!$C$2:$C$48,0)),"#N/D")) -> #N/D | N10: 7 | O10: 0 | P10: 0 | Q10: 1 | R10: 0 | S10: 0 | T10: 1 | U10: 1 | V10: 2 | W10: 2 | X10: 0 | Y10: 0 | Z10: 0 | AA10: 0 | AB10: 0 | AC10: 0 | AD10: 0 | AE10: 0 | AF10: 0 | AG10: =SUM(O10:X10) -> 7 | AJ10: 36.2 | AM10: Declarado afectado; sin lugar con nombre propio publicado en este registro. | AO10: =TRIM(SUBSTITUTE(SUBSTITUTE(SUBSTITUTE(SUBSTITUTE(SUBSTITUTE(SUBSTITUTE(SUBSTITUTE(SUBSTITUTE(SUBSTITUTE(LOWER(G10),"á","a"),"é","e"),"í","i"),"ó","o"),"ú","u"),"ñ","n"),"-"," "),","," "),"."," ")) -> cajamarca | AP10: =TRIM(SUBSTITUTE(SUBSTITUTE(SUBSTITUTE(SUBSTITUTE(SUBSTITUTE(SUBSTITUTE(SUBSTITUTE(SUBSTITUTE(SUBSTITUTE(LOWER(B10),"á","a"),"é","e"),"í","i"),"ó","o"),"ú","u"),"ñ","n"),"-"," "),","," "),"."," ")) -> tolima | AQ10: =COUNTIF($AO$2:$AO$433,AO10)>COUNTIFS($AO$2:$AO$433,AO10,$AP$2:$AP$433,AP10) -> FALSE | AR10: =IF(AQ10,AO10&"|"&AP10,AO10) -> cajamarca | AS10: =(I10<>"#N/D")+(J10<>"#N/D")+(L10<>"#N/D") -> 1 | AT10: =SUM(O10:X10) -> 7 | AU10: =IF(AT10<=$AY$2,0,IF(AT10<=$AY$3,1,IF(AT10<=$AY$4,2,3))) -> 3 | AV10: =IF(Y10<=$AY$7,3,IF(Y10<=$AY$8,2,IF(Y10<=$AY$9,1,0))) -> 3 | AZ10: =IF(Y10=0,3,0) -> 3 | BA10: =AS10+AU10+AZ10 -> 7 | BB10: =IFERROR(INDEX('Análisis general'!$E$4:$E$28,MATCH($B10,'Análisis general'!$B$4:$B$28,0)),"") -> 12.2 | BC10: =IF(BB10="","",IF(BB10<=$BG$2,0,IF(BB10<=$BG$3,1,IF(BB10<=$BG$4,2,3)))) -> 3 | BD10: =(AS10+AU10+AZ10+(BC10/2))*(9/10.5) -> 7.2857143 | BE10: =(AU10+AZ10+(BC10/2))*(9/7.5) -> 9
A11: 73678 | B11: Tolima | C11: Sin clasificación oficial | D11: =AS11+AU11+AV11 -> 7 | E11: =BD11 -> 7.2857143 | F11: =BE11 -> 9 | G11: San Luis | H11: Institucion Ednoeducativa Tecnica Nasawe´sx Fi´zni | I11: San Luis | J11: #N/D | K11: =IF($AQ11,"#N/D",IFERROR(INDEX(Olimpiadas!$A$2:$A$61,MATCH($AO11,Olimpiadas!$C$2:$C$61,0)),"#N/D")) -> #N/D | L11: =IF($AQ11,"#N/D",IFERROR(INDEX(Minculturas!$A$2:$A$48,MATCH($AO11,Minculturas!$C$2:$C$48,0)),"#N/D")) -> #N/D | M11: =IF($AQ11,"#N/D",IFERROR(INDEX(Minculturas!$B$2:$B$48,MATCH($AO11,Minculturas!$C$2:$C$48,0)),"#N/D")) -> #N/D | N11: 5 | O11: 0 | P11: 0 | Q11: 1 | R11: 1 | S11: 2 | T11: 0 | U11: 0 | V11: 1 | W11: 0 | X11: 0 | Y11: 0 | Z11: 0 | AA11: 0 | AB11: 0 | AC11: 0 | AD11: 0 | AE11: 0 | AF11: 0 | AG11: =SUM(O11:X11) -> 5 | AJ11: 39.4 | AM11: Declarado afectado; sin lugar con nombre propio publicado en este registro. | AO11: =TRIM(SUBSTITUTE(SUBSTITUTE(SUBSTITUTE(SUBSTITUTE(SUBSTITUTE(SUBSTITUTE(SUBSTITUTE(SUBSTITUTE(SUBSTITUTE(LOWER(G11),"á","a"),"é","e"),"í","i"),"ó","o"),"ú","u"),"ñ","n"),"-"," "),","," "),"."," ")) -> san luis | AP11: =TRIM(SUBSTITUTE(SUBSTITUTE(SUBSTITUTE(SUBSTITUTE(SUBSTITUTE(SUBSTITUTE(SUBSTITUTE(SUBSTITUTE(SUBSTITUTE(LOWER(B11),"á","a"),"é","e"),"í","i"),"ó","o"),"ú","u"),"ñ","n"),"-"," "),","," "),"."," ")) -> tolima | AQ11: =COUNTIF($AO$2:$AO$433,AO11)>COUNTIFS($AO$2:$AO$433,AO11,$AP$2:$AP$433,AP11) -> TRUE | AR11: =IF(AQ11,AO11&"|"&AP11,AO11) -> san luis|tolima | AS11: =(I11<>"#N/D")+(J11<>"#N/D")+(L11<>"#N/D") -> 1 | AT11: =SUM(O11:X11) -> 5 | AU11: =IF(AT11<=$AY$2,0,IF(AT11<=$AY$3,1,IF(AT11<=$AY$4,2,3))) -> 3 | AV11: =IF(Y11<=$AY$7,3,IF(Y11<=$AY$8,2,IF(Y11<=$AY$9,1,0))) -> 3 | AZ11: =IF(Y11=0,3,0) -> 3 | BA11: =AS11+AU11+AZ11 -> 7 | BB11: =IFERROR(INDEX('Análisis general'!$E$4:$E$28,MATCH($B11,'Análisis general'!$B$4:$B$28,0)),"") -> 12.2 | BC11: =IF(BB11="","",IF(BB11<=$BG$2,0,IF(BB11<=$BG$3,1,IF(BB11<=$BG$4,2,3)))) -> 3 | BD11: =(AS11+AU11+AZ11+(BC11/2))*(9/10.5) -> 7.2857143 | BE11: =(AU11+AZ11+(BC11/2))*(9/7.5) -> 9
A12: 41799 | B12: Huila | C12: Sin clasificación oficial | D12: =AS12+AU12+AV12 -> 6 | E12: =BD12 -> 6.4285714 | F12: =BE12 -> 9 | G12: Tello | H12: #N/D | I12: #N/D | J12: #N/D | K12: =IF($AQ12,"#N/D",IFERROR(INDEX(Olimpiadas!$A$2:$A$61,MATCH($AO12,Olimpiadas!$C$2:$C$61,0)),"#N/D")) -> #N/D | L12: =IF($AQ12,"#N/D",IFERROR(INDEX(Minculturas!$A$2:$A$48,MATCH($AO12,Minculturas!$C$2:$C$48,0)),"#N/D")) -> #N/D | M12: =IF($AQ12,"#N/D",IFERROR(INDEX(Minculturas!$B$2:$B$48,MATCH($AO12,Minculturas!$C$2:$C$48,0)),"#N/D")) -> #N/D | N12: 8 | O12: 0 | P12: 0 | Q12: 2 | R12: 1 | S12: 4 | T12: 0 | U12: 0 | V12: 1 | W12: 0 | X12: 0 | Y12: 0 | Z12: 0 | AA12: 0 | AB12: 0 | AC12: 0 | AD12: 0 | AE12: 0 | AF12: 0 | AG12: =SUM(O12:X12) -> 8 | AH12: 23 | AI12: 58 | AJ12: 44.5 | AM12: Declarado afectado; sin lugar con nombre propio publicado en este registro. | AO12: =TRIM(SUBSTITUTE(SUBSTITUTE(SUBSTITUTE(SUBSTITUTE(SUBSTITUTE(SUBSTITUTE(SUBSTITUTE(SUBSTITUTE(SUBSTITUTE(LOWER(G12),"á","a"),"é","e"),"í","i"),"ó","o"),"ú","u"),"ñ","n"),"-"," "),","," "),"."," ")) -> tello | AP12: =TRIM(SUBSTITUTE(SUBSTITUTE(SUBSTITUTE(SUBSTITUTE(SUBSTITUTE(SUBSTITUTE(SUBSTITUTE(SUBSTITUTE(SUBSTITUTE(LOWER(B12),"á","a"),"é","e"),"í","i"),"ó","o"),"ú","u"),"ñ","n"),"-"," "),","," "),"."," ")) -> huila | AQ12: =COUNTIF($AO$2:$AO$433,AO12)>COUNTIFS($AO$2:$AO$433,AO12,$AP$2:$AP$433,AP12) -> FALSE | AR12: =IF(AQ12,AO12&"|"&AP12,AO12) -> tello | AS12: =(I12<>"#N/D")+(J12<>"#N/D")+(L12<>"#N/D") -> 0 | AT12: =SUM(O12:X12) -> 8 | AU12: =IF(AT12<=$AY$2,0,IF(AT12<=$AY$3,1,IF(AT12<=$AY$4,2,3))) -> 3 | AV12: =IF(Y12<=$AY$7,3,IF(Y12<=$AY$8,2,IF(Y12<=$AY$9,1,0))) -> 3 | AZ12: =IF(Y12=0,3,0) -> 3 | BA12: =AS12+AU12+AZ12 -> 6 | BB12: =IFERROR(INDEX('Análisis general'!$E$4:$E$28,MATCH($B12,'Análisis general'!$B$4:$B$28,0)),"") -> 9.7 | BC12: =IF(BB12="","",IF(BB12<=$BG$2,0,IF(BB12<=$BG$3,1,IF(BB12<=$BG$4,2,3)))) -> 3 | BD12: =(AS12+AU12+AZ12+(BC12/2))*(9/10.5) -> 6.4285714 | BE12: =(AU12+AZ12+(BC12/2))*(9/7.5) -> 9
A13: 41078 | B13: Huila | C13: Sin clasificación oficial | D13: =AS13+AU13+AV13 -> 6 | E13: =BD13 -> 6.4285714 | F13: =BE13 -> 9 | G13: Baraya | H13: =IFERROR(IF($AQ13,INDEX(cpe!$C$2:$C$307,MATCH($AR13,cpe!$F$2:$F$307,0)),INDEX(cpe!$C$2:$C$307,MATCH($AR13,cpe!$D$2:$D$307,0))),"#N/D") -> #N/D | I13: =IFERROR(IF($AQ13,INDEX(cpe!$B$2:$B$307,MATCH($AR13,cpe!$F$2:$F$307,0)),INDEX(cpe!$B$2:$B$307,MATCH($AR13,cpe!$D$2:$D$307,0))),"#N/D") -> #N/D | J13: =IF($AQ13,"#N/D",IFERROR(INDEX(Olimpiadas!$B$2:$B$61,MATCH($AO13,Olimpiadas!$C$2:$C$61,0)),"#N/D")) -> #N/D | K13: =IF($AQ13,"#N/D",IFERROR(INDEX(Olimpiadas!$A$2:$A$61,MATCH($AO13,Olimpiadas!$C$2:$C$61,0)),"#N/D")) -> #N/D | L13: =IF($AQ13,"#N/D",IFERROR(INDEX(Minculturas!$A$2:$A$48,MATCH($AO13,Minculturas!$C$2:$C$48,0)),"#N/D")) -> #N/D | M13: =IF($AQ13,"#N/D",IFERROR(INDEX(Minculturas!$B$2:$B$48,MATCH($AO13,Minculturas!$C$2:$C$48,0)),"#N/D")) -> #N/D | N13: 5 | O13: 0 | P13: 1 | Q13: 0 | R13: 1 | S13: 3 | T13: 0 | U13: 0 | V13: 0 | W13: 0 | X13: 0 | Y13: 0 | Z13: 0 | AA13: 0 | AB13: 0 | AC13: 0 | AD13: 0 | AE13: 0 | AF13: 0 | AG13: =SUM(O13:X13) -> 5 | AJ13: 49.4 | AM13: Declarado afectado; sin lugar con nombre propio publicado en este registro. | AO13: =TRIM(SUBSTITUTE(SUBSTITUTE(SUBSTITUTE(SUBSTITUTE(SUBSTITUTE(SUBSTITUTE(SUBSTITUTE(SUBSTITUTE(SUBSTITUTE(LOWER(G13),"á","a"),"é","e"),"í","i"),"ó","o"),"ú","u"),"ñ","n"),"-"," "),","," "),"."," ")) -> baraya | AP13: =TRIM(SUBSTITUTE(SUBSTITUTE(SUBSTITUTE(SUBSTITUTE(SUBSTITUTE(SUBSTITUTE(SUBSTITUTE(SUBSTITUTE(SUBSTITUTE(LOWER(B13),"á","a"),"é","e"),"í","i"),"ó","o"),"ú","u"),"ñ","n"),"-"," "),","," "),"."," ")) -> huila | AQ13: =COUNTIF($AO$2:$AO$433,AO13)>COUNTIFS($AO$2:$AO$433,AO13,$AP$2:$AP$433,AP13) -> FALSE | AR13: =IF(AQ13,AO13&"|"&AP13,AO13) -> baraya | AS13: =(I13<>"#N/D")+(J13<>"#N/D")+(L13<>"#N/D") -> 0 | AT13: =SUM(O13:X13) -> 5 | AU13: =IF(AT13<=$AY$2,0,IF(AT13<=$AY$3,1,IF(AT13<=$AY$4,2,3))) -> 3 | AV13: =IF(Y13<=$AY$7,3,IF(Y13<=$AY$8,2,IF(Y13<=$AY$9,1,0))) -> 3 | AZ13: =IF(Y13=0,3,0) -> 3 | BA13: =AS13+AU13+AZ13 -> 6 | BB13: =IFERROR(INDEX('Análisis general'!$E$4:$E$28,MATCH($B13,'Análisis general'!$B$4:$B$28,0)),"") -> 9.7 | BC13: =IF(BB13="","",IF(BB13<=$BG$2,0,IF(BB13<=$BG$3,1,IF(BB13<=$BG$4,2,3)))) -> 3 | BD13: =(AS13+AU13+AZ13+(BC13/2))*(9/10.5) -> 6.4285714 | BE13: =(AU13+AZ13+(BC13/2))*(9/7.5) -> 9
A14: 52835 | B14: Nariño | C14: Sin clasificación oficial | D14: =AS14+AU14+AV14 -> 8 | E14: =BD14 -> 8.1428571 | F14: =BE14 -> 9 | G14: Tumaco | H14: Institucion Educativa Ana Elisa Cuenca Lara | I14: Tumaco | J14: Tumaco | K14: =IF($AQ14,"#N/D",IFERROR(INDEX(Olimpiadas!$A$2:$A$61,MATCH($AO14,Olimpiadas!$C$2:$C$61,0)),"#N/D")) -> INSTITUCIÓN EDUCATIVA SANTA TERESITA | L14: =IF($AQ14,"#N/D",IFERROR(INDEX(Minculturas!$A$2:$A$48,MATCH($AO14,Minculturas!$C$2:$C$48,0)),"#N/D")) -> #N/D | M14: =IF($AQ14,"#N/D",IFERROR(INDEX(Minculturas!$B$2:$B$48,MATCH($AO14,Minculturas!$C$2:$C$48,0)),"#N/D")) -> #N/D | N14: 3 | O14: 0 | P14: 2 | Q14: 0 | R14: 0 | S14: 0 | T14: 0 | U14: 1 | V14: 0 | W14: 0 | X14: 0 | Y14: 0 | Z14: 0 | AA14: 0 | AB14: 0 | AC14: 0 | AD14: 0 | AE14: 0 | AF14: 0 | AG14: =SUM(O14:X14) -> 3 | AJ14: 53.7 | AM14: Declarado afectado; sin lugar con nombre propio publicado en este registro. | AO14: =TRIM(SUBSTITUTE(SUBSTITUTE(SUBSTITUTE(SUBSTITUTE(SUBSTITUTE(SUBSTITUTE(SUBSTITUTE(SUBSTITUTE(SUBSTITUTE(LOWER(G14),"á","a"),"é","e"),"í","i"),"ó","o"),"ú","u"),"ñ","n"),"-"," "),","," "),"."," ")) -> tumaco | AP14: =TRIM(SUBSTITUTE(SUBSTITUTE(SUBSTITUTE(SUBSTITUTE(SUBSTITUTE(SUBSTITUTE(SUBSTITUTE(SUBSTITUTE(SUBSTITUTE(LOWER(B14),"á","a"),"é","e"),"í","i"),"ó","o"),"ú","u"),"ñ","n"),"-"," "),","," "),"."," ")) -> narino | AQ14: =COUNTIF($AO$2:$AO$433,AO14)>COUNTIFS($AO$2:$AO$433,AO14,$AP$2:$AP$433,AP14) -> FALSE | AR14: =IF(AQ14,AO14&"|"&AP14,AO14) -> tumaco | AS14: =(I14<>"#N/D")+(J14<>"#N/D")+(L14<>"#N/D") -> 2 | AT14: =SUM(O14:X14) -> 3 | AU14: =IF(AT14<=$AY$2,0,IF(AT14<=$AY$3,1,IF(AT14<=$AY$4,2,3))) -> 3 | AV14: =IF(Y14<=$AY$7,3,IF(Y14<=$AY$8,2,IF(Y14<=$AY$9,1,0))) -> 3 | AY14: =_xlfn.QUARTILE.INC($AT$2:$AT$433,3) -> 4 | AZ14: =IF(Y14=0,3,0) -> 3 | BA14: =AS14+AU14+AZ14 -> 8 | BB14: =IFERROR(INDEX('Análisis general'!$E$4:$E$28,MATCH($B14,'Análisis general'!$B$4:$B$28,0)),"") -> 13.2 | BC14: =IF(BB14="","",IF(BB14<=$BG$2,0,IF(BB14<=$BG$3,1,IF(BB14<=$BG$4,2,3)))) -> 3 | BD14: =(AS14+AU14+AZ14+(BC14/2))*(9/10.5) -> 8.1428571 | BE14: =(AU14+AZ14+(BC14/2))*(9/7.5) -> 9 | BF14: Q3 (75%) | BG14: =_xlfn.QUARTILE.INC($BB$2:$BB$433,3) -> 12.2
A15: 68081 | B15: Santander | C15: Sin clasificación oficial | D15: =AS15+AU15+AV15 -> 7 | E15: =BD15 -> 7.2857143 | F15: =BE15 -> 9 | G15: Barrancabermeja | H15: =IFERROR(IF($AQ15,INDEX(cpe!$C$2:$C$307,MATCH($AR15,cpe!$F$2:$F$307,0)),INDEX(cpe!$C$2:$C$307,MATCH($AR15,cpe!$D$2:$D$307,0))),"#N/D") -> Institucion Educativa Tecnica Maria Inmaculada de Pital de Megua | I15: =IFERROR(IF($AQ15,INDEX(cpe!$B$2:$B$307,MATCH($AR15,cpe!$F$2:$F$307,0)),INDEX(cpe!$B$2:$B$307,MATCH($AR15,cpe!$D$2:$D$307,0))),"#N/D") -> Barrancabermeja | J15: =IF($AQ15,"#N/D",IFERROR(INDEX(Olimpiadas!$B$2:$B$61,MATCH($AO15,Olimpiadas!$C$2:$C$61,0)),"#N/D")) -> #N/D | K15: =IF($AQ15,"#N/D",IFERROR(INDEX(Olimpiadas!$A$2:$A$61,MATCH($AO15,Olimpiadas!$C$2:$C$61,0)),"#N/D")) -> #N/D | L15: =IF($AQ15,"#N/D",IFERROR(INDEX(Minculturas!$A$2:$A$48,MATCH($AO15,Minculturas!$C$2:$C$48,0)),"#N/D")) -> #N/D | M15: =IF($AQ15,"#N/D",IFERROR(INDEX(Minculturas!$B$2:$B$48,MATCH($AO15,Minculturas!$C$2:$C$48,0)),"#N/D")) -> #N/D | N15: 16 | O15: 0 | P15: 2 | Q15: 5 | R15: 1 | S15: 8 | T15: 0 | U15: 0 | V15: 0 | W15: 0 | X15: 0 | Y15: 0 | Z15: 0 | AA15: 0 | AB15: 0 | AC15: 0 | AD15: 0 | AE15: 0 | AF15: 0 | AG15: =SUM(O15:X15) -> 16 | AJ15: 26.4 | AM15: Declarado afectado; sin lugar con nombre propio publicado en este registro. | AO15: =TRIM(SUBSTITUTE(SUBSTITUTE(SUBSTITUTE(SUBSTITUTE(SUBSTITUTE(SUBSTITUTE(SUBSTITUTE(SUBSTITUTE(SUBSTITUTE(LOWER(G15),"á","a"),"é","e"),"í","i"),"ó","o"),"ú","u"),"ñ","n"),"-"," "),","," "),"."," ")) -> barrancabermeja | AP15: =TRIM(SUBSTITUTE(SUBSTITUTE(SUBSTITUTE(SUBSTITUTE(SUBSTITUTE(SUBSTITUTE(SUBSTITUTE(SUBSTITUTE(SUBSTITUTE(LOWER(B15),"á","a"),"é","e"),"í","i"),"ó","o"),"ú","u"),"ñ","n"),"-"," "),","," "),"."," ")) -> santander | AQ15: =COUNTIF($AO$2:$AO$433,AO15)>COUNTIFS($AO$2:$AO$433,AO15,$AP$2:$AP$433,AP15) -> FALSE | AR15: =IF(AQ15,AO15&"|"&AP15,AO15) -> barrancabermeja | AS15: =(I15<>"#N/D")+(J15<>"#N/D")+(L15<>"#N/D") -> 1 | AT15: =SUM(O15:X15) -> 16 | AU15: =IF(AT15<=$AY$2,0,IF(AT15<=$AY$3,1,IF(AT15<=$AY$4,2,3))) -> 3 | AV15: =IF(Y15<=$AY$7,3,IF(Y15<=$AY$8,2,IF(Y15<=$AY$9,1,0))) -> 3 | AZ15: =IF(Y15=0,3,0) -> 3 | BA15: =AS15+AU15+AZ15 -> 7 | BB15: =IFERROR(INDEX('Análisis general'!$E$4:$E$28,MATCH($B15,'Análisis general'!$B$4:$B$28,0)),"") -> 6.9 | BC15: =IF(BB15="","",IF(BB15<=$BG$2,0,IF(BB15<=$BG$3,1,IF(BB15<=$BG$4,2,3)))) -> 3 | BD15: =(AS15+AU15+AZ15+(BC15/2))*(9/10.5) -> 7.2857143 | BE15: =(AU15+AZ15+(BC15/2))*(9/7.5) -> 9
A16: 63401 | B16: Quindío | C16: Sin clasificación oficial | D16: =AS16+AU16+AV16 -> 7 | E16: =BD16 -> 7.2857143 | F16: =BE16 -> 9 | G16: La Tebaida | H16: =IFERROR(IF($AQ16,INDEX(cpe!$C$2:$C$307,MATCH($AR16,cpe!$F$2:$F$307,0)),INDEX(cpe!$C$2:$C$307,MATCH($AR16,cpe!$D$2:$D$307,0))),"#N/D") -> Centro Educativo Puerto Lucas Margen Derecha | I16: =IFERROR(IF($AQ16,INDEX(cpe!$B$2:$B$307,MATCH($AR16,cpe!$F$2:$F$307,0)),INDEX(cpe!$B$2:$B$307,MATCH($AR16,cpe!$D$2:$D$307,0))),"#N/D") -> La Tebaida | J16: =IF($AQ16,"#N/D",IFERROR(INDEX(Olimpiadas!$B$2:$B$61,MATCH($AO16,Olimpiadas!$C$2:$C$61,0)),"#N/D")) -> #N/D | K16: =IF($AQ16,"#N/D",IFERROR(INDEX(Olimpiadas!$A$2:$A$61,MATCH($AO16,Olimpiadas!$C$2:$C$61,0)),"#N/D")) -> #N/D | L16: =IF($AQ16,"#N/D",IFERROR(INDEX(Minculturas!$A$2:$A$48,MATCH($AO16,Minculturas!$C$2:$C$48,0)),"#N/D")) -> #N/D | M16: =IF($AQ16,"#N/D",IFERROR(INDEX(Minculturas!$B$2:$B$48,MATCH($AO16,Minculturas!$C$2:$C$48,0)),"#N/D")) -> #N/D | N16: 13 | O16: 0 | P16: 3 | Q16: 2 | R16: 1 | S16: 0 | T16: 0 | U16: 4 | V16: 1 | W16: 0 | X16: 0 | Y16: 0 | Z16: 0 | AA16: 2 | AB16: 0 | AC16: 0 | AD16: 0 | AE16: 0 | AF16: 0 | AG16: =SUM(O16:X16) -> 11 | AH16: 64 | AI16: 204 | AJ16: 27.4 | AM16: Declarado afectado; sin lugar con nombre propio publicado en este registro. | AO16: =TRIM(SUBSTITUTE(SUBSTITUTE(SUBSTITUTE(SUBSTITUTE(SUBSTITUTE(SUBSTITUTE(SUBSTITUTE(SUBSTITUTE(SUBSTITUTE(LOWER(G16),"á","a"),"é","e"),"í","i"),"ó","o"),"ú","u"),"ñ","n"),"-"," "),","," "),"."," ")) -> la tebaida | AP16: =TRIM(SUBSTITUTE(SUBSTITUTE(SUBSTITUTE(SUBSTITUTE(SUBSTITUTE(SUBSTITUTE(SUBSTITUTE(SUBSTITUTE(SUBSTITUTE(LOWER(B16),"á","a"),"é","e"),"í","i"),"ó","o"),"ú","u"),"ñ","n"),"-"," "),","," "),"."," ")) -> quindio | AQ16: =COUNTIF($AO$2:$AO$433,AO16)>COUNTIFS($AO$2:$AO$433,AO16,$AP$2:$AP$433,AP16) -> FALSE | AR16: =IF(AQ16,AO16&"|"&AP16,AO16) -> la tebaida | AS16: =(I16<>"#N/D")+(J16<>"#N/D")+(L16<>"#N/D") -> 1 | AT16: =SUM(O16:X16) -> 11 | AU16: =IF(AT16<=$AY$2,0,IF(AT16<=$AY$3,1,IF(AT16<=$AY$4,2,3))) -> 3 | AV16: =IF(Y16<=$AY$7,3,IF(Y16<=$AY$8,2,IF(Y16<=$AY$9,1,0))) -> 3 | AZ16: =IF(Y16=0,3,0) -> 3 | BA16: =AS16+AU16+AZ16 -> 7 | BB16: =IFERROR(INDEX('Análisis general'!$E$4:$E$28,MATCH($B16,'Análisis general'!$B$4:$B$28,0)),"") -> 6.7 | BC16: =IF(BB16="","",IF(BB16<=$BG$2,0,IF(BB16<=$BG$3,1,IF(BB16<=$BG$4,2,3)))) -> 3 | BD16: =(AS16+AU16+AZ16+(BC16/2))*(9/10.5) -> 7.2857143 | BE16: =(AU16+AZ16+(BC16/2))*(9/7.5) -> 9
A17: 63272 | B17: Quindío | C17: Sin clasificación oficial | D17: =AS17+AU17+AV17 -> 7 | E17: =BD17 -> 7.2857143 | F17: =BE17 -> 9 | G17: Filandia | H17: =IFERROR(IF($AQ17,INDEX(cpe!$C$2:$C$307,MATCH($AR17,cpe!$F$2:$F$307,0)),INDEX(cpe!$C$2:$C$307,MATCH($AR17,cpe!$D$2:$D$307,0))),"#N/D") -> Inst Educ Tapias | I17: =IFERROR(IF($AQ17,INDEX(cpe!$B$2:$B$307,MATCH($AR17,cpe!$F$2:$F$307,0)),INDEX(cpe!$B$2:$B$307,MATCH($AR17,cpe!$D$2:$D$307,0))),"#N/D") -> Filandia | J17: =IF($AQ17,"#N/D",IFERROR(INDEX(Olimpiadas!$B$2:$B$61,MATCH($AO17,Olimpiadas!$C$2:$C$61,0)),"#N/D")) -> #N/D | K17: =IF($AQ17,"#N/D",IFERROR(INDEX(Olimpiadas!$A$2:$A$61,MATCH($AO17,Olimpiadas!$C$2:$C$61,0)),"#N/D")) -> #N/D | L17: =IF($AQ17,"#N/D",IFERROR(INDEX(Minculturas!$A$2:$A$48,MATCH($AO17,Minculturas!$C$2:$C$48,0)),"#N/D")) -> #N/D | M17: =IF($AQ17,"#N/D",IFERROR(INDEX(Minculturas!$B$2:$B$48,MATCH($AO17,Minculturas!$C$2:$C$48,0)),"#N/D")) -> #N/D | N17: 9 | O17: 0 | P17: 2 | Q17: 0 | R17: 0 | S17: 0 | T17: 2 | U17: 3 | V17: 2 | W17: 0 | X17: 0 | Y17: 0 | Z17: 0 | AA17: 0 | AB17: 0 | AC17: 0 | AD17: 0 | AE17: 0 | AF17: 0 | AG17: =SUM(O17:X17) -> 9 | AJ17: 18.1 | AM17: Declarado afectado; sin lugar con nombre propio publicado en este registro. | AO17: =TRIM(SUBSTITUTE(SUBSTITUTE(SUBSTITUTE(SUBSTITUTE(SUBSTITUTE(SUBSTITUTE(SUBSTITUTE(SUBSTITUTE(SUBSTITUTE(LOWER(G17),"á","a"),"é","e"),"í","i"),"ó","o"),"ú","u"),"ñ","n"),"-"," "),","," "),"."," ")) -> filandia | AP17: =TRIM(SUBSTITUTE(SUBSTITUTE(SUBSTITUTE(SUBSTITUTE(SUBSTITUTE(SUBSTITUTE(SUBSTITUTE(SUBSTITUTE(SUBSTITUTE(LOWER(B17),"á","a"),"é","e"),"í","i"),"ó","o"),"ú","u"),"ñ","n"),"-"," "),","," "),"."," ")) -> quindio | AQ17: =COUNTIF($AO$2:$AO$433,AO17)>COUNTIFS($AO$2:$AO$433,AO17,$AP$2:$AP$433,AP17) -> FALSE | AR17: =IF(AQ17,AO17&"|"&AP17,AO17) -> filandia | AS17: =(I17<>"#N/D")+(J17<>"#N/D")+(L17<>"#N/D") -> 1 | AT17: =SUM(O17:X17) -> 9 | AU17: =IF(AT17<=$AY$2,0,IF(AT17<=$AY$3,1,IF(AT17<=$AY$4,2,3))) -> 3 | AV17: =IF(Y17<=$AY$7,3,IF(Y17<=$AY$8,2,IF(Y17<=$AY$9,1,0))) -> 3 | AZ17: =IF(Y17=0,3,0) -> 3 | BA17: =AS17+AU17+AZ17 -> 7 | BB17: =IFERROR(INDEX('Análisis general'!$E$4:$E$28,MATCH($B17,'Análisis general'!$B$4:$B$28,0)),"") -> 6.7 | BC17: =IF(BB17="","",IF(BB17<=$BG$2,0,IF(BB17<=$BG$3,1,IF(BB17<=$BG$4,2,3)))) -> 3 | BD17: =(AS17+AU17+AZ17+(BC17/2))*(9/10.5) -> 7.2857143 | BE17: =(AU17+AZ17+(BC17/2))*(9/7.5) -> 9
A18: 27495 | B18: Chocó | C18: Sin clasificación oficial | D18: =AS18+AU18+AV18 -> 7 | E18: =BD18 -> 7.2857143 | F18: =BE18 -> 9 | G18: Nuquí | H18: =IFERROR(IF($AQ18,INDEX(cpe!$C$2:$C$307,MATCH($AR18,cpe!$F$2:$F$307,0)),INDEX(cpe!$C$2:$C$307,MATCH($AR18,cpe!$D$2:$D$307,0))),"#N/D") -> #N/D | I18: =IFERROR(IF($AQ18,INDEX(cpe!$B$2:$B$307,MATCH($AR18,cpe!$F$2:$F$307,0)),INDEX(cpe!$B$2:$B$307,MATCH($AR18,cpe!$D$2:$D$307,0))),"#N/D") -> #N/D | J18: =IF($AQ18,"#N/D",IFERROR(INDEX(Olimpiadas!$B$2:$B$61,MATCH($AO18,Olimpiadas!$C$2:$C$61,0)),"#N/D")) -> #N/D | K18: =IF($AQ18,"#N/D",IFERROR(INDEX(Olimpiadas!$A$2:$A$61,MATCH($AO18,Olimpiadas!$C$2:$C$61,0)),"#N/D")) -> #N/D | L18: =IF($AQ18,"#N/D",IFERROR(INDEX(Minculturas!$A$2:$A$48,MATCH($AO18,Minculturas!$C$2:$C$48,0)),"#N/D")) -> Nuquí | M18: =IF($AQ18,"#N/D",IFERROR(INDEX(Minculturas!$B$2:$B$48,MATCH($AO18,Minculturas!$C$2:$C$48,0)),"#N/D")) -> Fundación CLY Ambienta Serranías | N18: 3 | O18: 1 | P18: 0 | Q18: 0 | R18: 2 | S18: 0 | T18: 0 | U18: 0 | V18: 0 | W18: 0 | X18: 0 | Y18: 0 | Z18: 0 | AA18: 0 | AB18: 0 | AC18: 0 | AD18: 0 | AE18: 0 | AF18: 0 | AG18: =SUM(O18:X18) -> 3 | AH18: 54 | AI18: 71 | AJ18: 72.9 | AM18: Declarado afectado; sin lugar con nombre propio publicado en este registro. | AO18: =TRIM(SUBSTITUTE(SUBSTITUTE(SUBSTITUTE(SUBSTITUTE(SUBSTITUTE(SUBSTITUTE(SUBSTITUTE(SUBSTITUTE(SUBSTITUTE(LOWER(G18),"á","a"),"é","e"),"í","i"),"ó","o"),"ú","u"),"ñ","n"),"-"," "),","," "),"."," ")) -> nuqui | AP18: =TRIM(SUBSTITUTE(SUBSTITUTE(SUBSTITUTE(SUBSTITUTE(SUBSTITUTE(SUBSTITUTE(SUBSTITUTE(SUBSTITUTE(SUBSTITUTE(LOWER(B18),"á","a"),"é","e"),"í","i"),"ó","o"),"ú","u"),"ñ","n"),"-"," "),","," "),"."," ")) -> choco | AQ18: =COUNTIF($AO$2:$AO$433,AO18)>COUNTIFS($AO$2:$AO$433,AO18,$AP$2:$AP$433,AP18) -> FALSE | AR18: =IF(AQ18,AO18&"|"&AP18,AO18) -> nuqui | AS18: =(I18<>"#N/D")+(J18<>"#N/D")+(L18<>"#N/D") -> 1 | AT18: =SUM(O18:X18) -> 3 | AU18: =IF(AT18<=$AY$2,0,IF(AT18<=$AY$3,1,IF(AT18<=$AY$4,2,3))) -> 3 | AV18: =IF(Y18<=$AY$7,3,IF(Y18<=$AY$8,2,IF(Y18<=$AY$9,1,0))) -> 3 | AZ18: =IF(Y18=0,3,0) -> 3 | BA18: =AS18+AU18+AZ18 -> 7 | BB18: =IFERROR(INDEX('Análisis general'!$E$4:$E$28,MATCH($B18,'Análisis general'!$B$4:$B$28,0)),"") -> 30.8 | BC18: =IF(BB18="","",IF(BB18<=$BG$2,0,IF(BB18<=$BG$3,1,IF(BB18<=$BG$4,2,3)))) -> 3 | BD18: =(AS18+AU18+AZ18+(BC18/2))*(9/10.5) -> 7.2857143 | BE18: =(AU18+AZ18+(BC18/2))*(9/7.5) -> 9
A19: 27077 | B19: Chocó | C19: Sin clasificación oficial | D19: =AS19+AU19+AV19 -> 7 | E19: =BD19 -> 7.2857143 | F19: =BE19 -> 9 | G19: Bajo Baudó | H19: =IFERROR(IF($AQ19,INDEX(cpe!$C$2:$C$307,MATCH($AR19,cpe!$F$2:$F$307,0)),INDEX(cpe!$C$2:$C$307,MATCH($AR19,cpe!$D$2:$D$307,0))),"#N/D") -> IE de Samurindo | I19: =IFERROR(IF($AQ19,INDEX(cpe!$B$2:$B$307,MATCH($AR19,cpe!$F$2:$F$307,0)),INDEX(cpe!$B$2:$B$307,MATCH($AR19,cpe!$D$2:$D$307,0))),"#N/D") -> Bajo Baudó | J19: =IF($AQ19,"#N/D",IFERROR(INDEX(Olimpiadas!$B$2:$B$61,MATCH($AO19,Olimpiadas!$C$2:$C$61,0)),"#N/D")) -> #N/D | K19: =IF($AQ19,"#N/D",IFERROR(INDEX(Olimpiadas!$A$2:$A$61,MATCH($AO19,Olimpiadas!$C$2:$C$61,0)),"#N/D")) -> #N/D | L19: =IF($AQ19,"#N/D",IFERROR(INDEX(Minculturas!$A$2:$A$48,MATCH($AO19,Minculturas!$C$2:$C$48,0)),"#N/D")) -> #N/D | M19: =IF($AQ19,"#N/D",IFERROR(INDEX(Minculturas!$B$2:$B$48,MATCH($AO19,Minculturas!$C$2:$C$48,0)),"#N/D")) -> #N/D | N19: 6 | O19: 0 | P19: 0 | Q19: 2 | R19: 0 | S19: 0 | T19: 0 | U19: 1 | V19: 0 | W19: 0 | X19: 0 | Y19: 0 | Z19: 0 | AA19: 0 | AB19: 3 | AC19: 0 | AD19: 0 | AE19: 0 | AF19: 0 | AG19: =SUM(O19:X19) -> 3 | AH19: 285 | AI19: 630 | AJ19: 80.4 | AM19: Declarado afectado; sin lugar con nombre propio publicado en este registro. | AO19: =TRIM(SUBSTITUTE(SUBSTITUTE(SUBSTITUTE(SUBSTITUTE(SUBSTITUTE(SUBSTITUTE(SUBSTITUTE(SUBSTITUTE(SUBSTITUTE(LOWER(G19),"á","a"),"é","e"),"í","i"),"ó","o"),"ú","u"),"ñ","n"),"-"," "),","," "),"."," ")) -> bajo baudo | AP19: =TRIM(SUBSTITUTE(SUBSTITUTE(SUBSTITUTE(SUBSTITUTE(SUBSTITUTE(SUBSTITUTE(SUBSTITUTE(SUBSTITUTE(SUBSTITUTE(LOWER(B19),"á","a"),"é","e"),"í","i"),"ó","o"),"ú","u"),"ñ","n"),"-"," "),","," "),"."," ")) -> choco | AQ19: =COUNTIF($AO$2:$AO$433,AO19)>COUNTIFS($AO$2:$AO$433,AO19,$AP$2:$AP$433,AP19) -> FALSE | AR19: =IF(AQ19,AO19&"|"&AP19,AO19) -> bajo baudo | AS19: =(I19<>"#N/D")+(J19<>"#N/D")+(L19<>"#N/D") -> 1 | AT19: =SUM(O19:X19) -> 3 | AU19: =IF(AT19<=$AY$2,0,IF(AT19<=$AY$3,1,IF(AT19<=$AY$4,2,3))) -> 3 | AV19: =IF(Y19<=$AY$7,3,IF(Y19<=$AY$8,2,IF(Y19<=$AY$9,1,0))) -> 3 | AZ19: =IF(Y19=0,3,0) -> 3 | BA19: =AS19+AU19+AZ19 -> 7 | BB19: =IFERROR(INDEX('Análisis general'!$E$4:$E$28,MATCH($B19,'Análisis general'!$B$4:$B$28,0)),"") -> 30.8 | BC19: =IF(BB19="","",IF(BB19<=$BG$2,0,IF(BB19<=$BG$3,1,IF(BB19<=$BG$4,2,3)))) -> 3 | BD19: =(AS19+AU19+AZ19+(BC19/2))*(9/10.5) -> 7.2857143 | BE19: =(AU19+AZ19+(BC19/2))*(9/7.5) -> 9
A20: 52378 | B20: Nariño | C20: Sin clasificación oficial | D20: =AS20+AU20+AV20 -> 7 | E20: =BD20 -> 7.2857143 | F20: =BE20 -> 9 | G20: La Cruz | H20: =IFERROR(IF($AQ20,INDEX(cpe!$C$2:$C$307,MATCH($AR20,cpe!$F$2:$F$307,0)),INDEX(cpe!$C$2:$C$307,MATCH($AR20,cpe!$D$2:$D$307,0))),"#N/D") -> Institucion Educativa Rural San Sebastian | I20: =IFERROR(IF($AQ20,INDEX(cpe!$B$2:$B$307,MATCH($AR20,cpe!$F$2:$F$307,0)),INDEX(cpe!$B$2:$B$307,MATCH($AR20,cpe!$D$2:$D$307,0))),"#N/D") -> La Cruz | J20: =IF($AQ20,"#N/D",IFERROR(INDEX(Olimpiadas!$B$2:$B$61,MATCH($AO20,Olimpiadas!$C$2:$C$61,0)),"#N/D")) -> #N/D | K20: =IF($AQ20,"#N/D",IFERROR(INDEX(Olimpiadas!$A$2:$A$61,MATCH($AO20,Olimpiadas!$C$2:$C$61,0)),"#N/D")) -> #N/D | L20: =IF($AQ20,"#N/D",IFERROR(INDEX(Minculturas!$A$2:$A$48,MATCH($AO20,Minculturas!$C$2:$C$48,0)),"#N/D")) -> #N/D | M20: =IF($AQ20,"#N/D",IFERROR(INDEX(Minculturas!$B$2:$B$48,MATCH($AO20,Minculturas!$C$2:$C$48,0)),"#N/D")) -> #N/D | N20: 2 | O20: 0 | P20: 0 | Q20: 0 | R20: 2 | S20: 0 | T20: 0 | U20: 0 | V20: 0 | W20: 0 | X20: 0 | Y20: 0 | Z20: 0 | AA20: 0 | AB20: 0 | AC20: 0 | AD20: 0 | AE20: 0 | AF20: 0 | AG20: =SUM(O20:X20) -> 2 | AJ20: 27.8 | AM20: Declarado afectado; sin lugar con nombre propio publicado en este registro. | AO20: =TRIM(SUBSTITUTE(SUBSTITUTE(SUBSTITUTE(SUBSTITUTE(SUBSTITUTE(SUBSTITUTE(SUBSTITUTE(SUBSTITUTE(SUBSTITUTE(LOWER(G20),"á","a"),"é","e"),"í","i"),"ó","o"),"ú","u"),"ñ","n"),"-"," "),","," "),"."," ")) -> la cruz | AP20: =TRIM(SUBSTITUTE(SUBSTITUTE(SUBSTITUTE(SUBSTITUTE(SUBSTITUTE(SUBSTITUTE(SUBSTITUTE(SUBSTITUTE(SUBSTITUTE(LOWER(B20),"á","a"),"é","e"),"í","i"),"ó","o"),"ú","u"),"ñ","n"),"-"," "),","," "),"."," ")) -> narino | AQ20: =COUNTIF($AO$2:$AO$433,AO20)>COUNTIFS($AO$2:$AO$433,AO20,$AP$2:$AP$433,AP20) -> FALSE | AR20: =IF(AQ20,AO20&"|"&AP20,AO20) -> la cruz | AS20: =(I20<>"#N/D")+(J20<>"#N/D")+(L20<>"#N/D") -> 1 | AT20: =SUM(O20:X20) -> 2 | AU20: =IF(AT20<=$AY$2,0,IF(AT20<=$AY$3,1,IF(AT20<=$AY$4,2,3))) -> 3 | AV20: =IF(Y20<=$AY$7,3,IF(Y20<=$AY$8,2,IF(Y20<=$AY$9,1,0))) -> 3 | AZ20: =IF(Y20=0,3,0) -> 3 | BA20: =AS20+AU20+AZ20 -> 7 | BB20: =IFERROR(INDEX('Análisis general'!$E$4:$E$28,MATCH($B20,'Análisis general'!$B$4:$B$28,0)),"") -> 13.2 | BC20: =IF(BB20="","",IF(BB20<=$BG$2,0,IF(BB20<=$BG$3,1,IF(BB20<=$BG$4,2,3)))) -> 3 | BD20: =(AS20+AU20+AZ20+(BC20/2))*(9/10.5) -> 7.2857143 | BE20: =(AU20+AZ20+(BC20/2))*(9/7.5) -> 9
A21: 27430 | B21: Chocó | C21: Sin clasificación oficial | D21: =AS21+AU21+AV21 -> 7 | E21: =BD21 -> 7.2857143 | F21: =BE21 -> 9 | G21: Medio Baudó | H21: =IFERROR(IF($AQ21,INDEX(cpe!$C$2:$C$307,MATCH($AR21,cpe!$F$2:$F$307,0)),INDEX(cpe!$C$2:$C$307,MATCH($AR21,cpe!$D$2:$D$307,0))),"#N/D") -> Institucion Educativa Santa Teresa de Pachaquiaro | I21: =IFERROR(IF($AQ21,INDEX(cpe!$B$2:$B$307,MATCH($AR21,cpe!$F$2:$F$307,0)),INDEX(cpe!$B$2:$B$307,MATCH($AR21,cpe!$D$2:$D$307,0))),"#N/D") -> Medio Baudó | J21: =IF($AQ21,"#N/D",IFERROR(INDEX(Olimpiadas!$B$2:$B$61,MATCH($AO21,Olimpiadas!$C$2:$C$61,0)),"#N/D")) -> #N/D | K21: =IF($AQ21,"#N/D",IFERROR(INDEX(Olimpiadas!$A$2:$A$61,MATCH($AO21,Olimpiadas!$C$2:$C$61,0)),"#N/D")) -> #N/D | L21: =IF($AQ21,"#N/D",IFERROR(INDEX(Minculturas!$A$2:$A$48,MATCH($AO21,Minculturas!$C$2:$C$48,0)),"#N/D")) -> #N/D | M21: =IF($AQ21,"#N/D",IFERROR(INDEX(Minculturas!$B$2:$B$48,MATCH($AO21,Minculturas!$C$2:$C$48,0)),"#N/D")) -> #N/D | N21: 3 | O21: 0 | P21: 1 | Q21: 0 | R21: 0 | S21: 0 | T21: 0 | U21: 0 | V21: 0 | W21: 0 | X21: 1 | Y21: 0 | Z21: 0 | AA21: 0 | AB21: 1 | AC21: 0 | AD21: 0 | AE21: 0 | AF21: 0 | AG21: =SUM(O21:X21) -> 2 | AH21: 1008 | AI21: 2493 | AJ21: 80.2 | AM21: Declarado afectado; sin lugar con nombre propio publicado en este registro. | AO21: =TRIM(SUBSTITUTE(SUBSTITUTE(SUBSTITUTE(SUBSTITUTE(SUBSTITUTE(SUBSTITUTE(SUBSTITUTE(SUBSTITUTE(SUBSTITUTE(LOWER(G21),"á","a"),"é","e"),"í","i"),"ó","o"),"ú","u"),"ñ","n"),"-"," "),","," "),"."," ")) -> medio baudo | AP21: =TRIM(SUBSTITUTE(SUBSTITUTE(SUBSTITUTE(SUBSTITUTE(SUBSTITUTE(SUBSTITUTE(SUBSTITUTE(SUBSTITUTE(SUBSTITUTE(LOWER(B21),"á","a"),"é","e"),"í","i"),"ó","o"),"ú","u"),"ñ","n"),"-"," "),","," "),"."," ")) -> choco | AQ21: =COUNTIF($AO$2:$AO$433,AO21)>COUNTIFS($AO$2:$AO$433,AO21,$AP$2:$AP$433,AP21) -> FALSE | AR21: =IF(AQ21,AO21&"|"&AP21,AO21) -> medio baudo | AS21: =(I21<>"#N/D")+(J21<>"#N/D")+(L21<>"#N/D") -> 1 | AT21: =SUM(O21:X21) -> 2 | AU21: =IF(AT21<=$AY$2,0,IF(AT21<=$AY$3,1,IF(AT21<=$AY$4,2,3))) -> 3 | AV21: =IF(Y21<=$AY$7,3,IF(Y21<=$AY$8,2,IF(Y21<=$AY$9,1,0))) -> 3 | AZ21: =IF(Y21=0,3,0) -> 3 | BA21: =AS21+AU21+AZ21 -> 7 | BB21: =IFERROR(INDEX('Análisis general'!$E$4:$E$28,MATCH($B21,'Análisis general'!$B$4:$B$28,0)),"") -> 30.8 | BC21: =IF(BB21="","",IF(BB21<=$BG$2,0,IF(BB21<=$BG$3,1,IF(BB21<=$BG$4,2,3)))) -> 3 | BD21: =(AS21+AU21+AZ21+(BC21/2))*(9/10.5) -> 7.2857143 | BE21: =(AU21+AZ21+(BC21/2))*(9/7.5) -> 9
A22: 25612 | B22: Nariño | C22: Afectación media | D22: =AS22+AU22+AV22 -> 7 | E22: =BD22 -> 7.2857143 | F22: =BE22 -> 9 | G22: Ricaurte | H22: Institucion Educativa Luis Carlos Galan | I22: Ricaurte | J22: #N/D | K22: =IF($AQ22,"#N/D",IFERROR(INDEX(Olimpiadas!$A$2:$A$61,MATCH($AO22,Olimpiadas!$C$2:$C$61,0)),"#N/D")) -> #N/D | L22: =IF($AQ22,"#N/D",IFERROR(INDEX(Minculturas!$A$2:$A$48,MATCH($AO22,Minculturas!$C$2:$C$48,0)),"#N/D")) -> #N/D | M22: =IF($AQ22,"#N/D",IFERROR(INDEX(Minculturas!$B$2:$B$48,MATCH($AO22,Minculturas!$C$2:$C$48,0)),"#N/D")) -> #N/D | N22: 2 | O22: 0 | P22: 1 | Q22: 0 | R22: 1 | S22: 0 | T22: 0 | U22: 0 | V22: 0 | W22: 0 | X22: 0 | Y22: 0 | Z22: 0 | AA22: 0 | AB22: 0 | AC22: 0 | AD22: 0 | AE22: 0 | AF22: 0 | AG22: =SUM(O22:X22) -> 2 | AJ22: 17.5 | AM22: Declarado afectado; sin lugar con nombre propio publicado en este registro. | AO22: =TRIM(SUBSTITUTE(SUBSTITUTE(SUBSTITUTE(SUBSTITUTE(SUBSTITUTE(SUBSTITUTE(SUBSTITUTE(SUBSTITUTE(SUBSTITUTE(LOWER(G22),"á","a"),"é","e"),"í","i"),"ó","o"),"ú","u"),"ñ","n"),"-"," "),","," "),"."," ")) -> ricaurte | AP22: =TRIM(SUBSTITUTE(SUBSTITUTE(SUBSTITUTE(SUBSTITUTE(SUBSTITUTE(SUBSTITUTE(SUBSTITUTE(SUBSTITUTE(SUBSTITUTE(LOWER(B22),"á","a"),"é","e"),"í","i"),"ó","o"),"ú","u"),"ñ","n"),"-"," "),","," "),"."," ")) -> narino | AQ22: =COUNTIF($AO$2:$AO$433,AO22)>COUNTIFS($AO$2:$AO$433,AO22,$AP$2:$AP$433,AP22) -> TRUE | AR22: =IF(AQ22,AO22&"|"&AP22,AO22) -> ricaurte|narino | AS22: =(I22<>"#N/D")+(J22<>"#N/D")+(L22<>"#N/D") -> 1 | AT22: =SUM(O22:X22) -> 2 | AU22: =IF(AT22<=$AY$2,0,IF(AT22<=$AY$3,1,IF(AT22<=$AY$4,2,3))) -> 3 | AV22: =IF(Y22<=$AY$7,3,IF(Y22<=$AY$8,2,IF(Y22<=$AY$9,1,0))) -> 3 | AZ22: =IF(Y22=0,3,0) -> 3 | BA22: =AS22+AU22+AZ22 -> 7 | BB22: =IFERROR(INDEX('Análisis general'!$E$4:$E$28,MATCH($B22,'Análisis general'!$B$4:$B$28,0)),"") -> 13.2 | BC22: =IF(BB22="","",IF(BB22<=$BG$2,0,IF(BB22<=$BG$3,1,IF(BB22<=$BG$4,2,3)))) -> 3 | BD22: =(AS22+AU22+AZ22+(BC22/2))*(9/10.5) -> 7.2857143 | BE22: =(AU22+AZ22+(BC22/2))*(9/7.5) -> 9
A23: 17541 | B23: Caldas | C23: Sin clasificación oficial | D23: =AS23+AU23+AV23 -> 6 | E23: =BD23 -> 6.4285714 | F23: =BE23 -> 9 | G23: Pensilvania | H23: #N/D | I23: #N/D | J23: #N/D | K23: =IF($AQ23,"#N/D",IFERROR(INDEX(Olimpiadas!$A$2:$A$61,MATCH($AO23,Olimpiadas!$C$2:$C$61,0)),"#N/D")) -> #N/D | L23: =IF($AQ23,"#N/D",IFERROR(INDEX(Minculturas!$A$2:$A$48,MATCH($AO23,Minculturas!$C$2:$C$48,0)),"#N/D")) -> #N/D | M23: =IF($AQ23,"#N/D",IFERROR(INDEX(Minculturas!$B$2:$B$48,MATCH($AO23,Minculturas!$C$2:$C$48,0)),"#N/D")) -> #N/D | N23: 22 | O23: 0 | P23: 8 | Q23: 0 | R23: 3 | S23: 4 | T23: 2 | U23: 5 | V23: 0 | W23: 0 | X23: 0 | Y23: 0 | Z23: 0 | AA23: 0 | AB23: 0 | AC23: 0 | AD23: 0 | AE23: 0 | AF23: 0 | AG23: =SUM(O23:X23) -> 22 | AH23: 125 | AI23: 323 | AJ23: 37.3 | AM23: Daños y afectaciones en infraestructura. | AO23: =TRIM(SUBSTITUTE(SUBSTITUTE(SUBSTITUTE(SUBSTITUTE(SUBSTITUTE(SUBSTITUTE(SUBSTITUTE(SUBSTITUTE(SUBSTITUTE(LOWER(G23),"á","a"),"é","e"),"í","i"),"ó","o"),"ú","u"),"ñ","n"),"-"," "),","," "),"."," ")) -> pensilvania | AP23: =TRIM(SUBSTITUTE(SUBSTITUTE(SUBSTITUTE(SUBSTITUTE(SUBSTITUTE(SUBSTITUTE(SUBSTITUTE(SUBSTITUTE(SUBSTITUTE(LOWER(B23),"á","a"),"é","e"),"í","i"),"ó","o"),"ú","u"),"ñ","n"),"-"," "),","," "),"."," ")) -> caldas | AQ23: =COUNTIF($AO$2:$AO$433,AO23)>COUNTIFS($AO$2:$AO$433,AO23,$AP$2:$AP$433,AP23) -> FALSE | AR23: =IF(AQ23,AO23&"|"&AP23,AO23) -> pensilvania | AS23: =(I23<>"#N/D")+(J23<>"#N/D")+(L23<>"#N/D") -> 0 | AT23: =SUM(O23:X23) -> 22 | AU23: =IF(AT23<=$AY$2,0,IF(AT23<=$AY$3,1,IF(AT23<=$AY$4,2,3))) -> 3 | AV23: =IF(Y23<=$AY$7,3,IF(Y23<=$AY$8,2,IF(Y23<=$AY$9,1,0))) -> 3 | AZ23: =IF(Y23=0,3,0) -> 3 | BA23: =AS23+AU23+AZ23 -> 6 | BB23: =IFERROR(INDEX('Análisis general'!$E$4:$E$28,MATCH($B23,'Análisis general'!$B$4:$B$28,0)),"") -> 7.9 | BC23: =IF(BB23="","",IF(BB23<=$BG$2,0,IF(BB23<=$BG$3,1,IF(BB23<=$BG$4,2,3)))) -> 3 | BD23: =(AS23+AU23+AZ23+(BC23/2))*(9/10.5) -> 6.4285714 | BE23: =(AU23+AZ23+(BC23/2))*(9/7.5) -> 9
A24: 17653 | B24: Caldas | C24: Sin clasificación oficial | D24: =AS24+AU24+AV24 -> 6 | E24: =BD24 -> 6.4285714 | F24: =BE24 -> 9 | G24: Salamina | H24: #N/D | I24: #N/D | J24: #N/D | K24: =IF($AQ24,"#N/D",IFERROR(INDEX(Olimpiadas!$A$2:$A$61,MATCH($AO24,Olimpiadas!$C$2:$C$61,0)),"#N/D")) -> #N/D | L24: =IF($AQ24,"#N/D",IFERROR(INDEX(Minculturas!$A$2:$A$48,MATCH($AO24,Minculturas!$C$2:$C$48,0)),"#N/D")) -> #N/D | M24: =IF($AQ24,"#N/D",IFERROR(INDEX(Minculturas!$B$2:$B$48,MATCH($AO24,Minculturas!$C$2:$C$48,0)),"#N/D")) -> #N/D | N24: 21 | O24: 0 | P24: 1 | Q24: 7 | R24: 1 | S24: 6 | T24: 5 | U24: 0 | V24: 0 | W24: 0 | X24: 0 | Y24: 0 | Z24: 0 | AA24: 0 | AB24: 1 | AC24: 0 | AD24: 0 | AE24: 0 | AF24: 0 | AG24: =SUM(O24:X24) -> 20 | AH24: 30 | AI24: 81 | AJ24: 28.7 | AM24: Declarado afectado; sin lugar con nombre propio publicado en este registro. | AO24: =TRIM(SUBSTITUTE(SUBSTITUTE(SUBSTITUTE(SUBSTITUTE(SUBSTITUTE(SUBSTITUTE(SUBSTITUTE(SUBSTITUTE(SUBSTITUTE(LOWER(G24),"á","a"),"é","e"),"í","i"),"ó","o"),"ú","u"),"ñ","n"),"-"," "),","," "),"."," ")) -> salamina | AP24: =TRIM(SUBSTITUTE(SUBSTITUTE(SUBSTITUTE(SUBSTITUTE(SUBSTITUTE(SUBSTITUTE(SUBSTITUTE(SUBSTITUTE(SUBSTITUTE(LOWER(B24),"á","a"),"é","e"),"í","i"),"ó","o"),"ú","u"),"ñ","n"),"-"," "),","," "),"."," ")) -> caldas | AQ24: =COUNTIF($AO$2:$AO$433,AO24)>COUNTIFS($AO$2:$AO$433,AO24,$AP$2:$AP$433,AP24) -> FALSE | AR24: =IF(AQ24,AO24&"|"&AP24,AO24) -> salamina | AS24: =(I24<>"#N/D")+(J24<>"#N/D")+(L24<>"#N/D") -> 0 | AT24: =SUM(O24:X24) -> 20 | AU24: =IF(AT24<=$AY$2,0,IF(AT24<=$AY$3,1,IF(AT24<=$AY$4,2,3))) -> 3 | AV24: =IF(Y24<=$AY$7,3,IF(Y24<=$AY$8,2,IF(Y24<=$AY$9,1,0))) -> 3 | AZ24: =IF(Y24=0,3,0) -> 3 | BA24: =AS24+AU24+AZ24 -> 6 | BB24: =IFERROR(INDEX('Análisis general'!$E$4:$E$28,MATCH($B24,'Análisis general'!$B$4:$B$28,0)),"") -> 7.9 | BC24: =IF(BB24="","",IF(BB24<=$BG$2,0,IF(BB24<=$BG$3,1,IF(BB24<=$BG$4,2,3)))) -> 3 | BD24: =(AS24+AU24+AZ24+(BC24/2))*(9/10.5) -> 6.4285714 | BE24: =(AU24+AZ24+(BC24/2))*(9/7.5) -> 9
A25: 17042 | B25: Caldas | C25: Afectación alta | D25: =AS25+AU25+AV25 -> 6 | E25: =BD25 -> 6.4285714 | F25: =BE25 -> 9 | G25: Anserma | H25: =IFERROR(IF($AQ25,INDEX(cpe!$C$2:$C$307,MATCH($AR25,cpe!$F$2:$F$307,0)),INDEX(cpe!$C$2:$C$307,MATCH($AR25,cpe!$D$2:$D$307,0))),"#N/D") -> #N/D | I25: =IFERROR(IF($AQ25,INDEX(cpe!$B$2:$B$307,MATCH($AR25,cpe!$F$2:$F$307,0)),INDEX(cpe!$B$2:$B$307,MATCH($AR25,cpe!$D$2:$D$307,0))),"#N/D") -> #N/D | J25: =IF($AQ25,"#N/D",IFERROR(INDEX(Olimpiadas!$B$2:$B$61,MATCH($AO25,Olimpiadas!$C$2:$C$61,0)),"#N/D")) -> #N/D | K25: =IF($AQ25,"#N/D",IFERROR(INDEX(Olimpiadas!$A$2:$A$61,MATCH($AO25,Olimpiadas!$C$2:$C$61,0)),"#N/D")) -> #N/D | L25: =IF($AQ25,"#N/D",IFERROR(INDEX(Minculturas!$A$2:$A$48,MATCH($AO25,Minculturas!$C$2:$C$48,0)),"#N/D")) -> #N/D | M25: =IF($AQ25,"#N/D",IFERROR(INDEX(Minculturas!$B$2:$B$48,MATCH($AO25,Minculturas!$C$2:$C$48,0)),"#N/D")) -> #N/D | N25: 18 | O25: 0 | P25: 7 | Q25: 2 | R25: 1 | S25: 3 | T25: 1 | U25: 1 | V25: 0 | W25: 0 | X25: 0 | Y25: 0 | Z25: 0 | AA25: 0 | AB25: 3 | AC25: 0 | AD25: 0 | AE25: 0 | AF25: 0 | AG25: =SUM(O25:X25) -> 15 | AH25: 2 | AI25: 3 | AJ25: 32.5 | AM25: Afectaciones estructurales y daños en infraestructura. | AO25: =TRIM(SUBSTITUTE(SUBSTITUTE(SUBSTITUTE(SUBSTITUTE(SUBSTITUTE(SUBSTITUTE(SUBSTITUTE(SUBSTITUTE(SUBSTITUTE(LOWER(G25),"á","a"),"é","e"),"í","i"),"ó","o"),"ú","u"),"ñ","n"),"-"," "),","," "),"."," ")) -> anserma | AP25: =TRIM(SUBSTITUTE(SUBSTITUTE(SUBSTITUTE(SUBSTITUTE(SUBSTITUTE(SUBSTITUTE(SUBSTITUTE(SUBSTITUTE(SUBSTITUTE(LOWER(B25),"á","a"),"é","e"),"í","i"),"ó","o"),"ú","u"),"ñ","n"),"-"," "),","," "),"."," ")) -> caldas | AQ25: =COUNTIF($AO$2:$AO$433,AO25)>COUNTIFS($AO$2:$AO$433,AO25,$AP$2:$AP$433,AP25) -> FALSE | AR25: =IF(AQ25,AO25&"|"&AP25,AO25) -> anserma | AS25: =(I25<>"#N/D")+(J25<>"#N/D")+(L25<>"#N/D") -> 0 | AT25: =SUM(O25:X25) -> 15 | AU25: =IF(AT25<=$AY$2,0,IF(AT25<=$AY$3,1,IF(AT25<=$AY$4,2,3))) -> 3 | AV25: =IF(Y25<=$AY$7,3,IF(Y25<=$AY$8,2,IF(Y25<=$AY$9,1,0))) -> 3 | AZ25: =IF(Y25=0,3,0) -> 3 | BA25: =AS25+AU25+AZ25 -> 6 | BB25: =IFERROR(INDEX('Análisis general'!$E$4:$E$28,MATCH($B25,'Análisis general'!$B$4:$B$28,0)),"") -> 7.9 | BC25: =IF(BB25="","",IF(BB25<=$BG$2,0,IF(BB25<=$BG$3,1,IF(BB25<=$BG$4,2,3)))) -> 3 | BD25: =(AS25+AU25+AZ25+(BC25/2))*(9/10.5) -> 6.4285714 | BE25: =(AU25+AZ25+(BC25/2))*(9/7.5) -> 9
A26: 17050 | B26: Caldas | C26: Sin clasificación oficial | D26: =AS26+AU26+AV26 -> 6 | E26: =BD26 -> 6.4285714 | F26: =BE26 -> 9 | G26: Aranzazu | H26: =IFERROR(IF($AQ26,INDEX(cpe!$C$2:$C$307,MATCH($AR26,cpe!$F$2:$F$307,0)),INDEX(cpe!$C$2:$C$307,MATCH($AR26,cpe!$D$2:$D$307,0))),"#N/D") -> #N/D | I26: =IFERROR(IF($AQ26,INDEX(cpe!$B$2:$B$307,MATCH($AR26,cpe!$F$2:$F$307,0)),INDEX(cpe!$B$2:$B$307,MATCH($AR26,cpe!$D$2:$D$307,0))),"#N/D") -> #N/D | J26: =IF($AQ26,"#N/D",IFERROR(INDEX(Olimpiadas!$B$2:$B$61,MATCH($AO26,Olimpiadas!$C$2:$C$61,0)),"#N/D")) -> #N/D | K26: =IF($AQ26,"#N/D",IFERROR(INDEX(Olimpiadas!$A$2:$A$61,MATCH($AO26,Olimpiadas!$C$2:$C$61,0)),"#N/D")) -> #N/D | L26: =IF($AQ26,"#N/D",IFERROR(INDEX(Minculturas!$A$2:$A$48,MATCH($AO26,Minculturas!$C$2:$C$48,0)),"#N/D")) -> #N/D | M26: =IF($AQ26,"#N/D",IFERROR(INDEX(Minculturas!$B$2:$B$48,MATCH($AO26,Minculturas!$C$2:$C$48,0)),"#N/D")) -> #N/D | N26: 15 | O26: 0 | P26: 1 | Q26: 2 | R26: 0 | S26: 10 | T26: 1 | U26: 1 | V26: 0 | W26: 0 | X26: 0 | Y26: 0 | Z26: 0 | AA26: 0 | AB26: 0 | AC26: 0 | AD26: 0 | AE26: 0 | AF26: 0 | AG26: =SUM(O26:X26) -> 15 | AH26: 61 | AI26: 146 | AJ26: 32.1 | AM26: Declarado afectado; sin lugar con nombre propio publicado en este registro. | AO26: =TRIM(SUBSTITUTE(SUBSTITUTE(SUBSTITUTE(SUBSTITUTE(SUBSTITUTE(SUBSTITUTE(SUBSTITUTE(SUBSTITUTE(SUBSTITUTE(LOWER(G26),"á","a"),"é","e"),"í","i"),"ó","o"),"ú","u"),"ñ","n"),"-"," "),","," "),"."," ")) -> aranzazu | AP26: =TRIM(SUBSTITUTE(SUBSTITUTE(SUBSTITUTE(SUBSTITUTE(SUBSTITUTE(SUBSTITUTE(SUBSTITUTE(SUBSTITUTE(SUBSTITUTE(LOWER(B26),"á","a"),"é","e"),"í","i"),"ó","o"),"ú","u"),"ñ","n"),"-"," "),","," "),"."," ")) -> caldas | AQ26: =COUNTIF($AO$2:$AO$433,AO26)>COUNTIFS($AO$2:$AO$433,AO26,$AP$2:$AP$433,AP26) -> FALSE | AR26: =IF(AQ26,AO26&"|"&AP26,AO26) -> aranzazu | AS26: =(I26<>"#N/D")+(J26<>"#N/D")+(L26<>"#N/D") -> 0 | AT26: =SUM(O26:X26) -> 15 | AU26: =IF(AT26<=$AY$2,0,IF(AT26<=$AY$3,1,IF(AT26<=$AY$4,2,3))) -> 3 | AV26: =IF(Y26<=$AY$7,3,IF(Y26<=$AY$8,2,IF(Y26<=$AY$9,1,0))) -> 3 | AZ26: =IF(Y26=0,3,0) -> 3 | BA26: =AS26+AU26+AZ26 -> 6 | BB26: =IFERROR(INDEX('Análisis general'!$E$4:$E$28,MATCH($B26,'Análisis general'!$B$4:$B$28,0)),"") -> 7.9 | BC26: =IF(BB26="","",IF(BB26<=$BG$2,0,IF(BB26<=$BG$3,1,IF(BB26<=$BG$4,2,3)))) -> 3 | BD26: =(AS26+AU26+AZ26+(BC26/2))*(9/10.5) -> 6.4285714 | BE26: =(AU26+AZ26+(BC26/2))*(9/7.5) -> 9
A27: 05034 | B27: Antioquia | C27: Sin clasificación oficial | D27: =AS27+AU27+AV27 -> 6 | E27: =BD27 -> 6.4285714 | F27: =BE27 -> 9 | G27: Andes | H27: =IFERROR(IF($AQ27,INDEX(cpe!$C$2:$C$307,MATCH($AR27,cpe!$F$2:$F$307,0)),INDEX(cpe!$C$2:$C$307,MATCH($AR27,cpe!$D$2:$D$307,0))),"#N/D") -> #N/D | I27: =IFERROR(IF($AQ27,INDEX(cpe!$B$2:$B$307,MATCH($AR27,cpe!$F$2:$F$307,0)),INDEX(cpe!$B$2:$B$307,MATCH($AR27,cpe!$D$2:$D$307,0))),"#N/D") -> #N/D | J27: =IF($AQ27,"#N/D",IFERROR(INDEX(Olimpiadas!$B$2:$B$61,MATCH($AO27,Olimpiadas!$C$2:$C$61,0)),"#N/D")) -> #N/D | K27: =IF($AQ27,"#N/D",IFERROR(INDEX(Olimpiadas!$A$2:$A$61,MATCH($AO27,Olimpiadas!$C$2:$C$61,0)),"#N/D")) -> #N/D | L27: =IF($AQ27,"#N/D",IFERROR(INDEX(Minculturas!$A$2:$A$48,MATCH($AO27,Minculturas!$C$2:$C$48,0)),"#N/D")) -> #N/D | M27: =IF($AQ27,"#N/D",IFERROR(INDEX(Minculturas!$B$2:$B$48,MATCH($AO27,Minculturas!$C$2:$C$48,0)),"#N/D")) -> #N/D | N27: 12 | O27: 0 | P27: 1 | Q27: 6 | R27: 1 | S27: 4 | T27: 0 | U27: 0 | V27: 0 | W27: 0 | X27: 0 | Y27: 0 | Z27: 0 | AA27: 0 | AB27: 0 | AC27: 0 | AD27: 0 | AE27: 0 | AF27: 0 | AG27: =SUM(O27:X27) -> 12 | AJ27: 40.1 | AM27: Declarado afectado; sin lugar con nombre propio publicado en este registro. | AO27: =TRIM(SUBSTITUTE(SUBSTITUTE(SUBSTITUTE(SUBSTITUTE(SUBSTITUTE(SUBSTITUTE(SUBSTITUTE(SUBSTITUTE(SUBSTITUTE(LOWER(G27),"á","a"),"é","e"),"í","i"),"ó","o"),"ú","u"),"ñ","n"),"-"," "),","," "),"."," ")) -> andes | AP27: =TRIM(SUBSTITUTE(SUBSTITUTE(SUBSTITUTE(SUBSTITUTE(SUBSTITUTE(SUBSTITUTE(SUBSTITUTE(SUBSTITUTE(SUBSTITUTE(LOWER(B27),"á","a"),"é","e"),"í","i"),"ó","o"),"ú","u"),"ñ","n"),"-"," "),","," "),"."," ")) -> antioquia | AQ27: =COUNTIF($AO$2:$AO$433,AO27)>COUNTIFS($AO$2:$AO$433,AO27,$AP$2:$AP$433,AP27) -> FALSE | AR27: =IF(AQ27,AO27&"|"&AP27,AO27) -> andes | AS27: =(I27<>"#N/D")+(J27<>"#N/D")+(L27<>"#N/D") -> 0 | AT27: =SUM(O27:X27) -> 12 | AU27: =IF(AT27<=$AY$2,0,IF(AT27<=$AY$3,1,IF(AT27<=$AY$4,2,3))) -> 3 | AV27: =IF(Y27<=$AY$7,3,IF(Y27<=$AY$8,2,IF(Y27<=$AY$9,1,0))) -> 3 | AZ27: =IF(Y27=0,3,0) -> 3 | BA27: =AS27+AU27+AZ27 -> 6 | BB27: =IFERROR(INDEX('Análisis general'!$E$4:$E$28,MATCH($B27,'Análisis general'!$B$4:$B$28,0)),"") -> 9.5 | BC27: =IF(BB27="","",IF(BB27<=$BG$2,0,IF(BB27<=$BG$3,1,IF(BB27<=$BG$4,2,3)))) -> 3 | BD27: =(AS27+AU27+AZ27+(BC27/2))*(9/10.5) -> 6.4285714 | BE27: =(AU27+AZ27+(BC27/2))*(9/7.5) -> 9
A28: 17877 | B28: Caldas | C28: Sin clasificación oficial | D28: =AS28+AU28+AV28 -> 6 | E28: =BD28 -> 6.4285714 | F28: =BE28 -> 9 | G28: Viterbo | H28: #N/D | I28: #N/D | J28: #N/D | K28: =IF($AQ28,"#N/D",IFERROR(INDEX(Olimpiadas!$A$2:$A$61,MATCH($AO28,Olimpiadas!$C$2:$C$61,0)),"#N/D")) -> #N/D | L28: =IF($AQ28,"#N/D",IFERROR(INDEX(Minculturas!$A$2:$A$48,MATCH($AO28,Minculturas!$C$2:$C$48,0)),"#N/D")) -> #N/D | M28: =IF($AQ28,"#N/D",IFERROR(INDEX(Minculturas!$B$2:$B$48,MATCH($AO28,Minculturas!$C$2:$C$48,0)),"#N/D")) -> #N/D | N28: 12 | O28: 0 | P28: 2 | Q28: 0 | R28: 1 | S28: 1 | T28: 1 | U28: 3 | V28: 4 | W28: 0 | X28: 0 | Y28: 0 | Z28: 0 | AA28: 0 | AB28: 0 | AC28: 0 | AD28: 0 | AE28: 0 | AF28: 0 | AG28: =SUM(O28:X28) -> 12 | AJ28: 26 | AM28: Declarado afectado; sin lugar con nombre propio publicado en este registro. | AO28: =TRIM(SUBSTITUTE(SUBSTITUTE(SUBSTITUTE(SUBSTITUTE(SUBSTITUTE(SUBSTITUTE(SUBSTITUTE(SUBSTITUTE(SUBSTITUTE(LOWER(G28),"á","a"),"é","e"),"í","i"),"ó","o"),"ú","u"),"ñ","n"),"-"," "),","," "),"."," ")) -> viterbo | AP28: =TRIM(SUBSTITUTE(SUBSTITUTE(SUBSTITUTE(SUBSTITUTE(SUBSTITUTE(SUBSTITUTE(SUBSTITUTE(SUBSTITUTE(SUBSTITUTE(LOWER(B28),"á","a"),"é","e"),"í","i"),"ó","o"),"ú","u"),"ñ","n"),"-"," "),","," "),"."," ")) -> caldas | AQ28: =COUNTIF($AO$2:$AO$433,AO28)>COUNTIFS($AO$2:$AO$433,AO28,$AP$2:$AP$433,AP28) -> FALSE | AR28: =IF(AQ28,AO28&"|"&AP28,AO28) -> viterbo | AS28: =(I28<>"#N/D")+(J28<>"#N/D")+(L28<>"#N/D") -> 0 | AT28: =SUM(O28:X28) -> 12 | AU28: =IF(AT28<=$AY$2,0,IF(AT28<=$AY$3,1,IF(AT28<=$AY$4,2,3))) -> 3 | AV28: =IF(Y28<=$AY$7,3,IF(Y28<=$AY$8,2,IF(Y28<=$AY$9,1,0))) -> 3 | AZ28: =IF(Y28=0,3,0) -> 3 | BA28: =AS28+AU28+AZ28 -> 6 | BB28: =IFERROR(INDEX('Análisis general'!$E$4:$E$28,MATCH($B28,'Análisis general'!$B$4:$B$28,0)),"") -> 7.9 | BC28: =IF(BB28="","",IF(BB28<=$BG$2,0,IF(BB28<=$BG$3,1,IF(BB28<=$BG$4,2,3)))) -> 3 | BD28: =(AS28+AU28+AZ28+(BC28/2))*(9/10.5) -> 6.4285714 | BE28: =(AU28+AZ28+(BC28/2))*(9/7.5) -> 9
A29: 05789 | B29: Antioquia | C29: Sin clasificación oficial | D29: =AS29+AU29+AV29 -> 6 | E29: =BD29 -> 6.4285714 | F29: =BE29 -> 9 | G29: Támesis | H29: #N/D | I29: #N/D | J29: #N/D | K29: =IF($AQ29,"#N/D",IFERROR(INDEX(Olimpiadas!$A$2:$A$61,MATCH($AO29,Olimpiadas!$C$2:$C$61,0)),"#N/D")) -> #N/D | L29: =IF($AQ29,"#N/D",IFERROR(INDEX(Minculturas!$A$2:$A$48,MATCH($AO29,Minculturas!$C$2:$C$48,0)),"#N/D")) -> #N/D | M29: =IF($AQ29,"#N/D",IFERROR(INDEX(Minculturas!$B$2:$B$48,MATCH($AO29,Minculturas!$C$2:$C$48,0)),"#N/D")) -> #N/D | N29: 11 | O29: 0 | P29: 2 | Q29: 2 | R29: 0 | S29: 4 | T29: 2 | U29: 0 | V29: 0 | W29: 1 | X29: 0 | Y29: 0 | Z29: 0 | AA29: 0 | AB29: 0 | AC29: 0 | AD29: 0 | AE29: 0 | AF29: 0 | AG29: =SUM(O29:X29) -> 11 | AJ29: 36.6 | AM29: Declarado afectado; sin lugar con nombre propio publicado en este registro. | AO29: =TRIM(SUBSTITUTE(SUBSTITUTE(SUBSTITUTE(SUBSTITUTE(SUBSTITUTE(SUBSTITUTE(SUBSTITUTE(SUBSTITUTE(SUBSTITUTE(LOWER(G29),"á","a"),"é","e"),"í","i"),"ó","o"),"ú","u"),"ñ","n"),"-"," "),","," "),"."," ")) -> tamesis | AP29: =TRIM(SUBSTITUTE(SUBSTITUTE(SUBSTITUTE(SUBSTITUTE(SUBSTITUTE(SUBSTITUTE(SUBSTITUTE(SUBSTITUTE(SUBSTITUTE(LOWER(B29),"á","a"),"é","e"),"í","i"),"ó","o"),"ú","u"),"ñ","n"),"-"," "),","," "),"."," ")) -> antioquia | AQ29: =COUNTIF($AO$2:$AO$433,AO29)>COUNTIFS($AO$2:$AO$433,AO29,$AP$2:$AP$433,AP29) -> FALSE | AR29: =IF(AQ29,AO29&"|"&AP29,AO29) -> tamesis | AS29: =(I29<>"#N/D")+(J29<>"#N/D")+(L29<>"#N/D") -> 0 | AT29: =SUM(O29:X29) -> 11 | AU29: =IF(AT29<=$AY$2,0,IF(AT29<=$AY$3,1,IF(AT29<=$AY$4,2,3))) -> 3 | AV29: =IF(Y29<=$AY$7,3,IF(Y29<=$AY$8,2,IF(Y29<=$AY$9,1,0))) -> 3 | AZ29: =IF(Y29=0,3,0) -> 3 | BA29: =AS29+AU29+AZ29 -> 6 | BB29: =IFERROR(INDEX('Análisis general'!$E$4:$E$28,MATCH($B29,'Análisis general'!$B$4:$B$28,0)),"") -> 9.5 | BC29: =IF(BB29="","",IF(BB29<=$BG$2,0,IF(BB29<=$BG$3,1,IF(BB29<=$BG$4,2,3)))) -> 3 | BD29: =(AS29+AU29+AZ29+(BC29/2))*(9/10.5) -> 6.4285714 | BE29: =(AU29+AZ29+(BC29/2))*(9/7.5) -> 9
A30: 17486 | B30: Caldas | C30: Afectación alta | D30: =AS30+AU30+AV30 -> 6 | E30: =BD30 -> 6.4285714 | F30: =BE30 -> 9 | G30: Neira | H30: =IFERROR(IF($AQ30,INDEX(cpe!$C$2:$C$307,MATCH($AR30,cpe!$F$2:$F$307,0)),INDEX(cpe!$C$2:$C$307,MATCH($AR30,cpe!$D$2:$D$307,0))),"#N/D") -> #N/D | I30: =IFERROR(IF($AQ30,INDEX(cpe!$B$2:$B$307,MATCH($AR30,cpe!$F$2:$F$307,0)),INDEX(cpe!$B$2:$B$307,MATCH($AR30,cpe!$D$2:$D$307,0))),"#N/D") -> #N/D | J30: =IF($AQ30,"#N/D",IFERROR(INDEX(Olimpiadas!$B$2:$B$61,MATCH($AO30,Olimpiadas!$C$2:$C$61,0)),"#N/D")) -> #N/D | K30: =IF($AQ30,"#N/D",IFERROR(INDEX(Olimpiadas!$A$2:$A$61,MATCH($AO30,Olimpiadas!$C$2:$C$61,0)),"#N/D")) -> #N/D | L30: =IF($AQ30,"#N/D",IFERROR(INDEX(Minculturas!$A$2:$A$48,MATCH($AO30,Minculturas!$C$2:$C$48,0)),"#N/D")) -> #N/D | M30: =IF($AQ30,"#N/D",IFERROR(INDEX(Minculturas!$B$2:$B$48,MATCH($AO30,Minculturas!$C$2:$C$48,0)),"#N/D")) -> #N/D | N30: 11 | O30: 0 | P30: 0 | Q30: 2 | R30: 1 | S30: 2 | T30: 3 | U30: 1 | V30: 1 | W30: 0 | X30: 0 | Y30: 0 | Z30: 1 | AA30: 0 | AB30: 0 | AC30: 0 | AD30: 0 | AE30: 0 | AF30: 0 | AG30: =SUM(O30:X30) -> 10 | AJ30: 31.3 | AM30: Afectaciones en infraestructura y servicios. | AO30: =TRIM(SUBSTITUTE(SUBSTITUTE(SUBSTITUTE(SUBSTITUTE(SUBSTITUTE(SUBSTITUTE(SUBSTITUTE(SUBSTITUTE(SUBSTITUTE(LOWER(G30),"á","a"),"é","e"),"í","i"),"ó","o"),"ú","u"),"ñ","n"),"-"," "),","," "),"."," ")) -> neira | AP30: =TRIM(SUBSTITUTE(SUBSTITUTE(SUBSTITUTE(SUBSTITUTE(SUBSTITUTE(SUBSTITUTE(SUBSTITUTE(SUBSTITUTE(SUBSTITUTE(LOWER(B30),"á","a"),"é","e"),"í","i"),"ó","o"),"ú","u"),"ñ","n"),"-"," "),","," "),"."," ")) -> caldas | AQ30: =COUNTIF($AO$2:$AO$433,AO30)>COUNTIFS($AO$2:$AO$433,AO30,$AP$2:$AP$433,AP30) -> FALSE | AR30: =IF(AQ30,AO30&"|"&AP30,AO30) -> neira | AS30: =(I30<>"#N/D")+(J30<>"#N/D")+(L30<>"#N/D") -> 0 | AT30: =SUM(O30:X30) -> 10 | AU30: =IF(AT30<=$AY$2,0,IF(AT30<=$AY$3,1,IF(AT30<=$AY$4,2,3))) -> 3 | AV30: =IF(Y30<=$AY$7,3,IF(Y30<=$AY$8,2,IF(Y30<=$AY$9,1,0))) -> 3 | AZ30: =IF(Y30=0,3,0) -> 3 | BA30: =AS30+AU30+AZ30 -> 6 | BB30: =IFERROR(INDEX('Análisis general'!$E$4:$E$28,MATCH($B30,'Análisis general'!$B$4:$B$28,0)),"") -> 7.9 | BC30: =IF(BB30="","",IF(BB30<=$BG$2,0,IF(BB30<=$BG$3,1,IF(BB30<=$BG$4,2,3)))) -> 3 | BD30: =(AS30+AU30+AZ30+(BC30/2))*(9/10.5) -> 6.4285714 | BE30: =(AU30+AZ30+(BC30/2))*(9/7.5) -> 9
A31: 05756 | B31: Antioquia | C31: Sin clasificación oficial | D31: =AS31+AU31+AV31 -> 6 | E31: =BD31 -> 6.4285714 | F31: =BE31 -> 9 | G31: Sonsón | H31: #N/D | I31: #N/D | J31: #N/D | K31: =IF($AQ31,"#N/D",IFERROR(INDEX(Olimpiadas!$A$2:$A$61,MATCH($AO31,Olimpiadas!$C$2:$C$61,0)),"#N/D")) -> #N/D | L31: =IF($AQ31,"#N/D",IFERROR(INDEX(Minculturas!$A$2:$A$48,MATCH($AO31,Minculturas!$C$2:$C$48,0)),"#N/D")) -> #N/D | M31: =IF($AQ31,"#N/D",IFERROR(INDEX(Minculturas!$B$2:$B$48,MATCH($AO31,Minculturas!$C$2:$C$48,0)),"#N/D")) -> #N/D | N31: 8 | O31: 0 | P31: 1 | Q31: 3 | R31: 0 | S31: 0 | T31: 4 | U31: 0 | V31: 0 | W31: 0 | X31: 0 | Y31: 0 | Z31: 0 | AA31: 0 | AB31: 0 | AC31: 0 | AD31: 0 | AE31: 0 | AF31: 0 | AG31: =SUM(O31:X31) -> 8 | AJ31: 37.9 | AM31: Declarado afectado; sin lugar con nombre propio publicado en este registro. | AO31: =TRIM(SUBSTITUTE(SUBSTITUTE(SUBSTITUTE(SUBSTITUTE(SUBSTITUTE(SUBSTITUTE(SUBSTITUTE(SUBSTITUTE(SUBSTITUTE(LOWER(G31),"á","a"),"é","e"),"í","i"),"ó","o"),"ú","u"),"ñ","n"),"-"," "),","," "),"."," ")) -> sonson | AP31: =TRIM(SUBSTITUTE(SUBSTITUTE(SUBSTITUTE(SUBSTITUTE(SUBSTITUTE(SUBSTITUTE(SUBSTITUTE(SUBSTITUTE(SUBSTITUTE(LOWER(B31),"á","a"),"é","e"),"í","i"),"ó","o"),"ú","u"),"ñ","n"),"-"," "),","," "),"."," ")) -> antioquia | AQ31: =COUNTIF($AO$2:$AO$433,AO31)>COUNTIFS($AO$2:$AO$433,AO31,$AP$2:$AP$433,AP31) -> FALSE | AR31: =IF(AQ31,AO31&"|"&AP31,AO31) -> sonson | AS31: =(I31<>"#N/D")+(J31<>"#N/D")+(L31<>"#N/D") -> 0 | AT31: =SUM(O31:X31) -> 8 | AU31: =IF(AT31<=$AY$2,0,IF(AT31<=$AY$3,1,IF(AT31<=$AY$4,2,3))) -> 3 | AV31: =IF(Y31<=$AY$7,3,IF(Y31<=$AY$8,2,IF(Y31<=$AY$9,1,0))) -> 3 | AZ31: =IF(Y31=0,3,0) -> 3 | BA31: =AS31+AU31+AZ31 -> 6 | BB31: =IFERROR(INDEX('Análisis general'!$E$4:$E$28,MATCH($B31,'Análisis general'!$B$4:$B$28,0)),"") -> 9.5 | BC31: =IF(BB31="","",IF(BB31<=$BG$2,0,IF(BB31<=$BG$3,1,IF(BB31<=$BG$4,2,3)))) -> 3 | BD31: =(AS31+AU31+AZ31+(BC31/2))*(9/10.5) -> 6.4285714 | BE31: =(AU31+AZ31+(BC31/2))*(9/7.5) -> 9
A32: 05390 | B32: Antioquia | C32: Sin clasificación oficial | D32: =AS32+AU32+AV32 -> 6 | E32: =BD32 -> 6.4285714 | F32: =BE32 -> 9 | G32: La Pintada | H32: =IFERROR(IF($AQ32,INDEX(cpe!$C$2:$C$307,MATCH($AR32,cpe!$F$2:$F$307,0)),INDEX(cpe!$C$2:$C$307,MATCH($AR32,cpe!$D$2:$D$307,0))),"#N/D") -> #N/D | I32: =IFERROR(IF($AQ32,INDEX(cpe!$B$2:$B$307,MATCH($AR32,cpe!$F$2:$F$307,0)),INDEX(cpe!$B$2:$B$307,MATCH($AR32,cpe!$D$2:$D$307,0))),"#N/D") -> #N/D | J32: =IF($AQ32,"#N/D",IFERROR(INDEX(Olimpiadas!$B$2:$B$61,MATCH($AO32,Olimpiadas!$C$2:$C$61,0)),"#N/D")) -> #N/D | K32: =IF($AQ32,"#N/D",IFERROR(INDEX(Olimpiadas!$A$2:$A$61,MATCH($AO32,Olimpiadas!$C$2:$C$61,0)),"#N/D")) -> #N/D | L32: =IF($AQ32,"#N/D",IFERROR(INDEX(Minculturas!$A$2:$A$48,MATCH($AO32,Minculturas!$C$2:$C$48,0)),"#N/D")) -> #N/D | M32: =IF($AQ32,"#N/D",IFERROR(INDEX(Minculturas!$B$2:$B$48,MATCH($AO32,Minculturas!$C$2:$C$48,0)),"#N/D")) -> #N/D | N32: 7 | O32: 0 | P32: 2 | Q32: 0 | R32: 0 | S32: 4 | T32: 0 | U32: 0 | V32: 1 | W32: 0 | X32: 0 | Y32: 0 | Z32: 0 | AA32: 0 | AB32: 0 | AC32: 0 | AD32: 0 | AE32: 0 | AF32: 0 | AG32: =SUM(O32:X32) -> 7 | AJ32: 31.2 | AM32: Declarado afectado; sin lugar con nombre propio publicado en este registro. | AO32: =TRIM(SUBSTITUTE(SUBSTITUTE(SUBSTITUTE(SUBSTITUTE(SUBSTITUTE(SUBSTITUTE(SUBSTITUTE(SUBSTITUTE(SUBSTITUTE(LOWER(G32),"á","a"),"é","e"),"í","i"),"ó","o"),"ú","u"),"ñ","n"),"-"," "),","," "),"."," ")) -> la pintada | AP32: =TRIM(SUBSTITUTE(SUBSTITUTE(SUBSTITUTE(SUBSTITUTE(SUBSTITUTE(SUBSTITUTE(SUBSTITUTE(SUBSTITUTE(SUBSTITUTE(LOWER(B32),"á","a"),"é","e"),"í","i"),"ó","o"),"ú","u"),"ñ","n"),"-"," "),","," "),"."," ")) -> antioquia | AQ32: =COUNTIF($AO$2:$AO$433,AO32)>COUNTIFS($AO$2:$AO$433,AO32,$AP$2:$AP$433,AP32) -> FALSE | AR32: =IF(AQ32,AO32&"|"&AP32,AO32) -> la pintada | AS32: =(I32<>"#N/D")+(J32<>"#N/D")+(L32<>"#N/D") -> 0 | AT32: =SUM(O32:X32) -> 7 | AU32: =IF(AT32<=$AY$2,0,IF(AT32<=$AY$3,1,IF(AT32<=$AY$4,2,3))) -> 3 | AV32: =IF(Y32<=$AY$7,3,IF(Y32<=$AY$8,2,IF(Y32<=$AY$9,1,0))) -> 3 | AZ32: =IF(Y32=0,3,0) -> 3 | BA32: =AS32+AU32+AZ32 -> 6 | BB32: =IFERROR(INDEX('Análisis general'!$E$4:$E$28,MATCH($B32,'Análisis general'!$B$4:$B$28,0)),"") -> 9.5 | BC32: =IF(BB32="","",IF(BB32<=$BG$2,0,IF(BB32<=$BG$3,1,IF(BB32<=$BG$4,2,3)))) -> 3 | BD32: =(AS32+AU32+AZ32+(BC32/2))*(9/10.5) -> 6.4285714 | BE32: =(AU32+AZ32+(BC32/2))*(9/7.5) -> 9
A33: 05631 | B33: Antioquia | C33: Sin clasificación oficial | D33: =AS33+AU33+AV33 -> 6 | E33: =BD33 -> 6.4285714 | F33: =BE33 -> 9 | G33: Sabaneta | H33: #N/D | I33: #N/D | J33: #N/D | K33: =IF($AQ33,"#N/D",IFERROR(INDEX(Olimpiadas!$A$2:$A$61,MATCH($AO33,Olimpiadas!$C$2:$C$61,0)),"#N/D")) -> #N/D | L33: =IF($AQ33,"#N/D",IFERROR(INDEX(Minculturas!$A$2:$A$48,MATCH($AO33,Minculturas!$C$2:$C$48,0)),"#N/D")) -> #N/D | M33: =IF($AQ33,"#N/D",IFERROR(INDEX(Minculturas!$B$2:$B$48,MATCH($AO33,Minculturas!$C$2:$C$48,0)),"#N/D")) -> #N/D | N33: 7 | O33: 0 | P33: 7 | Q33: 0 | R33: 0 | S33: 0 | T33: 0 | U33: 0 | V33: 0 | W33: 0 | X33: 0 | Y33: 0 | Z33: 0 | AA33: 0 | AB33: 0 | AC33: 0 | AD33: 0 | AE33: 0 | AF33: 0 | AG33: =SUM(O33:X33) -> 7 | AJ33: 4.5 | AM33: Declarado afectado; sin lugar con nombre propio publicado en este registro. | AO33: =TRIM(SUBSTITUTE(SUBSTITUTE(SUBSTITUTE(SUBSTITUTE(SUBSTITUTE(SUBSTITUTE(SUBSTITUTE(SUBSTITUTE(SUBSTITUTE(LOWER(G33),"á","a"),"é","e"),"í","i"),"ó","o"),"ú","u"),"ñ","n"),"-"," "),","," "),"."," ")) -> sabaneta | AP33: =TRIM(SUBSTITUTE(SUBSTITUTE(SUBSTITUTE(SUBSTITUTE(SUBSTITUTE(SUBSTITUTE(SUBSTITUTE(SUBSTITUTE(SUBSTITUTE(LOWER(B33),"á","a"),"é","e"),"í","i"),"ó","o"),"ú","u"),"ñ","n"),"-"," "),","," "),"."," ")) -> antioquia | AQ33: =COUNTIF($AO$2:$AO$433,AO33)>COUNTIFS($AO$2:$AO$433,AO33,$AP$2:$AP$433,AP33) -> FALSE | AR33: =IF(AQ33,AO33&"|"&AP33,AO33) -> sabaneta | AS33: =(I33<>"#N/D")+(J33<>"#N/D")+(L33<>"#N/D") -> 0 | AT33: =SUM(O33:X33) -> 7 | AU33: =IF(AT33<=$AY$2,0,IF(AT33<=$AY$3,1,IF(AT33<=$AY$4,2,3))) -> 3 | AV33: =IF(Y33<=$AY$7,3,IF(Y33<=$AY$8,2,IF(Y33<=$AY$9,1,0))) -> 3 | AZ33: =IF(Y33=0,3,0) -> 3 | BA33: =AS33+AU33+AZ33 -> 6 | BB33: =IFERROR(INDEX('Análisis general'!$E$4:$E$28,MATCH($B33,'Análisis general'!$B$4:$B$28,0)),"") -> 9.5 | BC33: =IF(BB33="","",IF(BB33<=$BG$2,0,IF(BB33<=$BG$3,1,IF(BB33<=$BG$4,2,3)))) -> 3 | BD33: =(AS33+AU33+AZ33+(BC33/2))*(9/10.5) -> 6.4285714 | BE33: =(AU33+AZ33+(BC33/2))*(9/7.5) -> 9
A34: 05364 | B34: Antioquia | C34: Sin clasificación oficial | D34: =AS34+AU34+AV34 -> 6 | E34: =BD34 -> 6.4285714 | F34: =BE34 -> 9 | G34: Jardín | H34: =IFERROR(IF($AQ34,INDEX(cpe!$C$2:$C$307,MATCH($AR34,cpe!$F$2:$F$307,0)),INDEX(cpe!$C$2:$C$307,MATCH($AR34,cpe!$D$2:$D$307,0))),"#N/D") -> #N/D | I34: =IFERROR(IF($AQ34,INDEX(cpe!$B$2:$B$307,MATCH($AR34,cpe!$F$2:$F$307,0)),INDEX(cpe!$B$2:$B$307,MATCH($AR34,cpe!$D$2:$D$307,0))),"#N/D") -> #N/D | J34: =IF($AQ34,"#N/D",IFERROR(INDEX(Olimpiadas!$B$2:$B$61,MATCH($AO34,Olimpiadas!$C$2:$C$61,0)),"#N/D")) -> #N/D | K34: =IF($AQ34,"#N/D",IFERROR(INDEX(Olimpiadas!$A$2:$A$61,MATCH($AO34,Olimpiadas!$C$2:$C$61,0)),"#N/D")) -> #N/D | L34: =IF($AQ34,"#N/D",IFERROR(INDEX(Minculturas!$A$2:$A$48,MATCH($AO34,Minculturas!$C$2:$C$48,0)),"#N/D")) -> #N/D | M34: =IF($AQ34,"#N/D",IFERROR(INDEX(Minculturas!$B$2:$B$48,MATCH($AO34,Minculturas!$C$2:$C$48,0)),"#N/D")) -> #N/D | N34: 9 | O34: 0 | P34: 1 | Q34: 1 | R34: 0 | S34: 0 | T34: 4 | U34: 0 | V34: 0 | W34: 0 | X34: 0 | Y34: 0 | Z34: 0 | AA34: 0 | AB34: 2 | AC34: 1 | AD34: 0 | AE34: 0 | AF34: 0 | AG34: =SUM(O34:X34) -> 6 | AJ34: 28.5 | AM34: Declarado afectado; sin lugar con nombre propio publicado en este registro. | AO34: =TRIM(SUBSTITUTE(SUBSTITUTE(SUBSTITUTE(SUBSTITUTE(SUBSTITUTE(SUBSTITUTE(SUBSTITUTE(SUBSTITUTE(SUBSTITUTE(LOWER(G34),"á","a"),"é","e"),"í","i"),"ó","o"),"ú","u"),"ñ","n"),"-"," "),","," "),"."," ")) -> jardin | AP34: =TRIM(SUBSTITUTE(SUBSTITUTE(SUBSTITUTE(SUBSTITUTE(SUBSTITUTE(SUBSTITUTE(SUBSTITUTE(SUBSTITUTE(SUBSTITUTE(LOWER(B34),"á","a"),"é","e"),"í","i"),"ó","o"),"ú","u"),"ñ","n"),"-"," "),","," "),"."," ")) -> antioquia | AQ34: =COUNTIF($AO$2:$AO$433,AO34)>COUNTIFS($AO$2:$AO$433,AO34,$AP$2:$AP$433,AP34) -> FALSE | AR34: =IF(AQ34,AO34&"|"&AP34,AO34) -> jardin | AS34: =(I34<>"#N/D")+(J34<>"#N/D")+(L34<>"#N/D") -> 0 | AT34: =SUM(O34:X34) -> 6 | AU34: =IF(AT34<=$AY$2,0,IF(AT34<=$AY$3,1,IF(AT34<=$AY$4,2,3))) -> 3 | AV34: =IF(Y34<=$AY$7,3,IF(Y34<=$AY$8,2,IF(Y34<=$AY$9,1,0))) -> 3 | AZ34: =IF(Y34=0,3,0) -> 3 | BA34: =AS34+AU34+AZ34 -> 6 | BB34: =IFERROR(INDEX('Análisis general'!$E$4:$E$28,MATCH($B34,'Análisis general'!$B$4:$B$28,0)),"") -> 9.5 | BC34: =IF(BB34="","",IF(BB34<=$BG$2,0,IF(BB34<=$BG$3,1,IF(BB34<=$BG$4,2,3)))) -> 3 | BD34: =(AS34+AU34+AZ34+(BC34/2))*(9/10.5) -> 6.4285714 | BE34: =(AU34+AZ34+(BC34/2))*(9/7.5) -> 9
A35: 05368 | B35: Antioquia | C35: Sin clasificación oficial | D35: =AS35+AU35+AV35 -> 6 | E35: =BD35 -> 6.4285714 | F35: =BE35 -> 9 | G35: Jericó | H35: =IFERROR(IF($AQ35,INDEX(cpe!$C$2:$C$307,MATCH($AR35,cpe!$F$2:$F$307,0)),INDEX(cpe!$C$2:$C$307,MATCH($AR35,cpe!$D$2:$D$307,0))),"#N/D") -> #N/D | I35: =IFERROR(IF($AQ35,INDEX(cpe!$B$2:$B$307,MATCH($AR35,cpe!$F$2:$F$307,0)),INDEX(cpe!$B$2:$B$307,MATCH($AR35,cpe!$D$2:$D$307,0))),"#N/D") -> #N/D | J35: =IF($AQ35,"#N/D",IFERROR(INDEX(Olimpiadas!$B$2:$B$61,MATCH($AO35,Olimpiadas!$C$2:$C$61,0)),"#N/D")) -> #N/D | K35: =IF($AQ35,"#N/D",IFERROR(INDEX(Olimpiadas!$A$2:$A$61,MATCH($AO35,Olimpiadas!$C$2:$C$61,0)),"#N/D")) -> #N/D | L35: =IF($AQ35,"#N/D",IFERROR(INDEX(Minculturas!$A$2:$A$48,MATCH($AO35,Minculturas!$C$2:$C$48,0)),"#N/D")) -> #N/D | M35: =IF($AQ35,"#N/D",IFERROR(INDEX(Minculturas!$B$2:$B$48,MATCH($AO35,Minculturas!$C$2:$C$48,0)),"#N/D")) -> #N/D | N35: 6 | O35: 0 | P35: 2 | Q35: 1 | R35: 0 | S35: 0 | T35: 3 | U35: 0 | V35: 0 | W35: 0 | X35: 0 | Y35: 0 | Z35: 0 | AA35: 0 | AB35: 0 | AC35: 0 | AD35: 0 | AE35: 0 | AF35: 0 | AG35: =SUM(O35:X35) -> 6 | AJ35: 25.8 | AM35: Declarado afectado; sin lugar con nombre propio publicado en este registro. | AO35: =TRIM(SUBSTITUTE(SUBSTITUTE(SUBSTITUTE(SUBSTITUTE(SUBSTITUTE(SUBSTITUTE(SUBSTITUTE(SUBSTITUTE(SUBSTITUTE(LOWER(G35),"á","a"),"é","e"),"í","i"),"ó","o"),"ú","u"),"ñ","n"),"-"," "),","," "),"."," ")) -> jerico | AP35: =TRIM(SUBSTITUTE(SUBSTITUTE(SUBSTITUTE(SUBSTITUTE(SUBSTITUTE(SUBSTITUTE(SUBSTITUTE(SUBSTITUTE(SUBSTITUTE(LOWER(B35),"á","a"),"é","e"),"í","i"),"ó","o"),"ú","u"),"ñ","n"),"-"," "),","," "),"."," ")) -> antioquia | AQ35: =COUNTIF($AO$2:$AO$433,AO35)>COUNTIFS($AO$2:$AO$433,AO35,$AP$2:$AP$433,AP35) -> FALSE | AR35: =IF(AQ35,AO35&"|"&AP35,AO35) -> jerico | AS35: =(I35<>"#N/D")+(J35<>"#N/D")+(L35<>"#N/D") -> 0 | AT35: =SUM(O35:X35) -> 6 | AU35: =IF(AT35<=$AY$2,0,IF(AT35<=$AY$3,1,IF(AT35<=$AY$4,2,3))) -> 3 | AV35: =IF(Y35<=$AY$7,3,IF(Y35<=$AY$8,2,IF(Y35<=$AY$9,1,0))) -> 3 | AZ35: =IF(Y35=0,3,0) -> 3 | BA35: =AS35+AU35+AZ35 -> 6 | BB35: =IFERROR(INDEX('Análisis general'!$E$4:$E$28,MATCH($B35,'Análisis general'!$B$4:$B$28,0)),"") -> 9.5 | BC35: =IF(BB35="","",IF(BB35<=$BG$2,0,IF(BB35<=$BG$3,1,IF(BB35<=$BG$4,2,3)))) -> 3 | BD35: =(AS35+AU35+AZ35+(BC35/2))*(9/10.5) -> 6.4285714 | BE35: =(AU35+AZ35+(BC35/2))*(9/7.5) -> 9
A36: 17662 | B36: Caldas | C36: Sin clasificación oficial | D36: =AS36+AU36+AV36 -> 6 | E36: =BD36 -> 6.4285714 | F36: =BE36 -> 9 | G36: Samaná | H36: #N/D | I36: #N/D | J36: #N/D | K36: =IF($AQ36,"#N/D",IFERROR(INDEX(Olimpiadas!$A$2:$A$61,MATCH($AO36,Olimpiadas!$C$2:$C$61,0)),"#N/D")) -> #N/D | L36: =IF($AQ36,"#N/D",IFERROR(INDEX(Minculturas!$A$2:$A$48,MATCH($AO36,Minculturas!$C$2:$C$48,0)),"#N/D")) -> #N/D | M36: =IF($AQ36,"#N/D",IFERROR(INDEX(Minculturas!$B$2:$B$48,MATCH($AO36,Minculturas!$C$2:$C$48,0)),"#N/D")) -> #N/D | N36: 5 | O36: 0 | P36: 0 | Q36: 1 | R36: 0 | S36: 3 | T36: 0 | U36: 1 | V36: 0 | W36: 0 | X36: 0 | Y36: 0 | Z36: 0 | AA36: 0 | AB36: 0 | AC36: 0 | AD36: 0 | AE36: 0 | AF36: 0 | AG36: =SUM(O36:X36) -> 5 | AJ36: 39.9 | AM36: Declarado afectado; sin lugar con nombre propio publicado en este registro. | AO36: =TRIM(SUBSTITUTE(SUBSTITUTE(SUBSTITUTE(SUBSTITUTE(SUBSTITUTE(SUBSTITUTE(SUBSTITUTE(SUBSTITUTE(SUBSTITUTE(LOWER(G36),"á","a"),"é","e"),"í","i"),"ó","o"),"ú","u"),"ñ","n"),"-"," "),","," "),"."," ")) -> samana | AP36: =TRIM(SUBSTITUTE(SUBSTITUTE(SUBSTITUTE(SUBSTITUTE(SUBSTITUTE(SUBSTITUTE(SUBSTITUTE(SUBSTITUTE(SUBSTITUTE(LOWER(B36),"á","a"),"é","e"),"í","i"),"ó","o"),"ú","u"),"ñ","n"),"-"," "),","," "),"."," ")) -> caldas | AQ36: =COUNTIF($AO$2:$AO$433,AO36)>COUNTIFS($AO$2:$AO$433,AO36,$AP$2:$AP$433,AP36) -> FALSE | AR36: =IF(AQ36,AO36&"|"&AP36,AO36) -> samana | AS36: =(I36<>"#N/D")+(J36<>"#N/D")+(L36<>"#N/D") -> 0 | AT36: =SUM(O36:X36) -> 5 | AU36: =IF(AT36<=$AY$2,0,IF(AT36<=$AY$3,1,IF(AT36<=$AY$4,2,3))) -> 3 | AV36: =IF(Y36<=$AY$7,3,IF(Y36<=$AY$8,2,IF(Y36<=$AY$9,1,0))) -> 3 | AZ36: =IF(Y36=0,3,0) -> 3 | BA36: =AS36+AU36+AZ36 -> 6 | BB36: =IFERROR(INDEX('Análisis general'!$E$4:$E$28,MATCH($B36,'Análisis general'!$B$4:$B$28,0)),"") -> 7.9 | BC36: =IF(BB36="","",IF(BB36<=$BG$2,0,IF(BB36<=$BG$3,1,IF(BB36<=$BG$4,2,3)))) -> 3 | BD36: =(AS36+AU36+AZ36+(BC36/2))*(9/10.5) -> 6.4285714 | BE36: =(AU36+AZ36+(BC36/2))*(9/7.5) -> 9
A37: 05055 | B37: Cauca | C37: Sin clasificación oficial | D37: =AS37+AU37+AV37 -> 6 | E37: =BD37 -> 6.4285714 | F37: =BE37 -> 9 | G37: Argelia | H37: =IFERROR(IF($AQ37,INDEX(cpe!$C$2:$C$307,MATCH($AR37,cpe!$F$2:$F$307,0)),INDEX(cpe!$C$2:$C$307,MATCH($AR37,cpe!$D$2:$D$307,0))),"#N/D") -> #N/D | I37: =IFERROR(IF($AQ37,INDEX(cpe!$B$2:$B$307,MATCH($AR37,cpe!$F$2:$F$307,0)),INDEX(cpe!$B$2:$B$307,MATCH($AR37,cpe!$D$2:$D$307,0))),"#N/D") -> #N/D | J37: =IF($AQ37,"#N/D",IFERROR(INDEX(Olimpiadas!$B$2:$B$61,MATCH($AO37,Olimpiadas!$C$2:$C$61,0)),"#N/D")) -> #N/D | K37: =IF($AQ37,"#N/D",IFERROR(INDEX(Olimpiadas!$A$2:$A$61,MATCH($AO37,Olimpiadas!$C$2:$C$61,0)),"#N/D")) -> #N/D | L37: =IF($AQ37,"#N/D",IFERROR(INDEX(Minculturas!$A$2:$A$48,MATCH($AO37,Minculturas!$C$2:$C$48,0)),"#N/D")) -> #N/D | M37: =IF($AQ37,"#N/D",IFERROR(INDEX(Minculturas!$B$2:$B$48,MATCH($AO37,Minculturas!$C$2:$C$48,0)),"#N/D")) -> #N/D | N37: 5 | O37: 0 | P37: 0 | Q37: 1 | R37: 0 | S37: 1 | T37: 1 | U37: 1 | V37: 0 | W37: 0 | X37: 0 | Y37: 0 | Z37: 0 | AA37: 0 | AB37: 1 | AC37: 0 | AD37: 0 | AE37: 0 | AF37: 0 | AG37: =SUM(O37:X37) -> 4 | AJ37: 48.7 | AM37: Declarado afectado; sin lugar con nombre propio publicado en este registro. | AO37: =TRIM(SUBSTITUTE(SUBSTITUTE(SUBSTITUTE(SUBSTITUTE(SUBSTITUTE(SUBSTITUTE(SUBSTITUTE(SUBSTITUTE(SUBSTITUTE(LOWER(G37),"á","a"),"é","e"),"í","i"),"ó","o"),"ú","u"),"ñ","n"),"-"," "),","," "),"."," ")) -> argelia | AP37: =TRIM(SUBSTITUTE(SUBSTITUTE(SUBSTITUTE(SUBSTITUTE(SUBSTITUTE(SUBSTITUTE(SUBSTITUTE(SUBSTITUTE(SUBSTITUTE(LOWER(B37),"á","a"),"é","e"),"í","i"),"ó","o"),"ú","u"),"ñ","n"),"-"," "),","," "),"."," ")) -> cauca | AQ37: =COUNTIF($AO$2:$AO$433,AO37)>COUNTIFS($AO$2:$AO$433,AO37,$AP$2:$AP$433,AP37) -> TRUE | AR37: =IF(AQ37,AO37&"|"&AP37,AO37) -> argelia|cauca | AS37: =(I37<>"#N/D")+(J37<>"#N/D")+(L37<>"#N/D") -> 0 | AT37: =SUM(O37:X37) -> 4 | AU37: =IF(AT37<=$AY$2,0,IF(AT37<=$AY$3,1,IF(AT37<=$AY$4,2,3))) -> 3 | AV37: =IF(Y37<=$AY$7,3,IF(Y37<=$AY$8,2,IF(Y37<=$AY$9,1,0))) -> 3 | AZ37: =IF(Y37=0,3,0) -> 3 | BA37: =AS37+AU37+AZ37 -> 6 | BB37: =IFERROR(INDEX('Análisis general'!$E$4:$E$28,MATCH($B37,'Análisis general'!$B$4:$B$28,0)),"") -> 13 | BC37: =IF(BB37="","",IF(BB37<=$BG$2,0,IF(BB37<=$BG$3,1,IF(BB37<=$BG$4,2,3)))) -> 3 | BD37: =(AS37+AU37+AZ37+(BC37/2))*(9/10.5) -> 6.4285714 | BE37: =(AU37+AZ37+(BC37/2))*(9/7.5) -> 9
A38: 27160 | B38: Chocó | C38: Sin clasificación oficial | D38: =AS38+AU38+AV38 -> 6 | E38: =BD38 -> 6.4285714 | F38: =BE38 -> 9 | G38: Cértegui | H38: =IFERROR(IF($AQ38,INDEX(cpe!$C$2:$C$307,MATCH($AR38,cpe!$F$2:$F$307,0)),INDEX(cpe!$C$2:$C$307,MATCH($AR38,cpe!$D$2:$D$307,0))),"#N/D") -> #N/D | I38: =IFERROR(IF($AQ38,INDEX(cpe!$B$2:$B$307,MATCH($AR38,cpe!$F$2:$F$307,0)),INDEX(cpe!$B$2:$B$307,MATCH($AR38,cpe!$D$2:$D$307,0))),"#N/D") -> #N/D | J38: =IF($AQ38,"#N/D",IFERROR(INDEX(Olimpiadas!$B$2:$B$61,MATCH($AO38,Olimpiadas!$C$2:$C$61,0)),"#N/D")) -> #N/D | K38: =IF($AQ38,"#N/D",IFERROR(INDEX(Olimpiadas!$A$2:$A$61,MATCH($AO38,Olimpiadas!$C$2:$C$61,0)),"#N/D")) -> #N/D | L38: =IF($AQ38,"#N/D",IFERROR(INDEX(Minculturas!$A$2:$A$48,MATCH($AO38,Minculturas!$C$2:$C$48,0)),"#N/D")) -> #N/D | M38: =IF($AQ38,"#N/D",IFERROR(INDEX(Minculturas!$B$2:$B$48,MATCH($AO38,Minculturas!$C$2:$C$48,0)),"#N/D")) -> #N/D | N38: 5 | O38: 0 | P38: 1 | Q38: 0 | R38: 0 | S38: 2 | T38: 0 | U38: 1 | V38: 0 | W38: 0 | X38: 0 | Y38: 0 | Z38: 1 | AA38: 0 | AB38: 0 | AC38: 0 | AD38: 0 | AE38: 0 | AF38: 0 | AG38: =SUM(O38:X38) -> 4 | AJ38: 55.9 | AM38: Declarado afectado; sin lugar con nombre propio publicado en este registro. | AO38: =TRIM(SUBSTITUTE(SUBSTITUTE(SUBSTITUTE(SUBSTITUTE(SUBSTITUTE(SUBSTITUTE(SUBSTITUTE(SUBSTITUTE(SUBSTITUTE(LOWER(G38),"á","a"),"é","e"),"í","i"),"ó","o"),"ú","u"),"ñ","n"),"-"," "),","," "),"."," ")) -> certegui | AP38: =TRIM(SUBSTITUTE(SUBSTITUTE(SUBSTITUTE(SUBSTITUTE(SUBSTITUTE(SUBSTITUTE(SUBSTITUTE(SUBSTITUTE(SUBSTITUTE(LOWER(B38),"á","a"),"é","e"),"í","i"),"ó","o"),"ú","u"),"ñ","n"),"-"," "),","," "),"."," ")) -> choco | AQ38: =COUNTIF($AO$2:$AO$433,AO38)>COUNTIFS($AO$2:$AO$433,AO38,$AP$2:$AP$433,AP38) -> FALSE | AR38: =IF(AQ38,AO38&"|"&AP38,AO38) -> certegui | AS38: =(I38<>"#N/D")+(J38<>"#N/D")+(L38<>"#N/D") -> 0 | AT38: =SUM(O38:X38) -> 4 | AU38: =IF(AT38<=$AY$2,0,IF(AT38<=$AY$3,1,IF(AT38<=$AY$4,2,3))) -> 3 | AV38: =IF(Y38<=$AY$7,3,IF(Y38<=$AY$8,2,IF(Y38<=$AY$9,1,0))) -> 3 | AZ38: =IF(Y38=0,3,0) -> 3 | BA38: =AS38+AU38+AZ38 -> 6 | BB38: =IFERROR(INDEX('Análisis general'!$E$4:$E$28,MATCH($B38,'Análisis general'!$B$4:$B$28,0)),"") -> 30.8 | BC38: =IF(BB38="","",IF(BB38<=$BG$2,0,IF(BB38<=$BG$3,1,IF(BB38<=$BG$4,2,3)))) -> 3 | BD38: =(AS38+AU38+AZ38+(BC38/2))*(9/10.5) -> 6.4285714 | BE38: =(AU38+AZ38+(BC38/2))*(9/7.5) -> 9
A39: 19473 | B39: Cauca | C39: Sin clasificación oficial | D39: =AS39+AU39+AV39 -> 6 | E39: =BD39 -> 6.4285714 | F39: =BE39 -> 9 | G39: Morales | H39: =IFERROR(IF($AQ39,INDEX(cpe!$C$2:$C$307,MATCH($AR39,cpe!$F$2:$F$307,0)),INDEX(cpe!$C$2:$C$307,MATCH($AR39,cpe!$D$2:$D$307,0))),"#N/D") -> #N/D | I39: =IFERROR(IF($AQ39,INDEX(cpe!$B$2:$B$307,MATCH($AR39,cpe!$F$2:$F$307,0)),INDEX(cpe!$B$2:$B$307,MATCH($AR39,cpe!$D$2:$D$307,0))),"#N/D") -> #N/D | J39: =IF($AQ39,"#N/D",IFERROR(INDEX(Olimpiadas!$B$2:$B$61,MATCH($AO39,Olimpiadas!$C$2:$C$61,0)),"#N/D")) -> #N/D | K39: =IF($AQ39,"#N/D",IFERROR(INDEX(Olimpiadas!$A$2:$A$61,MATCH($AO39,Olimpiadas!$C$2:$C$61,0)),"#N/D")) -> #N/D | L39: =IF($AQ39,"#N/D",IFERROR(INDEX(Minculturas!$A$2:$A$48,MATCH($AO39,Minculturas!$C$2:$C$48,0)),"#N/D")) -> #N/D | M39: =IF($AQ39,"#N/D",IFERROR(INDEX(Minculturas!$B$2:$B$48,MATCH($AO39,Minculturas!$C$2:$C$48,0)),"#N/D")) -> #N/D | N39: 4 | O39: 0 | P39: 2 | Q39: 0 | R39: 0 | S39: 0 | T39: 1 | U39: 0 | V39: 0 | W39: 0 | X39: 1 | Y39: 0 | Z39: 0 | AA39: 0 | AB39: 0 | AC39: 0 | AD39: 0 | AE39: 0 | AF39: 0 | AG39: =SUM(O39:X39) -> 4 | AJ39: 48.7 | AM39: Declarado afectado; sin lugar con nombre propio publicado en este registro. | AO39: =TRIM(SUBSTITUTE(SUBSTITUTE(SUBSTITUTE(SUBSTITUTE(SUBSTITUTE(SUBSTITUTE(SUBSTITUTE(SUBSTITUTE(SUBSTITUTE(LOWER(G39),"á","a"),"é","e"),"í","i"),"ó","o"),"ú","u"),"ñ","n"),"-"," "),","," "),"."," ")) -> morales | AP39: =TRIM(SUBSTITUTE(SUBSTITUTE(SUBSTITUTE(SUBSTITUTE(SUBSTITUTE(SUBSTITUTE(SUBSTITUTE(SUBSTITUTE(SUBSTITUTE(LOWER(B39),"á","a"),"é","e"),"í","i"),"ó","o"),"ú","u"),"ñ","n"),"-"," "),","," "),"."," ")) -> cauca | AQ39: =COUNTIF($AO$2:$AO$433,AO39)>COUNTIFS($AO$2:$AO$433,AO39,$AP$2:$AP$433,AP39) -> FALSE | AR39: =IF(AQ39,AO39&"|"&AP39,AO39) -> morales | AS39: =(I39<>"#N/D")+(J39<>"#N/D")+(L39<>"#N/D") -> 0 | AT39: =SUM(O39:X39) -> 4 | AU39: =IF(AT39<=$AY$2,0,IF(AT39<=$AY$3,1,IF(AT39<=$AY$4,2,3))) -> 3 | AV39: =IF(Y39<=$AY$7,3,IF(Y39<=$AY$8,2,IF(Y39<=$AY$9,1,0))) -> 3 | AZ39: =IF(Y39=0,3,0) -> 3 | BA39: =AS39+AU39+AZ39 -> 6 | BB39: =IFERROR(INDEX('Análisis general'!$E$4:$E$28,MATCH($B39,'Análisis general'!$B$4:$B$28,0)),"") -> 13 | BC39: =IF(BB39="","",IF(BB39<=$BG$2,0,IF(BB39<=$BG$3,1,IF(BB39<=$BG$4,2,3)))) -> 3 | BD39: =(AS39+AU39+AZ39+(BC39/2))*(9/10.5) -> 6.4285714 | BE39: =(AU39+AZ39+(BC39/2))*(9/7.5) -> 9
A40: 27025 | B40: Chocó | C40: Sin clasificación oficial | D40: =AS40+AU40+AV40 -> 6 | E40: =BD40 -> 6.4285714 | F40: =BE40 -> 9 | G40: Alto Baudó | H40: =IFERROR(IF($AQ40,INDEX(cpe!$C$2:$C$307,MATCH($AR40,cpe!$F$2:$F$307,0)),INDEX(cpe!$C$2:$C$307,MATCH($AR40,cpe!$D$2:$D$307,0))),"#N/D") -> #N/D | I40: =IFERROR(IF($AQ40,INDEX(cpe!$B$2:$B$307,MATCH($AR40,cpe!$F$2:$F$307,0)),INDEX(cpe!$B$2:$B$307,MATCH($AR40,cpe!$D$2:$D$307,0))),"#N/D") -> #N/D | J40: =IF($AQ40,"#N/D",IFERROR(INDEX(Olimpiadas!$B$2:$B$61,MATCH($AO40,Olimpiadas!$C$2:$C$61,0)),"#N/D")) -> #N/D | K40: =IF($AQ40,"#N/D",IFERROR(INDEX(Olimpiadas!$A$2:$A$61,MATCH($AO40,Olimpiadas!$C$2:$C$61,0)),"#N/D")) -> #N/D | L40: =IF($AQ40,"#N/D",IFERROR(INDEX(Minculturas!$A$2:$A$48,MATCH($AO40,Minculturas!$C$2:$C$48,0)),"#N/D")) -> #N/D | M40: =IF($AQ40,"#N/D",IFERROR(INDEX(Minculturas!$B$2:$B$48,MATCH($AO40,Minculturas!$C$2:$C$48,0)),"#N/D")) -> #N/D | N40: 4 | O40: 0 | P40: 1 | Q40: 0 | R40: 1 | S40: 1 | T40: 0 | U40: 0 | V40: 0 | W40: 0 | X40: 0 | Y40: 0 | Z40: 1 | AA40: 0 | AB40: 0 | AC40: 0 | AD40: 0 | AE40: 0 | AF40: 0 | AG40: =SUM(O40:X40) -> 3 | AH40: 340 | AI40: 784 | AJ40: 90.6 | AM40: Declarado afectado; sin lugar con nombre propio publicado en este registro. | AO40: =TRIM(SUBSTITUTE(SUBSTITUTE(SUBSTITUTE(SUBSTITUTE(SUBSTITUTE(SUBSTITUTE(SUBSTITUTE(SUBSTITUTE(SUBSTITUTE(LOWER(G40),"á","a"),"é","e"),"í","i"),"ó","o"),"ú","u"),"ñ","n"),"-"," "),","," "),"."," ")) -> alto baudo | AP40: =TRIM(SUBSTITUTE(SUBSTITUTE(SUBSTITUTE(SUBSTITUTE(SUBSTITUTE(SUBSTITUTE(SUBSTITUTE(SUBSTITUTE(SUBSTITUTE(LOWER(B40),"á","a"),"é","e"),"í","i"),"ó","o"),"ú","u"),"ñ","n"),"-"," "),","," "),"."," ")) -> choco | AQ40: =COUNTIF($AO$2:$AO$433,AO40)>COUNTIFS($AO$2:$AO$433,AO40,$AP$2:$AP$433,AP40) -> FALSE | AR40: =IF(AQ40,AO40&"|"&AP40,AO40) -> alto baudo | AS40: =(I40<>"#N/D")+(J40<>"#N/D")+(L40<>"#N/D") -> 0 | AT40: =SUM(O40:X40) -> 3 | AU40: =IF(AT40<=$AY$2,0,IF(AT40<=$AY$3,1,IF(AT40<=$AY$4,2,3))) -> 3 | AV40: =IF(Y40<=$AY$7,3,IF(Y40<=$AY$8,2,IF(Y40<=$AY$9,1,0))) -> 3 | AZ40: =IF(Y40=0,3,0) -> 3 | BA40: =AS40+AU40+AZ40 -> 6 | BB40: =IFERROR(INDEX('Análisis general'!$E$4:$E$28,MATCH($B40,'Análisis general'!$B$4:$B$28,0)),"") -> 30.8 | BC40: =IF(BB40="","",IF(BB40<=$BG$2,0,IF(BB40<=$BG$3,1,IF(BB40<=$BG$4,2,3)))) -> 3 | BD40: =(AS40+AU40+AZ40+(BC40/2))*(9/10.5) -> 6.4285714 | BE40: =(AU40+AZ40+(BC40/2))*(9/7.5) -> 9
A41: 52240 | B41: Nariño | C41: Sin clasificación oficial | D41: =AS41+AU41+AV41 -> 6 | E41: =BD41 -> 6.4285714 | F41: =BE41 -> 9 | G41: Chachagüí | H41: =IFERROR(IF($AQ41,INDEX(cpe!$C$2:$C$307,MATCH($AR41,cpe!$F$2:$F$307,0)),INDEX(cpe!$C$2:$C$307,MATCH($AR41,cpe!$D$2:$D$307,0))),"#N/D") -> #N/D | I41: =IFERROR(IF($AQ41,INDEX(cpe!$B$2:$B$307,MATCH($AR41,cpe!$F$2:$F$307,0)),INDEX(cpe!$B$2:$B$307,MATCH($AR41,cpe!$D$2:$D$307,0))),"#N/D") -> #N/D | J41: =IF($AQ41,"#N/D",IFERROR(INDEX(Olimpiadas!$B$2:$B$61,MATCH($AO41,Olimpiadas!$C$2:$C$61,0)),"#N/D")) -> #N/D | K41: =IF($AQ41,"#N/D",IFERROR(INDEX(Olimpiadas!$A$2:$A$61,MATCH($AO41,Olimpiadas!$C$2:$C$61,0)),"#N/D")) -> #N/D | L41: =IF($AQ41,"#N/D",IFERROR(INDEX(Minculturas!$A$2:$A$48,MATCH($AO41,Minculturas!$C$2:$C$48,0)),"#N/D")) -> #N/D | M41: =IF($AQ41,"#N/D",IFERROR(INDEX(Minculturas!$B$2:$B$48,MATCH($AO41,Minculturas!$C$2:$C$48,0)),"#N/D")) -> #N/D | N41: 3 | O41: 0 | P41: 0 | Q41: 1 | R41: 0 | S41: 0 | T41: 1 | U41: 0 | V41: 0 | W41: 1 | X41: 0 | Y41: 0 | Z41: 0 | AA41: 0 | AB41: 0 | AC41: 0 | AD41: 0 | AE41: 0 | AF41: 0 | AG41: =SUM(O41:X41) -> 3 | AJ41: 32.2 | AM41: Declarado afectado; sin lugar con nombre propio publicado en este registro. | AO41: =TRIM(SUBSTITUTE(SUBSTITUTE(SUBSTITUTE(SUBSTITUTE(SUBSTITUTE(SUBSTITUTE(SUBSTITUTE(SUBSTITUTE(SUBSTITUTE(LOWER(G41),"á","a"),"é","e"),"í","i"),"ó","o"),"ú","u"),"ñ","n"),"-"," "),","," "),"."," ")) -> chachagüi | AP41: =TRIM(SUBSTITUTE(SUBSTITUTE(SUBSTITUTE(SUBSTITUTE(SUBSTITUTE(SUBSTITUTE(SUBSTITUTE(SUBSTITUTE(SUBSTITUTE(LOWER(B41),"á","a"),"é","e"),"í","i"),"ó","o"),"ú","u"),"ñ","n"),"-"," "),","," "),"."," ")) -> narino | AQ41: =COUNTIF($AO$2:$AO$433,AO41)>COUNTIFS($AO$2:$AO$433,AO41,$AP$2:$AP$433,AP41) -> FALSE | AR41: =IF(AQ41,AO41&"|"&AP41,AO41) -> chachagüi | AS41: =(I41<>"#N/D")+(J41<>"#N/D")+(L41<>"#N/D") -> 0 | AT41: =SUM(O41:X41) -> 3 | AU41: =IF(AT41<=$AY$2,0,IF(AT41<=$AY$3,1,IF(AT41<=$AY$4,2,3))) -> 3 | AV41: =IF(Y41<=$AY$7,3,IF(Y41<=$AY$8,2,IF(Y41<=$AY$9,1,0))) -> 3 | AZ41: =IF(Y41=0,3,0) -> 3 | BA41: =AS41+AU41+AZ41 -> 6 | BB41: =IFERROR(INDEX('Análisis general'!$E$4:$E$28,MATCH($B41,'Análisis general'!$B$4:$B$28,0)),"") -> 13.2 | BC41: =IF(BB41="","",IF(BB41<=$BG$2,0,IF(BB41<=$BG$3,1,IF(BB41<=$BG$4,2,3)))) -> 3 | BD41: =(AS41+AU41+AZ41+(BC41/2))*(9/10.5) -> 6.4285714 | BE41: =(AU41+AZ41+(BC41/2))*(9/7.5) -> 9
A42: 27580 | B42: Chocó | C42: Afectación muy alta | D42: =AS42+AU42+AV42 -> 6 | E42: =BD42 -> 6.4285714 | F42: =BE42 -> 9 | G42: Río Iró | H42: #N/D | I42: #N/D | J42: #N/D | K42: =IF($AQ42,"#N/D",IFERROR(INDEX(Olimpiadas!$A$2:$A$61,MATCH($AO42,Olimpiadas!$C$2:$C$61,0)),"#N/D")) -> #N/D | L42: =IF($AQ42,"#N/D",IFERROR(INDEX(Minculturas!$A$2:$A$48,MATCH($AO42,Minculturas!$C$2:$C$48,0)),"#N/D")) -> #N/D | M42: =IF($AQ42,"#N/D",IFERROR(INDEX(Minculturas!$B$2:$B$48,MATCH($AO42,Minculturas!$C$2:$C$48,0)),"#N/D")) -> #N/D | N42: 3 | O42: 0 | P42: 0 | Q42: 0 | R42: 0 | S42: 0 | T42: 0 | U42: 0 | V42: 0 | W42: 0 | X42: 2 | Y42: 0 | Z42: 0 | AA42: 0 | AB42: 1 | AC42: 0 | AD42: 0 | AE42: 0 | AF42: 0 | AG42: =SUM(O42:X42) -> 2 | AH42: 133 | AI42: 489 | AJ42: 75.1 | AM42: Zona próxima al epicentro; afectaciones graves y priorización humanitaria. | AO42: =TRIM(SUBSTITUTE(SUBSTITUTE(SUBSTITUTE(SUBSTITUTE(SUBSTITUTE(SUBSTITUTE(SUBSTITUTE(SUBSTITUTE(SUBSTITUTE(LOWER(G42),"á","a"),"é","e"),"í","i"),"ó","o"),"ú","u"),"ñ","n"),"-"," "),","," "),"."," ")) -> rio iro | AP42: =TRIM(SUBSTITUTE(SUBSTITUTE(SUBSTITUTE(SUBSTITUTE(SUBSTITUTE(SUBSTITUTE(SUBSTITUTE(SUBSTITUTE(SUBSTITUTE(LOWER(B42),"á","a"),"é","e"),"í","i"),"ó","o"),"ú","u"),"ñ","n"),"-"," "),","," "),"."," ")) -> choco | AQ42: =COUNTIF($AO$2:$AO$433,AO42)>COUNTIFS($AO$2:$AO$433,AO42,$AP$2:$AP$433,AP42) -> FALSE | AR42: =IF(AQ42,AO42&"|"&AP42,AO42) -> rio iro | AS42: =(I42<>"#N/D")+(J42<>"#N/D")+(L42<>"#N/D") -> 0 | AT42: =SUM(O42:X42) -> 2 | AU42: =IF(AT42<=$AY$2,0,IF(AT42<=$AY$3,1,IF(AT42<=$AY$4,2,3))) -> 3 | AV42: =IF(Y42<=$AY$7,3,IF(Y42<=$AY$8,2,IF(Y42<=$AY$9,1,0))) -> 3 | AZ42: =IF(Y42=0,3,0) -> 3 | BA42: =AS42+AU42+AZ42 -> 6 | BB42: =IFERROR(INDEX('Análisis general'!$E$4:$E$28,MATCH($B42,'Análisis general'!$B$4:$B$28,0)),"") -> 30.8 | BC42: =IF(BB42="","",IF(BB42<=$BG$2,0,IF(BB42<=$BG$3,1,IF(BB42<=$BG$4,2,3)))) -> 3 | BD42: =(AS42+AU42+AZ42+(BC42/2))*(9/10.5) -> 6.4285714 | BE42: =(AU42+AZ42+(BC42/2))*(9/7.5) -> 9
A43: 27135 | B43: Chocó | C43: Sin clasificación oficial | D43: =AS43+AU43+AV43 -> 6 | E43: =BD43 -> 6.4285714 | F43: =BE43 -> 9 | G43: El Cantón del San Pablo | H43: =IFERROR(IF($AQ43,INDEX(cpe!$C$2:$C$307,MATCH($AR43,cpe!$F$2:$F$307,0)),INDEX(cpe!$C$2:$C$307,MATCH($AR43,cpe!$D$2:$D$307,0))),"#N/D") -> #N/D | I43: =IFERROR(IF($AQ43,INDEX(cpe!$B$2:$B$307,MATCH($AR43,cpe!$F$2:$F$307,0)),INDEX(cpe!$B$2:$B$307,MATCH($AR43,cpe!$D$2:$D$307,0))),"#N/D") -> #N/D | J43: =IF($AQ43,"#N/D",IFERROR(INDEX(Olimpiadas!$B$2:$B$61,MATCH($AO43,Olimpiadas!$C$2:$C$61,0)),"#N/D")) -> #N/D | K43: =IF($AQ43,"#N/D",IFERROR(INDEX(Olimpiadas!$A$2:$A$61,MATCH($AO43,Olimpiadas!$C$2:$C$61,0)),"#N/D")) -> #N/D | L43: =IF($AQ43,"#N/D",IFERROR(INDEX(Minculturas!$A$2:$A$48,MATCH($AO43,Minculturas!$C$2:$C$48,0)),"#N/D")) -> #N/D | M43: =IF($AQ43,"#N/D",IFERROR(INDEX(Minculturas!$B$2:$B$48,MATCH($AO43,Minculturas!$C$2:$C$48,0)),"#N/D")) -> #N/D | N43: 3 | O43: 0 | P43: 0 | Q43: 0 | R43: 0 | S43: 0 | T43: 0 | U43: 0 | V43: 0 | W43: 0 | X43: 2 | Y43: 0 | Z43: 0 | AA43: 0 | AB43: 1 | AC43: 0 | AD43: 0 | AE43: 0 | AF43: 0 | AG43: =SUM(O43:X43) -> 2 | AH43: 4 | AI43: 10 | AJ43: 60.2 | AM43: Nombrado en la «Tabla No. 2: Municipios afectados por departamento» del Flash Update No. 003 de OCHA Colombia (11-08-2026) y en el reparto municipal del EDAN de viviendas de la UNGRD (capa 3iS/iMMAP, 12-08-2026). Sin ningún lugar con nombre propio publicado. | AO43: =TRIM(SUBSTITUTE(SUBSTITUTE(SUBSTITUTE(SUBSTITUTE(SUBSTITUTE(SUBSTITUTE(SUBSTITUTE(SUBSTITUTE(SUBSTITUTE(LOWER(G43),"á","a"),"é","e"),"í","i"),"ó","o"),"ú","u"),"ñ","n"),"-"," "),","," "),"."," ")) -> el canton del san pablo | AP43: =TRIM(SUBSTITUTE(SUBSTITUTE(SUBSTITUTE(SUBSTITUTE(SUBSTITUTE(SUBSTITUTE(SUBSTITUTE(SUBSTITUTE(SUBSTITUTE(LOWER(B43),"á","a"),"é","e"),"í","i"),"ó","o"),"ú","u"),"ñ","n"),"-"," "),","," "),"."," ")) -> choco | AQ43: =COUNTIF($AO$2:$AO$433,AO43)>COUNTIFS($AO$2:$AO$433,AO43,$AP$2:$AP$433,AP43) -> FALSE | AR43: =IF(AQ43,AO43&"|"&AP43,AO43) -> el canton del san pablo | AS43: =(I43<>"#N/D")+(J43<>"#N/D")+(L43<>"#N/D") -> 0 | AT43: =SUM(O43:X43) -> 2 | AU43: =IF(AT43<=$AY$2,0,IF(AT43<=$AY$3,1,IF(AT43<=$AY$4,2,3))) -> 3 | AV43: =IF(Y43<=$AY$7,3,IF(Y43<=$AY$8,2,IF(Y43<=$AY$9,1,0))) -> 3 | AZ43: =IF(Y43=0,3,0) -> 3 | BA43: =AS43+AU43+AZ43 -> 6 | BB43: =IFERROR(INDEX('Análisis general'!$E$4:$E$28,MATCH($B43,'Análisis general'!$B$4:$B$28,0)),"") -> 30.8 | BC43: =IF(BB43="","",IF(BB43<=$BG$2,0,IF(BB43<=$BG$3,1,IF(BB43<=$BG$4,2,3)))) -> 3 | BD43: =(AS43+AU43+AZ43+(BC43/2))*(9/10.5) -> 6.4285714 | BE43: =(AU43+AZ43+(BC43/2))*(9/7.5) -> 9
A44: 19256 | B44: Cauca | C44: Sin clasificación oficial | D44: =AS44+AU44+AV44 -> 6 | E44: =BD44 -> 6.4285714 | F44: =BE44 -> 9 | G44: El Tambo | H44: =IFERROR(IF($AQ44,INDEX(cpe!$C$2:$C$307,MATCH($AR44,cpe!$F$2:$F$307,0)),INDEX(cpe!$C$2:$C$307,MATCH($AR44,cpe!$D$2:$D$307,0))),"#N/D") -> #N/D | I44: =IFERROR(IF($AQ44,INDEX(cpe!$B$2:$B$307,MATCH($AR44,cpe!$F$2:$F$307,0)),INDEX(cpe!$B$2:$B$307,MATCH($AR44,cpe!$D$2:$D$307,0))),"#N/D") -> #N/D | J44: =IF($AQ44,"#N/D",IFERROR(INDEX(Olimpiadas!$B$2:$B$61,MATCH($AO44,Olimpiadas!$C$2:$C$61,0)),"#N/D")) -> #N/D | K44: =IF($AQ44,"#N/D",IFERROR(INDEX(Olimpiadas!$A$2:$A$61,MATCH($AO44,Olimpiadas!$C$2:$C$61,0)),"#N/D")) -> #N/D | L44: =IF($AQ44,"#N/D",IFERROR(INDEX(Minculturas!$A$2:$A$48,MATCH($AO44,Minculturas!$C$2:$C$48,0)),"#N/D")) -> #N/D | M44: =IF($AQ44,"#N/D",IFERROR(INDEX(Minculturas!$B$2:$B$48,MATCH($AO44,Minculturas!$C$2:$C$48,0)),"#N/D")) -> #N/D | N44: 2 | O44: 0 | P44: 0 | Q44: 0 | R44: 1 | S44: 0 | T44: 1 | U44: 0 | V44: 0 | W44: 0 | X44: 0 | Y44: 0 | Z44: 0 | AA44: 0 | AB44: 0 | AC44: 0 | AD44: 0 | AE44: 0 | AF44: 0 | AG44: =SUM(O44:X44) -> 2 | AJ44: 46 | AM44: Declarado afectado; sin lugar con nombre propio publicado en este registro. | AO44: =TRIM(SUBSTITUTE(SUBSTITUTE(SUBSTITUTE(SUBSTITUTE(SUBSTITUTE(SUBSTITUTE(SUBSTITUTE(SUBSTITUTE(SUBSTITUTE(LOWER(G44),"á","a"),"é","e"),"í","i"),"ó","o"),"ú","u"),"ñ","n"),"-"," "),","," "),"."," ")) -> el tambo | AP44: =TRIM(SUBSTITUTE(SUBSTITUTE(SUBSTITUTE(SUBSTITUTE(SUBSTITUTE(SUBSTITUTE(SUBSTITUTE(SUBSTITUTE(SUBSTITUTE(LOWER(B44),"á","a"),"é","e"),"í","i"),"ó","o"),"ú","u"),"ñ","n"),"-"," "),","," "),"."," ")) -> cauca | AQ44: =COUNTIF($AO$2:$AO$433,AO44)>COUNTIFS($AO$2:$AO$433,AO44,$AP$2:$AP$433,AP44) -> FALSE | AR44: =IF(AQ44,AO44&"|"&AP44,AO44) -> el tambo | AS44: =(I44<>"#N/D")+(J44<>"#N/D")+(L44<>"#N/D") -> 0 | AT44: =SUM(O44:X44) -> 2 | AU44: =IF(AT44<=$AY$2,0,IF(AT44<=$AY$3,1,IF(AT44<=$AY$4,2,3))) -> 3 | AV44: =IF(Y44<=$AY$7,3,IF(Y44<=$AY$8,2,IF(Y44<=$AY$9,1,0))) -> 3 | AZ44: =IF(Y44=0,3,0) -> 3 | BA44: =AS44+AU44+AZ44 -> 6 | BB44: =IFERROR(INDEX('Análisis general'!$E$4:$E$28,MATCH($B44,'Análisis general'!$B$4:$B$28,0)),"") -> 13 | BC44: =IF(BB44="","",IF(BB44<=$BG$2,0,IF(BB44<=$BG$3,1,IF(BB44<=$BG$4,2,3)))) -> 3 | BD44: =(AS44+AU44+AZ44+(BC44/2))*(9/10.5) -> 6.4285714 | BE44: =(AU44+AZ44+(BC44/2))*(9/7.5) -> 9
A45: 25473 | B45: Nariño | C45: Afectación media | D45: =AS45+AU45+AV45 -> 6 | E45: =BD45 -> 6.4285714 | F45: =BE45 -> 9 | G45: Mosquera | H45: =IFERROR(IF($AQ45,INDEX(cpe!$C$2:$C$307,MATCH($AR45,cpe!$F$2:$F$307,0)),INDEX(cpe!$C$2:$C$307,MATCH($AR45,cpe!$D$2:$D$307,0))),"#N/D") -> #N/D | I45: =IFERROR(IF($AQ45,INDEX(cpe!$B$2:$B$307,MATCH($AR45,cpe!$F$2:$F$307,0)),INDEX(cpe!$B$2:$B$307,MATCH($AR45,cpe!$D$2:$D$307,0))),"#N/D") -> #N/D | J45: =IF($AQ45,"#N/D",IFERROR(INDEX(Olimpiadas!$B$2:$B$61,MATCH($AO45,Olimpiadas!$C$2:$C$61,0)),"#N/D")) -> #N/D | K45: =IF($AQ45,"#N/D",IFERROR(INDEX(Olimpiadas!$A$2:$A$61,MATCH($AO45,Olimpiadas!$C$2:$C$61,0)),"#N/D")) -> #N/D | L45: =IF($AQ45,"#N/D",IFERROR(INDEX(Minculturas!$A$2:$A$48,MATCH($AO45,Minculturas!$C$2:$C$48,0)),"#N/D")) -> #N/D | M45: =IF($AQ45,"#N/D",IFERROR(INDEX(Minculturas!$B$2:$B$48,MATCH($AO45,Minculturas!$C$2:$C$48,0)),"#N/D")) -> #N/D | N45: 2 | O45: 0 | P45: 1 | Q45: 0 | R45: 0 | S45: 0 | T45: 0 | U45: 1 | V45: 0 | W45: 0 | X45: 0 | Y45: 0 | Z45: 0 | AA45: 0 | AB45: 0 | AC45: 0 | AD45: 0 | AE45: 0 | AF45: 0 | AG45: =SUM(O45:X45) -> 2 | AJ45: 9.6 | AM45: Declarado afectado; sin lugar con nombre propio publicado en este registro. | AO45: =TRIM(SUBSTITUTE(SUBSTITUTE(SUBSTITUTE(SUBSTITUTE(SUBSTITUTE(SUBSTITUTE(SUBSTITUTE(SUBSTITUTE(SUBSTITUTE(LOWER(G45),"á","a"),"é","e"),"í","i"),"ó","o"),"ú","u"),"ñ","n"),"-"," "),","," "),"."," ")) -> mosquera | AP45: =TRIM(SUBSTITUTE(SUBSTITUTE(SUBSTITUTE(SUBSTITUTE(SUBSTITUTE(SUBSTITUTE(SUBSTITUTE(SUBSTITUTE(SUBSTITUTE(LOWER(B45),"á","a"),"é","e"),"í","i"),"ó","o"),"ú","u"),"ñ","n"),"-"," "),","," "),"."," ")) -> narino | AQ45: =COUNTIF($AO$2:$AO$433,AO45)>COUNTIFS($AO$2:$AO$433,AO45,$AP$2:$AP$433,AP45) -> TRUE | AR45: =IF(AQ45,AO45&"|"&AP45,AO45) -> mosquera|narino | AS45: =(I45<>"#N/D")+(J45<>"#N/D")+(L45<>"#N/D") -> 0 | AT45: =SUM(O45:X45) -> 2 | AU45: =IF(AT45<=$AY$2,0,IF(AT45<=$AY$3,1,IF(AT45<=$AY$4,2,3))) -> 3 | AV45: =IF(Y45<=$AY$7,3,IF(Y45<=$AY$8,2,IF(Y45<=$AY$9,1,0))) -> 3 | AZ45: =IF(Y45=0,3,0) -> 3 | BA45: =AS45+AU45+AZ45 -> 6 | BB45: =IFERROR(INDEX('Análisis general'!$E$4:$E$28,MATCH($B45,'Análisis general'!$B$4:$B$28,0)),"") -> 13.2 | BC45: =IF(BB45="","",IF(BB45<=$BG$2,0,IF(BB45<=$BG$3,1,IF(BB45<=$BG$4,2,3)))) -> 3 | BD45: =(AS45+AU45+AZ45+(BC45/2))*(9/10.5) -> 6.4285714 | BE45: =(AU45+AZ45+(BC45/2))*(9/7.5) -> 9
A46: 19548 | B46: Cauca | C46: Sin clasificación oficial | D46: =AS46+AU46+AV46 -> 6 | E46: =BD46 -> 6.4285714 | F46: =BE46 -> 9 | G46: Piendamó | H46: #N/D | I46: #N/D | J46: #N/D | K46: =IF($AQ46,"#N/D",IFERROR(INDEX(Olimpiadas!$A$2:$A$61,MATCH($AO46,Olimpiadas!$C$2:$C$61,0)),"#N/D")) -> #N/D | L46: =IF($AQ46,"#N/D",IFERROR(INDEX(Minculturas!$A$2:$A$48,MATCH($AO46,Minculturas!$C$2:$C$48,0)),"#N/D")) -> #N/D | M46: =IF($AQ46,"#N/D",IFERROR(INDEX(Minculturas!$B$2:$B$48,MATCH($AO46,Minculturas!$C$2:$C$48,0)),"#N/D")) -> #N/D | N46: 2 | O46: 0 | P46: 0 | Q46: 1 | R46: 0 | S46: 0 | T46: 0 | U46: 1 | V46: 0 | W46: 0 | X46: 0 | Y46: 0 | Z46: 0 | AA46: 0 | AB46: 0 | AC46: 0 | AD46: 0 | AE46: 0 | AF46: 0 | AG46: =SUM(O46:X46) -> 2 | AJ46: 30.7 | AM46: Declarado afectado; sin lugar con nombre propio publicado en este registro. | AO46: =TRIM(SUBSTITUTE(SUBSTITUTE(SUBSTITUTE(SUBSTITUTE(SUBSTITUTE(SUBSTITUTE(SUBSTITUTE(SUBSTITUTE(SUBSTITUTE(LOWER(G46),"á","a"),"é","e"),"í","i"),"ó","o"),"ú","u"),"ñ","n"),"-"," "),","," "),"."," ")) -> piendamo | AP46: =TRIM(SUBSTITUTE(SUBSTITUTE(SUBSTITUTE(SUBSTITUTE(SUBSTITUTE(SUBSTITUTE(SUBSTITUTE(SUBSTITUTE(SUBSTITUTE(LOWER(B46),"á","a"),"é","e"),"í","i"),"ó","o"),"ú","u"),"ñ","n"),"-"," "),","," "),"."," ")) -> cauca | AQ46: =COUNTIF($AO$2:$AO$433,AO46)>COUNTIFS($AO$2:$AO$433,AO46,$AP$2:$AP$433,AP46) -> FALSE | AR46: =IF(AQ46,AO46&"|"&AP46,AO46) -> piendamo | AS46: =(I46<>"#N/D")+(J46<>"#N/D")+(L46<>"#N/D") -> 0 | AT46: =SUM(O46:X46) -> 2 | AU46: =IF(AT46<=$AY$2,0,IF(AT46<=$AY$3,1,IF(AT46<=$AY$4,2,3))) -> 3 | AV46: =IF(Y46<=$AY$7,3,IF(Y46<=$AY$8,2,IF(Y46<=$AY$9,1,0))) -> 3 | AZ46: =IF(Y46=0,3,0) -> 3 | BA46: =AS46+AU46+AZ46 -> 6 | BB46: =IFERROR(INDEX('Análisis general'!$E$4:$E$28,MATCH($B46,'Análisis general'!$B$4:$B$28,0)),"") -> 13 | BC46: =IF(BB46="","",IF(BB46<=$BG$2,0,IF(BB46<=$BG$3,1,IF(BB46<=$BG$4,2,3)))) -> 3 | BD46: =(AS46+AU46+AZ46+(BC46/2))*(9/10.5) -> 6.4285714 | BE46: =(AU46+AZ46+(BC46/2))*(9/7.5) -> 9
A47: 19622 | B47: Cauca | C47: Sin clasificación oficial | D47: =AS47+AU47+AV47 -> 6 | E47: =BD47 -> 6.4285714 | F47: =BE47 -> 9 | G47: Rosas | H47: #N/D | I47: #N/D | J47: #N/D | K47: =IF($AQ47,"#N/D",IFERROR(INDEX(Olimpiadas!$A$2:$A$61,MATCH($AO47,Olimpiadas!$C$2:$C$61,0)),"#N/D")) -> #N/D | L47: =IF($AQ47,"#N/D",IFERROR(INDEX(Minculturas!$A$2:$A$48,MATCH($AO47,Minculturas!$C$2:$C$48,0)),"#N/D")) -> #N/D | M47: =IF($AQ47,"#N/D",IFERROR(INDEX(Minculturas!$B$2:$B$48,MATCH($AO47,Minculturas!$C$2:$C$48,0)),"#N/D")) -> #N/D | N47: 2 | O47: 0 | P47: 1 | Q47: 0 | R47: 0 | S47: 1 | T47: 0 | U47: 0 | V47: 0 | W47: 0 | X47: 0 | Y47: 0 | Z47: 0 | AA47: 0 | AB47: 0 | AC47: 0 | AD47: 0 | AE47: 0 | AF47: 0 | AG47: =SUM(O47:X47) -> 2 | AJ47: 43.2 | AM47: Declarado afectado en el reparto municipal del EDAN de viviendas de la UNGRD (capa 3iS/iMMAP para OCHA, 12-08-2026). Sin ningún lugar con nombre propio publicado. | AO47: =TRIM(SUBSTITUTE(SUBSTITUTE(SUBSTITUTE(SUBSTITUTE(SUBSTITUTE(SUBSTITUTE(SUBSTITUTE(SUBSTITUTE(SUBSTITUTE(LOWER(G47),"á","a"),"é","e"),"í","i"),"ó","o"),"ú","u"),"ñ","n"),"-"," "),","," "),"."," ")) -> rosas | AP47: =TRIM(SUBSTITUTE(SUBSTITUTE(SUBSTITUTE(SUBSTITUTE(SUBSTITUTE(SUBSTITUTE(SUBSTITUTE(SUBSTITUTE(SUBSTITUTE(LOWER(B47),"á","a"),"é","e"),"í","i"),"ó","o"),"ú","u"),"ñ","n"),"-"," "),","," "),"."," ")) -> cauca | AQ47: =COUNTIF($AO$2:$AO$433,AO47)>COUNTIFS($AO$2:$AO$433,AO47,$AP$2:$AP$433,AP47) -> FALSE | AR47: =IF(AQ47,AO47&"|"&AP47,AO47) -> rosas | AS47: =(I47<>"#N/D")+(J47<>"#N/D")+(L47<>"#N/D") -> 0 | AT47: =SUM(O47:X47) -> 2 | AU47: =IF(AT47<=$AY$2,0,IF(AT47<=$AY$3,1,IF(AT47<=$AY$4,2,3))) -> 3 | AV47: =IF(Y47<=$AY$7,3,IF(Y47<=$AY$8,2,IF(Y47<=$AY$9,1,0))) -> 3 | AZ47: =IF(Y47=0,3,0) -> 3 | BA47: =AS47+AU47+AZ47 -> 6 | BB47: =IFERROR(INDEX('Análisis general'!$E$4:$E$28,MATCH($B47,'Análisis general'!$B$4:$B$28,0)),"") -> 13 | BC47: =IF(BB47="","",IF(BB47<=$BG$2,0,IF(BB47<=$BG$3,1,IF(BB47<=$BG$4,2,3)))) -> 3 | BD47: =(AS47+AU47+AZ47+(BC47/2))*(9/10.5) -> 6.4285714 | BE47: =(AU47+AZ47+(BC47/2))*(9/7.5) -> 9
A48: 54743 | B48: Norte de Santander | C48: Sin clasificación oficial | D48: =AS48+AU48+AV48 -> 6 | E48: =BD48 -> 6.4285714 | F48: =BE48 -> 9 | G48: Silos | H48: #N/D | I48: #N/D | J48: #N/D | K48: =IF($AQ48,"#N/D",IFERROR(INDEX(Olimpiadas!$A$2:$A$61,MATCH($AO48,Olimpiadas!$C$2:$C$61,0)),"#N/D")) -> #N/D | L48: =IF($AQ48,"#N/D",IFERROR(INDEX(Minculturas!$A$2:$A$48,MATCH($AO48,Minculturas!$C$2:$C$48,0)),"#N/D")) -> #N/D | M48: =IF($AQ48,"#N/D",IFERROR(INDEX(Minculturas!$B$2:$B$48,MATCH($AO48,Minculturas!$C$2:$C$48,0)),"#N/D")) -> #N/D | N48: 2 | O48: 0 | P48: 0 | Q48: 0 | R48: 0 | S48: 0 | T48: 2 | U48: 0 | V48: 0 | W48: 0 | X48: 0 | Y48: 0 | Z48: 0 | AA48: 0 | AB48: 0 | AC48: 0 | AD48: 0 | AE48: 0 | AF48: 0 | AG48: =SUM(O48:X48) -> 2 | AJ48: 46.6 | AM48: Declarado afectado; sin lugar con nombre propio publicado en este registro. | AO48: =TRIM(SUBSTITUTE(SUBSTITUTE(SUBSTITUTE(SUBSTITUTE(SUBSTITUTE(SUBSTITUTE(SUBSTITUTE(SUBSTITUTE(SUBSTITUTE(LOWER(G48),"á","a"),"é","e"),"í","i"),"ó","o"),"ú","u"),"ñ","n"),"-"," "),","," "),"."," ")) -> silos | AP48: =TRIM(SUBSTITUTE(SUBSTITUTE(SUBSTITUTE(SUBSTITUTE(SUBSTITUTE(SUBSTITUTE(SUBSTITUTE(SUBSTITUTE(SUBSTITUTE(LOWER(B48),"á","a"),"é","e"),"í","i"),"ó","o"),"ú","u"),"ñ","n"),"-"," "),","," "),"."," ")) -> norte de santander | AQ48: =COUNTIF($AO$2:$AO$433,AO48)>COUNTIFS($AO$2:$AO$433,AO48,$AP$2:$AP$433,AP48) -> FALSE | AR48: =IF(AQ48,AO48&"|"&AP48,AO48) -> silos | AS48: =(I48<>"#N/D")+(J48<>"#N/D")+(L48<>"#N/D") -> 0 | AT48: =SUM(O48:X48) -> 2 | AU48: =IF(AT48<=$AY$2,0,IF(AT48<=$AY$3,1,IF(AT48<=$AY$4,2,3))) -> 3 | AV48: =IF(Y48<=$AY$7,3,IF(Y48<=$AY$8,2,IF(Y48<=$AY$9,1,0))) -> 3 | AZ48: =IF(Y48=0,3,0) -> 3 | BA48: =AS48+AU48+AZ48 -> 6 | BB48: =IFERROR(INDEX('Análisis general'!$E$4:$E$28,MATCH($B48,'Análisis general'!$B$4:$B$28,0)),"") -> 13.3 | BC48: =IF(BB48="","",IF(BB48<=$BG$2,0,IF(BB48<=$BG$3,1,IF(BB48<=$BG$4,2,3)))) -> 3 | BD48: =(AS48+AU48+AZ48+(BC48/2))*(9/10.5) -> 6.4285714 | BE48: =(AU48+AZ48+(BC48/2))*(9/7.5) -> 9
A49: 19824 | B49: Cauca | C49: Sin clasificación oficial | D49: =AS49+AU49+AV49 -> 6 | E49: =BD49 -> 6.4285714 | F49: =BE49 -> 9 | G49: Totoró | H49: #N/D | I49: #N/D | J49: #N/D | K49: =IF($AQ49,"#N/D",IFERROR(INDEX(Olimpiadas!$A$2:$A$61,MATCH($AO49,Olimpiadas!$C$2:$C$61,0)),"#N/D")) -> #N/D | L49: =IF($AQ49,"#N/D",IFERROR(INDEX(Minculturas!$A$2:$A$48,MATCH($AO49,Minculturas!$C$2:$C$48,0)),"#N/D")) -> #N/D | M49: =IF($AQ49,"#N/D",IFERROR(INDEX(Minculturas!$B$2:$B$48,MATCH($AO49,Minculturas!$C$2:$C$48,0)),"#N/D")) -> #N/D | N49: 2 | O49: 0 | P49: 0 | Q49: 0 | R49: 0 | S49: 0 | T49: 1 | U49: 1 | V49: 0 | W49: 0 | X49: 0 | Y49: 0 | Z49: 0 | AA49: 0 | AB49: 0 | AC49: 0 | AD49: 0 | AE49: 0 | AF49: 0 | AG49: =SUM(O49:X49) -> 2 | AJ49: 55.1 | AM49: Declarado afectado; sin lugar con nombre propio publicado en este registro. | AO49: =TRIM(SUBSTITUTE(SUBSTITUTE(SUBSTITUTE(SUBSTITUTE(SUBSTITUTE(SUBSTITUTE(SUBSTITUTE(SUBSTITUTE(SUBSTITUTE(LOWER(G49),"á","a"),"é","e"),"í","i"),"ó","o"),"ú","u"),"ñ","n"),"-"," "),","," "),"."," ")) -> totoro | AP49: =TRIM(SUBSTITUTE(SUBSTITUTE(SUBSTITUTE(SUBSTITUTE(SUBSTITUTE(SUBSTITUTE(SUBSTITUTE(SUBSTITUTE(SUBSTITUTE(LOWER(B49),"á","a"),"é","e"),"í","i"),"ó","o"),"ú","u"),"ñ","n"),"-"," "),","," "),"."," ")) -> cauca | AQ49: =COUNTIF($AO$2:$AO$433,AO49)>COUNTIFS($AO$2:$AO$433,AO49,$AP$2:$AP$433,AP49) -> FALSE | AR49: =IF(AQ49,AO49&"|"&AP49,AO49) -> totoro | AS49: =(I49<>"#N/D")+(J49<>"#N/D")+(L49<>"#N/D") -> 0 | AT49: =SUM(O49:X49) -> 2 | AU49: =IF(AT49<=$AY$2,0,IF(AT49<=$AY$3,1,IF(AT49<=$AY$4,2,3))) -> 3 | AV49: =IF(Y49<=$AY$7,3,IF(Y49<=$AY$8,2,IF(Y49<=$AY$9,1,0))) -> 3 | AZ49: =IF(Y49=0,3,0) -> 3 | BA49: =AS49+AU49+AZ49 -> 6 | BB49: =IFERROR(INDEX('Análisis general'!$E$4:$E$28,MATCH($B49,'Análisis general'!$B$4:$B$28,0)),"") -> 13 | BC49: =IF(BB49="","",IF(BB49<=$BG$2,0,IF(BB49<=$BG$3,1,IF(BB49<=$BG$4,2,3)))) -> 3 | BD49: =(AS49+AU49+AZ49+(BC49/2))*(9/10.5) -> 6.4285714 | BE49: =(AU49+AZ49+(BC49/2))*(9/7.5) -> 9
A50: 27425 | B50: Chocó | C50: Sin clasificación oficial | D50: =AS50+AU50+AV50 -> 6 | E50: =BD50 -> 6.4285714 | F50: =BE50 -> 9 | G50: Medio Atrato | H50: =IFERROR(IF($AQ50,INDEX(cpe!$C$2:$C$307,MATCH($AR50,cpe!$F$2:$F$307,0)),INDEX(cpe!$C$2:$C$307,MATCH($AR50,cpe!$D$2:$D$307,0))),"#N/D") -> #N/D | I50: =IFERROR(IF($AQ50,INDEX(cpe!$B$2:$B$307,MATCH($AR50,cpe!$F$2:$F$307,0)),INDEX(cpe!$B$2:$B$307,MATCH($AR50,cpe!$D$2:$D$307,0))),"#N/D") -> #N/D | J50: =IF($AQ50,"#N/D",IFERROR(INDEX(Olimpiadas!$B$2:$B$61,MATCH($AO50,Olimpiadas!$C$2:$C$61,0)),"#N/D")) -> #N/D | K50: =IF($AQ50,"#N/D",IFERROR(INDEX(Olimpiadas!$A$2:$A$61,MATCH($AO50,Olimpiadas!$C$2:$C$61,0)),"#N/D")) -> #N/D | L50: =IF($AQ50,"#N/D",IFERROR(INDEX(Minculturas!$A$2:$A$48,MATCH($AO50,Minculturas!$C$2:$C$48,0)),"#N/D")) -> #N/D | M50: =IF($AQ50,"#N/D",IFERROR(INDEX(Minculturas!$B$2:$B$48,MATCH($AO50,Minculturas!$C$2:$C$48,0)),"#N/D")) -> #N/D | N50: 2 | O50: 0 | P50: 0 | Q50: 1 | R50: 0 | S50: 0 | T50: 1 | U50: 0 | V50: 0 | W50: 0 | X50: 0 | Y50: 0 | Z50: 0 | AA50: 0 | AB50: 0 | AC50: 0 | AD50: 0 | AE50: 0 | AF50: 0 | AG50: =SUM(O50:X50) -> 2 | AH50: 68 | AI50: 140 | AJ50: 76.6 | AM50: Declarado afectado en el reparto municipal del EDAN de viviendas de la UNGRD (capa 3iS/iMMAP para OCHA, 12-08-2026). Sin ningún lugar con nombre propio publicado. | AO50: =TRIM(SUBSTITUTE(SUBSTITUTE(SUBSTITUTE(SUBSTITUTE(SUBSTITUTE(SUBSTITUTE(SUBSTITUTE(SUBSTITUTE(SUBSTITUTE(LOWER(G50),"á","a"),"é","e"),"í","i"),"ó","o"),"ú","u"),"ñ","n"),"-"," "),","," "),"."," ")) -> medio atrato | AP50: =TRIM(SUBSTITUTE(SUBSTITUTE(SUBSTITUTE(SUBSTITUTE(SUBSTITUTE(SUBSTITUTE(SUBSTITUTE(SUBSTITUTE(SUBSTITUTE(LOWER(B50),"á","a"),"é","e"),"í","i"),"ó","o"),"ú","u"),"ñ","n"),"-"," "),","," "),"."," ")) -> choco | AQ50: =COUNTIF($AO$2:$AO$433,AO50)>COUNTIFS($AO$2:$AO$433,AO50,$AP$2:$AP$433,AP50) -> FALSE | AR50: =IF(AQ50,AO50&"|"&AP50,AO50) -> medio atrato | AS50: =(I50<>"#N/D")+(J50<>"#N/D")+(L50<>"#N/D") -> 0 | AT50: =SUM(O50:X50) -> 2 | AU50: =IF(AT50<=$AY$2,0,IF(AT50<=$AY$3,1,IF(AT50<=$AY$4,2,3))) -> 3 | AV50: =IF(Y50<=$AY$7,3,IF(Y50<=$AY$8,2,IF(Y50<=$AY$9,1,0))) -> 3 | AZ50: =IF(Y50=0,3,0) -> 3 | BA50: =AS50+AU50+AZ50 -> 6 | BB50: =IFERROR(INDEX('Análisis general'!$E$4:$E$28,MATCH($B50,'Análisis general'!$B$4:$B$28,0)),"") -> 30.8 | BC50: =IF(BB50="","",IF(BB50<=$BG$2,0,IF(BB50<=$BG$3,1,IF(BB50<=$BG$4,2,3)))) -> 3 | BD50: =(AS50+AU50+AZ50+(BC50/2))*(9/10.5) -> 6.4285714 | BE50: =(AU50+AZ50+(BC50/2))*(9/7.5) -> 9
A51: 19780 | B51: Cauca | C51: Sin clasificación oficial | D51: =AS51+AU51+AV51 -> 6 | E51: =BD51 -> 6.4285714 | F51: =BE51 -> 9 | G51: Suárez | H51: #N/D | I51: #N/D | J51: #N/D | K51: =IF($AQ51,"#N/D",IFERROR(INDEX(Olimpiadas!$A$2:$A$61,MATCH($AO51,Olimpiadas!$C$2:$C$61,0)),"#N/D")) -> #N/D | L51: =IF($AQ51,"#N/D",IFERROR(INDEX(Minculturas!$A$2:$A$48,MATCH($AO51,Minculturas!$C$2:$C$48,0)),"#N/D")) -> #N/D | M51: =IF($AQ51,"#N/D",IFERROR(INDEX(Minculturas!$B$2:$B$48,MATCH($AO51,Minculturas!$C$2:$C$48,0)),"#N/D")) -> #N/D | N51: 3 | O51: 0 | P51: 0 | Q51: 0 | R51: 0 | S51: 1 | T51: 0 | U51: 1 | V51: 0 | W51: 0 | X51: 0 | Y51: 0 | Z51: 0 | AA51: 0 | AB51: 1 | AC51: 0 | AD51: 0 | AE51: 0 | AF51: 0 | AG51: =SUM(O51:X51) -> 2 | AJ51: 44.1 | AM51: Declarado afectado; sin lugar con nombre propio publicado en este registro. | AO51: =TRIM(SUBSTITUTE(SUBSTITUTE(SUBSTITUTE(SUBSTITUTE(SUBSTITUTE(SUBSTITUTE(SUBSTITUTE(SUBSTITUTE(SUBSTITUTE(LOWER(G51),"á","a"),"é","e"),"í","i"),"ó","o"),"ú","u"),"ñ","n"),"-"," "),","," "),"."," ")) -> suarez | AP51: =TRIM(SUBSTITUTE(SUBSTITUTE(SUBSTITUTE(SUBSTITUTE(SUBSTITUTE(SUBSTITUTE(SUBSTITUTE(SUBSTITUTE(SUBSTITUTE(LOWER(B51),"á","a"),"é","e"),"í","i"),"ó","o"),"ú","u"),"ñ","n"),"-"," "),","," "),"."," ")) -> cauca | AQ51: =COUNTIF($AO$2:$AO$433,AO51)>COUNTIFS($AO$2:$AO$433,AO51,$AP$2:$AP$433,AP51) -> TRUE | AR51: =IF(AQ51,AO51&"|"&AP51,AO51) -> suarez|cauca | AS51: =(I51<>"#N/D")+(J51<>"#N/D")+(L51<>"#N/D") -> 0 | AT51: =SUM(O51:X51) -> 2 | AU51: =IF(AT51<=$AY$2,0,IF(AT51<=$AY$3,1,IF(AT51<=$AY$4,2,3))) -> 3 | AV51: =IF(Y51<=$AY$7,3,IF(Y51<=$AY$8,2,IF(Y51<=$AY$9,1,0))) -> 3 | AZ51: =IF(Y51=0,3,0) -> 3 | BA51: =AS51+AU51+AZ51 -> 6 | BB51: =IFERROR(INDEX('Análisis general'!$E$4:$E$28,MATCH($B51,'Análisis general'!$B$4:$B$28,0)),"") -> 13 | BC51: =IF(BB51="","",IF(BB51<=$BG$2,0,IF(BB51<=$BG$3,1,IF(BB51<=$BG$4,2,3)))) -> 3 | BD51: =(AS51+AU51+AZ51+(BC51/2))*(9/10.5) -> 6.4285714 | BE51: =(AU51+AZ51+(BC51/2))*(9/7.5) -> 9
A52: 76126 | B52: Valle del Cauca | C52: Afectación crítica | D52: =AS52+AU52+AV52 -> 7 | E52: =BD52 -> 7.2857143 | F52: =BE52 -> 9 | G52: Calima-El Darién | H52: =IFERROR(IF($AQ52,INDEX(cpe!$C$2:$C$307,MATCH($AR52,cpe!$F$2:$F$307,0)),INDEX(cpe!$C$2:$C$307,MATCH($AR52,cpe!$D$2:$D$307,0))),"#N/D") -> Colegio Externado Nacional Camilo Torres (ied) | I52: =IFERROR(IF($AQ52,INDEX(cpe!$B$2:$B$307,MATCH($AR52,cpe!$F$2:$F$307,0)),INDEX(cpe!$B$2:$B$307,MATCH($AR52,cpe!$D$2:$D$307,0))),"#N/D") -> Calima-El Darién | J52: =IF($AQ52,"#N/D",IFERROR(INDEX(Olimpiadas!$B$2:$B$61,MATCH($AO52,Olimpiadas!$C$2:$C$61,0)),"#N/D")) -> #N/D | K52: =IF($AQ52,"#N/D",IFERROR(INDEX(Olimpiadas!$A$2:$A$61,MATCH($AO52,Olimpiadas!$C$2:$C$61,0)),"#N/D")) -> #N/D | L52: =IF($AQ52,"#N/D",IFERROR(INDEX(Minculturas!$A$2:$A$48,MATCH($AO52,Minculturas!$C$2:$C$48,0)),"#N/D")) -> #N/D | M52: =IF($AQ52,"#N/D",IFERROR(INDEX(Minculturas!$B$2:$B$48,MATCH($AO52,Minculturas!$C$2:$C$48,0)),"#N/D")) -> #N/D | N52: 14 | O52: 1 | P52: 4 | Q52: 3 | R52: 1 | S52: 2 | T52: 1 | U52: 0 | V52: 0 | W52: 0 | X52: 1 | Y52: 0 | Z52: 1 | AA52: 0 | AB52: 0 | AC52: 0 | AD52: 0 | AE52: 0 | AF52: 0 | AG52: =SUM(O52:X52) -> 13 | AH52: 211 | AI52: 493 | AJ52: 25.7 | AM52: Colapso de pared con tres menores fallecidos; daños importantes en infraestructura. | AO52: =TRIM(SUBSTITUTE(SUBSTITUTE(SUBSTITUTE(SUBSTITUTE(SUBSTITUTE(SUBSTITUTE(SUBSTITUTE(SUBSTITUTE(SUBSTITUTE(LOWER(G52),"á","a"),"é","e"),"í","i"),"ó","o"),"ú","u"),"ñ","n"),"-"," "),","," "),"."," ")) -> calima el darien | AP52: =TRIM(SUBSTITUTE(SUBSTITUTE(SUBSTITUTE(SUBSTITUTE(SUBSTITUTE(SUBSTITUTE(SUBSTITUTE(SUBSTITUTE(SUBSTITUTE(LOWER(B52),"á","a"),"é","e"),"í","i"),"ó","o"),"ú","u"),"ñ","n"),"-"," "),","," "),"."," ")) -> valle del cauca | AQ52: =COUNTIF($AO$2:$AO$433,AO52)>COUNTIFS($AO$2:$AO$433,AO52,$AP$2:$AP$433,AP52) -> FALSE | AR52: =IF(AQ52,AO52&"|"&AP52,AO52) -> calima el darien | AS52: =(I52<>"#N/D")+(J52<>"#N/D")+(L52<>"#N/D") -> 1 | AT52: =SUM(O52:X52) -> 13 | AU52: =IF(AT52<=$AY$2,0,IF(AT52<=$AY$3,1,IF(AT52<=$AY$4,2,3))) -> 3 | AV52: =IF(Y52<=$AY$7,3,IF(Y52<=$AY$8,2,IF(Y52<=$AY$9,1,0))) -> 3 | AZ52: =IF(Y52=0,3,0) -> 3 | BA52: =AS52+AU52+AZ52 -> 7 | BB52: =IFERROR(INDEX('Análisis general'!$E$4:$E$28,MATCH($B52,'Análisis general'!$B$4:$B$28,0)),"") -> 4.9 | BC52: =IF(BB52="","",IF(BB52<=$BG$2,0,IF(BB52<=$BG$3,1,IF(BB52<=$BG$4,2,3)))) -> 3 | BD52: =(AS52+AU52+AZ52+(BC52/2))*(9/10.5) -> 7.2857143 | BE52: =(AU52+AZ52+(BC52/2))*(9/7.5) -> 9
A53: 76122 | B53: Valle del Cauca | C53: Sin clasificación oficial | D53: =AS53+AU53+AV53 -> 7 | E53: =BD53 -> 7.2857143 | F53: =BE53 -> 9 | G53: Caicedonia | H53: =IFERROR(IF($AQ53,INDEX(cpe!$C$2:$C$307,MATCH($AR53,cpe!$F$2:$F$307,0)),INDEX(cpe!$C$2:$C$307,MATCH($AR53,cpe!$D$2:$D$307,0))),"#N/D") -> #N/D | I53: =IFERROR(IF($AQ53,INDEX(cpe!$B$2:$B$307,MATCH($AR53,cpe!$F$2:$F$307,0)),INDEX(cpe!$B$2:$B$307,MATCH($AR53,cpe!$D$2:$D$307,0))),"#N/D") -> #N/D | J53: =IF($AQ53,"#N/D",IFERROR(INDEX(Olimpiadas!$B$2:$B$61,MATCH($AO53,Olimpiadas!$C$2:$C$61,0)),"#N/D")) -> Caicedonia | K53: =IF($AQ53,"#N/D",IFERROR(INDEX(Olimpiadas!$A$2:$A$61,MATCH($AO53,Olimpiadas!$C$2:$C$61,0)),"#N/D")) -> INSTITUCIÓN EDUCATIVA LA CONSOLITA | L53: =IF($AQ53,"#N/D",IFERROR(INDEX(Minculturas!$A$2:$A$48,MATCH($AO53,Minculturas!$C$2:$C$48,0)),"#N/D")) -> #N/D | M53: =IF($AQ53,"#N/D",IFERROR(INDEX(Minculturas!$B$2:$B$48,MATCH($AO53,Minculturas!$C$2:$C$48,0)),"#N/D")) -> #N/D | N53: 11 | O53: 0 | P53: 2 | Q53: 5 | R53: 0 | S53: 0 | T53: 1 | U53: 0 | V53: 0 | W53: 0 | X53: 1 | Y53: 0 | Z53: 1 | AA53: 0 | AB53: 1 | AC53: 0 | AD53: 0 | AE53: 0 | AF53: 0 | AG53: =SUM(O53:X53) -> 9 | AH53: 979 | AI53: 1912 | AJ53: 24.6 | AM53: Declarado afectado; sin lugar con nombre propio publicado en este registro. | AO53: =TRIM(SUBSTITUTE(SUBSTITUTE(SUBSTITUTE(SUBSTITUTE(SUBSTITUTE(SUBSTITUTE(SUBSTITUTE(SUBSTITUTE(SUBSTITUTE(LOWER(G53),"á","a"),"é","e"),"í","i"),"ó","o"),"ú","u"),"ñ","n"),"-"," "),","," "),"."," ")) -> caicedonia | AP53: =TRIM(SUBSTITUTE(SUBSTITUTE(SUBSTITUTE(SUBSTITUTE(SUBSTITUTE(SUBSTITUTE(SUBSTITUTE(SUBSTITUTE(SUBSTITUTE(LOWER(B53),"á","a"),"é","e"),"í","i"),"ó","o"),"ú","u"),"ñ","n"),"-"," "),","," "),"."," ")) -> valle del cauca | AQ53: =COUNTIF($AO$2:$AO$433,AO53)>COUNTIFS($AO$2:$AO$433,AO53,$AP$2:$AP$433,AP53) -> FALSE | AR53: =IF(AQ53,AO53&"|"&AP53,AO53) -> caicedonia | AS53: =(I53<>"#N/D")+(J53<>"#N/D")+(L53<>"#N/D") -> 1 | AT53: =SUM(O53:X53) -> 9 | AU53: =IF(AT53<=$AY$2,0,IF(AT53<=$AY$3,1,IF(AT53<=$AY$4,2,3))) -> 3 | AV53: =IF(Y53<=$AY$7,3,IF(Y53<=$AY$8,2,IF(Y53<=$AY$9,1,0))) -> 3 | AZ53: =IF(Y53=0,3,0) -> 3 | BA53: =AS53+AU53+AZ53 -> 7 | BB53: =IFERROR(INDEX('Análisis general'!$E$4:$E$28,MATCH($B53,'Análisis general'!$B$4:$B$28,0)),"") -> 4.9 | BC53: =IF(BB53="","",IF(BB53<=$BG$2,0,IF(BB53<=$BG$3,1,IF(BB53<=$BG$4,2,3)))) -> 3 | BD53: =(AS53+AU53+AZ53+(BC53/2))*(9/10.5) -> 7.2857143 | BE53: =(AU53+AZ53+(BC53/2))*(9/7.5) -> 9
A54: 76248 | B54: Valle del Cauca | C54: Sin clasificación oficial | D54: =AS54+AU54+AV54 -> 7 | E54: =BD54 -> 7.2857143 | F54: =BE54 -> 9 | G54: El Cerrito | H54: =IFERROR(IF($AQ54,INDEX(cpe!$C$2:$C$307,MATCH($AR54,cpe!$F$2:$F$307,0)),INDEX(cpe!$C$2:$C$307,MATCH($AR54,cpe!$D$2:$D$307,0))),"#N/D") -> I.E. Marco Fidel Suarez | I54: =IFERROR(IF($AQ54,INDEX(cpe!$B$2:$B$307,MATCH($AR54,cpe!$F$2:$F$307,0)),INDEX(cpe!$B$2:$B$307,MATCH($AR54,cpe!$D$2:$D$307,0))),"#N/D") -> El Cerrito | J54: =IF($AQ54,"#N/D",IFERROR(INDEX(Olimpiadas!$B$2:$B$61,MATCH($AO54,Olimpiadas!$C$2:$C$61,0)),"#N/D")) -> #N/D | K54: =IF($AQ54,"#N/D",IFERROR(INDEX(Olimpiadas!$A$2:$A$61,MATCH($AO54,Olimpiadas!$C$2:$C$61,0)),"#N/D")) -> #N/D | L54: =IF($AQ54,"#N/D",IFERROR(INDEX(Minculturas!$A$2:$A$48,MATCH($AO54,Minculturas!$C$2:$C$48,0)),"#N/D")) -> #N/D | M54: =IF($AQ54,"#N/D",IFERROR(INDEX(Minculturas!$B$2:$B$48,MATCH($AO54,Minculturas!$C$2:$C$48,0)),"#N/D")) -> #N/D | N54: 6 | O54: 0 | P54: 2 | Q54: 0 | R54: 1 | S54: 0 | T54: 2 | U54: 1 | V54: 0 | W54: 0 | X54: 0 | Y54: 0 | Z54: 0 | AA54: 0 | AB54: 0 | AC54: 0 | AD54: 0 | AE54: 0 | AF54: 0 | AG54: =SUM(O54:X54) -> 6 | AJ54: 15.2 | AM54: Declarado afectado; sin lugar con nombre propio publicado en este registro. | AO54: =TRIM(SUBSTITUTE(SUBSTITUTE(SUBSTITUTE(SUBSTITUTE(SUBSTITUTE(SUBSTITUTE(SUBSTITUTE(SUBSTITUTE(SUBSTITUTE(LOWER(G54),"á","a"),"é","e"),"í","i"),"ó","o"),"ú","u"),"ñ","n"),"-"," "),","," "),"."," ")) -> el cerrito | AP54: =TRIM(SUBSTITUTE(SUBSTITUTE(SUBSTITUTE(SUBSTITUTE(SUBSTITUTE(SUBSTITUTE(SUBSTITUTE(SUBSTITUTE(SUBSTITUTE(LOWER(B54),"á","a"),"é","e"),"í","i"),"ó","o"),"ú","u"),"ñ","n"),"-"," "),","," "),"."," ")) -> valle del cauca | AQ54: =COUNTIF($AO$2:$AO$433,AO54)>COUNTIFS($AO$2:$AO$433,AO54,$AP$2:$AP$433,AP54) -> FALSE | AR54: =IF(AQ54,AO54&"|"&AP54,AO54) -> el cerrito | AS54: =(I54<>"#N/D")+(J54<>"#N/D")+(L54<>"#N/D") -> 1 | AT54: =SUM(O54:X54) -> 6 | AU54: =IF(AT54<=$AY$2,0,IF(AT54<=$AY$3,1,IF(AT54<=$AY$4,2,3))) -> 3 | AV54: =IF(Y54<=$AY$7,3,IF(Y54<=$AY$8,2,IF(Y54<=$AY$9,1,0))) -> 3 | AZ54: =IF(Y54=0,3,0) -> 3 | BA54: =AS54+AU54+AZ54 -> 7 | BB54: =IFERROR(INDEX('Análisis general'!$E$4:$E$28,MATCH($B54,'Análisis general'!$B$4:$B$28,0)),"") -> 4.9 | BC54: =IF(BB54="","",IF(BB54<=$BG$2,0,IF(BB54<=$BG$3,1,IF(BB54<=$BG$4,2,3)))) -> 3 | BD54: =(AS54+AU54+AZ54+(BC54/2))*(9/10.5) -> 7.2857143 | BE54: =(AU54+AZ54+(BC54/2))*(9/7.5) -> 9
A55: 25839 | B55: Cundinamarca | C55: Sin clasificación oficial | D55: =AS55+AU55+AV55 -> 7 | E55: =BD55 -> 7.2857143 | F55: =BE55 -> 9 | G55: Ubalá | H55: Institucion Educativa Gallardo | I55: Ubalá | J55: #N/D | K55: =IF($AQ55,"#N/D",IFERROR(INDEX(Olimpiadas!$A$2:$A$61,MATCH($AO55,Olimpiadas!$C$2:$C$61,0)),"#N/D")) -> #N/D | L55: =IF($AQ55,"#N/D",IFERROR(INDEX(Minculturas!$A$2:$A$48,MATCH($AO55,Minculturas!$C$2:$C$48,0)),"#N/D")) -> #N/D | M55: =IF($AQ55,"#N/D",IFERROR(INDEX(Minculturas!$B$2:$B$48,MATCH($AO55,Minculturas!$C$2:$C$48,0)),"#N/D")) -> #N/D | N55: 5 | O55: 0 | P55: 2 | Q55: 0 | R55: 0 | S55: 3 | T55: 0 | U55: 0 | V55: 0 | W55: 0 | X55: 0 | Y55: 0 | Z55: 0 | AA55: 0 | AB55: 0 | AC55: 0 | AD55: 0 | AE55: 0 | AF55: 0 | AG55: =SUM(O55:X55) -> 5 | AJ55: 47 | AM55: Declarado afectado en el reparto municipal del EDAN de viviendas de la UNGRD (capa 3iS/iMMAP para OCHA, 12-08-2026). Sin ningún lugar con nombre propio publicado. | AO55: =TRIM(SUBSTITUTE(SUBSTITUTE(SUBSTITUTE(SUBSTITUTE(SUBSTITUTE(SUBSTITUTE(SUBSTITUTE(SUBSTITUTE(SUBSTITUTE(LOWER(G55),"á","a"),"é","e"),"í","i"),"ó","o"),"ú","u"),"ñ","n"),"-"," "),","," "),"."," ")) -> ubala | AP55: =TRIM(SUBSTITUTE(SUBSTITUTE(SUBSTITUTE(SUBSTITUTE(SUBSTITUTE(SUBSTITUTE(SUBSTITUTE(SUBSTITUTE(SUBSTITUTE(LOWER(B55),"á","a"),"é","e"),"í","i"),"ó","o"),"ú","u"),"ñ","n"),"-"," "),","," "),"."," ")) -> cundinamarca | AQ55: =COUNTIF($AO$2:$AO$433,AO55)>COUNTIFS($AO$2:$AO$433,AO55,$AP$2:$AP$433,AP55) -> FALSE | AR55: =IF(AQ55,AO55&"|"&AP55,AO55) -> ubala | AS55: =(I55<>"#N/D")+(J55<>"#N/D")+(L55<>"#N/D") -> 1 | AT55: =SUM(O55:X55) -> 5 | AU55: =IF(AT55<=$AY$2,0,IF(AT55<=$AY$3,1,IF(AT55<=$AY$4,2,3))) -> 3 | AV55: =IF(Y55<=$AY$7,3,IF(Y55<=$AY$8,2,IF(Y55<=$AY$9,1,0))) -> 3 | AZ55: =IF(Y55=0,3,0) -> 3 | BA55: =AS55+AU55+AZ55 -> 7 | BB55: =IFERROR(INDEX('Análisis general'!$E$4:$E$28,MATCH($B55,'Análisis general'!$B$4:$B$28,0)),"") -> 4.1 | BC55: =IF(BB55="","",IF(BB55<=$BG$2,0,IF(BB55<=$BG$3,1,IF(BB55<=$BG$4,2,3)))) -> 3 | BD55: =(AS55+AU55+AZ55+(BC55/2))*(9/10.5) -> 7.2857143 | BE55: =(AU55+AZ55+(BC55/2))*(9/7.5) -> 9
A56: 76869 | B56: Valle del Cauca | C56: Sin clasificación oficial | D56: =AS56+AU56+AV56 -> 7 | E56: =BD56 -> 7.2857143 | F56: =BE56 -> 9 | G56: Vijes | H56: I.E. Maria Inmaculada | I56: Vijes | J56: #N/D | K56: =IF($AQ56,"#N/D",IFERROR(INDEX(Olimpiadas!$A$2:$A$61,MATCH($AO56,Olimpiadas!$C$2:$C$61,0)),"#N/D")) -> #N/D | L56: =IF($AQ56,"#N/D",IFERROR(INDEX(Minculturas!$A$2:$A$48,MATCH($AO56,Minculturas!$C$2:$C$48,0)),"#N/D")) -> #N/D | M56: =IF($AQ56,"#N/D",IFERROR(INDEX(Minculturas!$B$2:$B$48,MATCH($AO56,Minculturas!$C$2:$C$48,0)),"#N/D")) -> #N/D | N56: 5 | O56: 0 | P56: 1 | Q56: 1 | R56: 0 | S56: 0 | T56: 1 | U56: 0 | V56: 1 | W56: 0 | X56: 1 | Y56: 0 | Z56: 0 | AA56: 0 | AB56: 0 | AC56: 0 | AD56: 0 | AE56: 0 | AF56: 0 | AG56: =SUM(O56:X56) -> 5 | AJ56: 19 | AM56: Declarado afectado en el reparto municipal del EDAN de viviendas de la UNGRD (capa 3iS/iMMAP para OCHA, 12-08-2026). Sin ningún lugar con nombre propio publicado. | AO56: =TRIM(SUBSTITUTE(SUBSTITUTE(SUBSTITUTE(SUBSTITUTE(SUBSTITUTE(SUBSTITUTE(SUBSTITUTE(SUBSTITUTE(SUBSTITUTE(LOWER(G56),"á","a"),"é","e"),"í","i"),"ó","o"),"ú","u"),"ñ","n"),"-"," "),","," "),"."," ")) -> vijes | AP56: =TRIM(SUBSTITUTE(SUBSTITUTE(SUBSTITUTE(SUBSTITUTE(SUBSTITUTE(SUBSTITUTE(SUBSTITUTE(SUBSTITUTE(SUBSTITUTE(LOWER(B56),"á","a"),"é","e"),"í","i"),"ó","o"),"ú","u"),"ñ","n"),"-"," "),","," "),"."," ")) -> valle del cauca | AQ56: =COUNTIF($AO$2:$AO$433,AO56)>COUNTIFS($AO$2:$AO$433,AO56,$AP$2:$AP$433,AP56) -> FALSE | AR56: =IF(AQ56,AO56&"|"&AP56,AO56) -> vijes | AS56: =(I56<>"#N/D")+(J56<>"#N/D")+(L56<>"#N/D") -> 1 | AT56: =SUM(O56:X56) -> 5 | AU56: =IF(AT56<=$AY$2,0,IF(AT56<=$AY$3,1,IF(AT56<=$AY$4,2,3))) -> 3 | AV56: =IF(Y56<=$AY$7,3,IF(Y56<=$AY$8,2,IF(Y56<=$AY$9,1,0))) -> 3 | AZ56: =IF(Y56=0,3,0) -> 3 | BA56: =AS56+AU56+AZ56 -> 7 | BB56: =IFERROR(INDEX('Análisis general'!$E$4:$E$28,MATCH($B56,'Análisis general'!$B$4:$B$28,0)),"") -> 4.9 | BC56: =IF(BB56="","",IF(BB56<=$BG$2,0,IF(BB56<=$BG$3,1,IF(BB56<=$BG$4,2,3)))) -> 3 | BD56: =(AS56+AU56+AZ56+(BC56/2))*(9/10.5) -> 7.2857143 | BE56: =(AU56+AZ56+(BC56/2))*(9/7.5) -> 9
A57: 73283 | B57: Tolima | C57: Sin clasificación oficial | D57: =AS57+AU57+AV57 -> 7 | E57: =BD57 -> 7.2857143 | F57: =BE57 -> 9 | G57: Fresno | H57: =IFERROR(IF($AQ57,INDEX(cpe!$C$2:$C$307,MATCH($AR57,cpe!$F$2:$F$307,0)),INDEX(cpe!$C$2:$C$307,MATCH($AR57,cpe!$D$2:$D$307,0))),"#N/D") -> Inst. Educativa Monse¿or Sarmiento Peralta | I57: =IFERROR(IF($AQ57,INDEX(cpe!$B$2:$B$307,MATCH($AR57,cpe!$F$2:$F$307,0)),INDEX(cpe!$B$2:$B$307,MATCH($AR57,cpe!$D$2:$D$307,0))),"#N/D") -> Fresno | J57: =IF($AQ57,"#N/D",IFERROR(INDEX(Olimpiadas!$B$2:$B$61,MATCH($AO57,Olimpiadas!$C$2:$C$61,0)),"#N/D")) -> #N/D | K57: =IF($AQ57,"#N/D",IFERROR(INDEX(Olimpiadas!$A$2:$A$61,MATCH($AO57,Olimpiadas!$C$2:$C$61,0)),"#N/D")) -> #N/D | L57: =IF($AQ57,"#N/D",IFERROR(INDEX(Minculturas!$A$2:$A$48,MATCH($AO57,Minculturas!$C$2:$C$48,0)),"#N/D")) -> #N/D | M57: =IF($AQ57,"#N/D",IFERROR(INDEX(Minculturas!$B$2:$B$48,MATCH($AO57,Minculturas!$C$2:$C$48,0)),"#N/D")) -> #N/D | N57: 4 | O57: 0 | P57: 0 | Q57: 0 | R57: 0 | S57: 0 | T57: 0 | U57: 0 | V57: 3 | W57: 0 | X57: 1 | Y57: 0 | Z57: 0 | AA57: 0 | AB57: 0 | AC57: 0 | AD57: 0 | AE57: 0 | AF57: 0 | AG57: =SUM(O57:X57) -> 4 | AJ57: 33.6 | AM57: Declarado afectado; sin lugar con nombre propio publicado en este registro. | AO57: =TRIM(SUBSTITUTE(SUBSTITUTE(SUBSTITUTE(SUBSTITUTE(SUBSTITUTE(SUBSTITUTE(SUBSTITUTE(SUBSTITUTE(SUBSTITUTE(LOWER(G57),"á","a"),"é","e"),"í","i"),"ó","o"),"ú","u"),"ñ","n"),"-"," "),","," "),"."," ")) -> fresno | AP57: =TRIM(SUBSTITUTE(SUBSTITUTE(SUBSTITUTE(SUBSTITUTE(SUBSTITUTE(SUBSTITUTE(SUBSTITUTE(SUBSTITUTE(SUBSTITUTE(LOWER(B57),"á","a"),"é","e"),"í","i"),"ó","o"),"ú","u"),"ñ","n"),"-"," "),","," "),"."," ")) -> tolima | AQ57: =COUNTIF($AO$2:$AO$433,AO57)>COUNTIFS($AO$2:$AO$433,AO57,$AP$2:$AP$433,AP57) -> FALSE | AR57: =IF(AQ57,AO57&"|"&AP57,AO57) -> fresno | AS57: =(I57<>"#N/D")+(J57<>"#N/D")+(L57<>"#N/D") -> 1 | AT57: =SUM(O57:X57) -> 4 | AU57: =IF(AT57<=$AY$2,0,IF(AT57<=$AY$3,1,IF(AT57<=$AY$4,2,3))) -> 3 | AV57: =IF(Y57<=$AY$7,3,IF(Y57<=$AY$8,2,IF(Y57<=$AY$9,1,0))) -> 3 | AZ57: =IF(Y57=0,3,0) -> 3 | BA57: =AS57+AU57+AZ57 -> 7 | BB57: =IFERROR(INDEX('Análisis general'!$E$4:$E$28,MATCH($B57,'Análisis general'!$B$4:$B$28,0)),"") -> 12.2 | BC57: =IF(BB57="","",IF(BB57<=$BG$2,0,IF(BB57<=$BG$3,1,IF(BB57<=$BG$4,2,3)))) -> 3 | BD57: =(AS57+AU57+AZ57+(BC57/2))*(9/10.5) -> 7.2857143 | BE57: =(AU57+AZ57+(BC57/2))*(9/7.5) -> 9
A58: 73520 | B58: Tolima | C58: Sin clasificación oficial | D58: =AS58+AU58+AV58 -> 7 | E58: =BD58 -> 7.2857143 | F58: =BE58 -> 9 | G58: Palocabildo | H58: =IFERROR(IF($AQ58,INDEX(cpe!$C$2:$C$307,MATCH($AR58,cpe!$F$2:$F$307,0)),INDEX(cpe!$C$2:$C$307,MATCH($AR58,cpe!$D$2:$D$307,0))),"#N/D") -> Institucion Educativa Sucre | I58: =IFERROR(IF($AQ58,INDEX(cpe!$B$2:$B$307,MATCH($AR58,cpe!$F$2:$F$307,0)),INDEX(cpe!$B$2:$B$307,MATCH($AR58,cpe!$D$2:$D$307,0))),"#N/D") -> Palocabildo | J58: =IF($AQ58,"#N/D",IFERROR(INDEX(Olimpiadas!$B$2:$B$61,MATCH($AO58,Olimpiadas!$C$2:$C$61,0)),"#N/D")) -> #N/D | K58: =IF($AQ58,"#N/D",IFERROR(INDEX(Olimpiadas!$A$2:$A$61,MATCH($AO58,Olimpiadas!$C$2:$C$61,0)),"#N/D")) -> #N/D | L58: =IF($AQ58,"#N/D",IFERROR(INDEX(Minculturas!$A$2:$A$48,MATCH($AO58,Minculturas!$C$2:$C$48,0)),"#N/D")) -> #N/D | M58: =IF($AQ58,"#N/D",IFERROR(INDEX(Minculturas!$B$2:$B$48,MATCH($AO58,Minculturas!$C$2:$C$48,0)),"#N/D")) -> #N/D | N58: 4 | O58: 0 | P58: 0 | Q58: 0 | R58: 1 | S58: 1 | T58: 0 | U58: 1 | V58: 1 | W58: 0 | X58: 0 | Y58: 0 | Z58: 0 | AA58: 0 | AB58: 0 | AC58: 0 | AD58: 0 | AE58: 0 | AF58: 0 | AG58: =SUM(O58:X58) -> 4 | AJ58: 45.5 | AM58: Declarado afectado; sin lugar con nombre propio publicado en este registro. | AO58: =TRIM(SUBSTITUTE(SUBSTITUTE(SUBSTITUTE(SUBSTITUTE(SUBSTITUTE(SUBSTITUTE(SUBSTITUTE(SUBSTITUTE(SUBSTITUTE(LOWER(G58),"á","a"),"é","e"),"í","i"),"ó","o"),"ú","u"),"ñ","n"),"-"," "),","," "),"."," ")) -> palocabildo | AP58: =TRIM(SUBSTITUTE(SUBSTITUTE(SUBSTITUTE(SUBSTITUTE(SUBSTITUTE(SUBSTITUTE(SUBSTITUTE(SUBSTITUTE(SUBSTITUTE(LOWER(B58),"á","a"),"é","e"),"í","i"),"ó","o"),"ú","u"),"ñ","n"),"-"," "),","," "),"."," ")) -> tolima | AQ58: =COUNTIF($AO$2:$AO$433,AO58)>COUNTIFS($AO$2:$AO$433,AO58,$AP$2:$AP$433,AP58) -> FALSE | AR58: =IF(AQ58,AO58&"|"&AP58,AO58) -> palocabildo | AS58: =(I58<>"#N/D")+(J58<>"#N/D")+(L58<>"#N/D") -> 1 | AT58: =SUM(O58:X58) -> 4 | AU58: =IF(AT58<=$AY$2,0,IF(AT58<=$AY$3,1,IF(AT58<=$AY$4,2,3))) -> 3 | AV58: =IF(Y58<=$AY$7,3,IF(Y58<=$AY$8,2,IF(Y58<=$AY$9,1,0))) -> 3 | AZ58: =IF(Y58=0,3,0) -> 3 | BA58: =AS58+AU58+AZ58 -> 7 | BB58: =IFERROR(INDEX('Análisis general'!$E$4:$E$28,MATCH($B58,'Análisis general'!$B$4:$B$28,0)),"") -> 12.2 | BC58: =IF(BB58="","",IF(BB58<=$BG$2,0,IF(BB58<=$BG$3,1,IF(BB58<=$BG$4,2,3)))) -> 3 | BD58: =(AS58+AU58+AZ58+(BC58/2))*(9/10.5) -> 7.2857143 | BE58: =(AU58+AZ58+(BC58/2))*(9/7.5) -> 9
A59: 41016 | B59: Huila | C59: Sin clasificación oficial | D59: =AS59+AU59+AV59 -> 7 | E59: =BD59 -> 7.2857143 | F59: =BE59 -> 9 | G59: Aipe | H59: =IFERROR(IF($AQ59,INDEX(cpe!$C$2:$C$307,MATCH($AR59,cpe!$F$2:$F$307,0)),INDEX(cpe!$C$2:$C$307,MATCH($AR59,cpe!$D$2:$D$307,0))),"#N/D") -> Institucion Educativa Santa Lucia | I59: =IFERROR(IF($AQ59,INDEX(cpe!$B$2:$B$307,MATCH($AR59,cpe!$F$2:$F$307,0)),INDEX(cpe!$B$2:$B$307,MATCH($AR59,cpe!$D$2:$D$307,0))),"#N/D") -> Aipe | J59: =IF($AQ59,"#N/D",IFERROR(INDEX(Olimpiadas!$B$2:$B$61,MATCH($AO59,Olimpiadas!$C$2:$C$61,0)),"#N/D")) -> #N/D | K59: =IF($AQ59,"#N/D",IFERROR(INDEX(Olimpiadas!$A$2:$A$61,MATCH($AO59,Olimpiadas!$C$2:$C$61,0)),"#N/D")) -> #N/D | L59: =IF($AQ59,"#N/D",IFERROR(INDEX(Minculturas!$A$2:$A$48,MATCH($AO59,Minculturas!$C$2:$C$48,0)),"#N/D")) -> #N/D | M59: =IF($AQ59,"#N/D",IFERROR(INDEX(Minculturas!$B$2:$B$48,MATCH($AO59,Minculturas!$C$2:$C$48,0)),"#N/D")) -> #N/D | N59: 3 | O59: 0 | P59: 0 | Q59: 3 | R59: 0 | S59: 0 | T59: 0 | U59: 0 | V59: 0 | W59: 0 | X59: 0 | Y59: 0 | Z59: 0 | AA59: 0 | AB59: 0 | AC59: 0 | AD59: 0 | AE59: 0 | AF59: 0 | AG59: =SUM(O59:X59) -> 3 | AJ59: 35.4 | AM59: Declarado afectado; sin lugar con nombre propio publicado en este registro. | AO59: =TRIM(SUBSTITUTE(SUBSTITUTE(SUBSTITUTE(SUBSTITUTE(SUBSTITUTE(SUBSTITUTE(SUBSTITUTE(SUBSTITUTE(SUBSTITUTE(LOWER(G59),"á","a"),"é","e"),"í","i"),"ó","o"),"ú","u"),"ñ","n"),"-"," "),","," "),"."," ")) -> aipe | AP59: =TRIM(SUBSTITUTE(SUBSTITUTE(SUBSTITUTE(SUBSTITUTE(SUBSTITUTE(SUBSTITUTE(SUBSTITUTE(SUBSTITUTE(SUBSTITUTE(LOWER(B59),"á","a"),"é","e"),"í","i"),"ó","o"),"ú","u"),"ñ","n"),"-"," "),","," "),"."," ")) -> huila | AQ59: =COUNTIF($AO$2:$AO$433,AO59)>COUNTIFS($AO$2:$AO$433,AO59,$AP$2:$AP$433,AP59) -> FALSE | AR59: =IF(AQ59,AO59&"|"&AP59,AO59) -> aipe | AS59: =(I59<>"#N/D")+(J59<>"#N/D")+(L59<>"#N/D") -> 1 | AT59: =SUM(O59:X59) -> 3 | AU59: =IF(AT59<=$AY$2,0,IF(AT59<=$AY$3,1,IF(AT59<=$AY$4,2,3))) -> 3 | AV59: =IF(Y59<=$AY$7,3,IF(Y59<=$AY$8,2,IF(Y59<=$AY$9,1,0))) -> 3 | AZ59: =IF(Y59=0,3,0) -> 3 | BA59: =AS59+AU59+AZ59 -> 7 | BB59: =IFERROR(INDEX('Análisis general'!$E$4:$E$28,MATCH($B59,'Análisis general'!$B$4:$B$28,0)),"") -> 9.7 | BC59: =IF(BB59="","",IF(BB59<=$BG$2,0,IF(BB59<=$BG$3,1,IF(BB59<=$BG$4,2,3)))) -> 3 | BD59: =(AS59+AU59+AZ59+(BC59/2))*(9/10.5) -> 7.2857143 | BE59: =(AU59+AZ59+(BC59/2))*(9/7.5) -> 9
A60: 73236 | B60: Tolima | C60: Sin clasificación oficial | D60: =AS60+AU60+AV60 -> 7 | E60: =BD60 -> 7.2857143 | F60: =BE60 -> 9 | G60: Dolores | H60: =IFERROR(IF($AQ60,INDEX(cpe!$C$2:$C$307,MATCH($AR60,cpe!$F$2:$F$307,0)),INDEX(cpe!$C$2:$C$307,MATCH($AR60,cpe!$D$2:$D$307,0))),"#N/D") -> Intitución Educativa Maria Auxiliadora | I60: =IFERROR(IF($AQ60,INDEX(cpe!$B$2:$B$307,MATCH($AR60,cpe!$F$2:$F$307,0)),INDEX(cpe!$B$2:$B$307,MATCH($AR60,cpe!$D$2:$D$307,0))),"#N/D") -> Dolores | J60: =IF($AQ60,"#N/D",IFERROR(INDEX(Olimpiadas!$B$2:$B$61,MATCH($AO60,Olimpiadas!$C$2:$C$61,0)),"#N/D")) -> #N/D | K60: =IF($AQ60,"#N/D",IFERROR(INDEX(Olimpiadas!$A$2:$A$61,MATCH($AO60,Olimpiadas!$C$2:$C$61,0)),"#N/D")) -> #N/D | L60: =IF($AQ60,"#N/D",IFERROR(INDEX(Minculturas!$A$2:$A$48,MATCH($AO60,Minculturas!$C$2:$C$48,0)),"#N/D")) -> #N/D | M60: =IF($AQ60,"#N/D",IFERROR(INDEX(Minculturas!$B$2:$B$48,MATCH($AO60,Minculturas!$C$2:$C$48,0)),"#N/D")) -> #N/D | N60: 3 | O60: 0 | P60: 1 | Q60: 0 | R60: 0 | S60: 0 | T60: 1 | U60: 1 | V60: 0 | W60: 0 | X60: 0 | Y60: 0 | Z60: 0 | AA60: 0 | AB60: 0 | AC60: 0 | AD60: 0 | AE60: 0 | AF60: 0 | AG60: =SUM(O60:X60) -> 3 | AJ60: 32.8 | AM60: Declarado afectado; sin lugar con nombre propio publicado en este registro. | AO60: =TRIM(SUBSTITUTE(SUBSTITUTE(SUBSTITUTE(SUBSTITUTE(SUBSTITUTE(SUBSTITUTE(SUBSTITUTE(SUBSTITUTE(SUBSTITUTE(LOWER(G60),"á","a"),"é","e"),"í","i"),"ó","o"),"ú","u"),"ñ","n"),"-"," "),","," "),"."," ")) -> dolores | AP60: =TRIM(SUBSTITUTE(SUBSTITUTE(SUBSTITUTE(SUBSTITUTE(SUBSTITUTE(SUBSTITUTE(SUBSTITUTE(SUBSTITUTE(SUBSTITUTE(LOWER(B60),"á","a"),"é","e"),"í","i"),"ó","o"),"ú","u"),"ñ","n"),"-"," "),","," "),"."," ")) -> tolima | AQ60: =COUNTIF($AO$2:$AO$433,AO60)>COUNTIFS($AO$2:$AO$433,AO60,$AP$2:$AP$433,AP60) -> FALSE | AR60: =IF(AQ60,AO60&"|"&AP60,AO60) -> dolores | AS60: =(I60<>"#N/D")+(J60<>"#N/D")+(L60<>"#N/D") -> 1 | AT60: =SUM(O60:X60) -> 3 | AU60: =IF(AT60<=$AY$2,0,IF(AT60<=$AY$3,1,IF(AT60<=$AY$4,2,3))) -> 3 | AV60: =IF(Y60<=$AY$7,3,IF(Y60<=$AY$8,2,IF(Y60<=$AY$9,1,0))) -> 3 | AZ60: =IF(Y60=0,3,0) -> 3 | BA60: =AS60+AU60+AZ60 -> 7 | BB60: =IFERROR(INDEX('Análisis general'!$E$4:$E$28,MATCH($B60,'Análisis general'!$B$4:$B$28,0)),"") -> 12.2 | BC60: =IF(BB60="","",IF(BB60<=$BG$2,0,IF(BB60<=$BG$3,1,IF(BB60<=$BG$4,2,3)))) -> 3 | BD60: =(AS60+AU60+AZ60+(BC60/2))*(9/10.5) -> 7.2857143 | BE60: =(AU60+AZ60+(BC60/2))*(9/7.5) -> 9
A61: 73555 | B61: Tolima | C61: Sin clasificación oficial | D61: =AS61+AU61+AV61 -> 7 | E61: =BD61 -> 7.2857143 | F61: =BE61 -> 9 | G61: Planadas | H61: Institucion Educativa Tecnica Agroindustrial San Gerardo | I61: Planadas | J61: #N/D | K61: =IF($AQ61,"#N/D",IFERROR(INDEX(Olimpiadas!$A$2:$A$61,MATCH($AO61,Olimpiadas!$C$2:$C$61,0)),"#N/D")) -> #N/D | L61: =IF($AQ61,"#N/D",IFERROR(INDEX(Minculturas!$A$2:$A$48,MATCH($AO61,Minculturas!$C$2:$C$48,0)),"#N/D")) -> #N/D | M61: =IF($AQ61,"#N/D",IFERROR(INDEX(Minculturas!$B$2:$B$48,MATCH($AO61,Minculturas!$C$2:$C$48,0)),"#N/D")) -> #N/D | N61: 3 | O61: 0 | P61: 0 | Q61: 1 | R61: 1 | S61: 0 | T61: 0 | U61: 1 | V61: 0 | W61: 0 | X61: 0 | Y61: 0 | Z61: 0 | AA61: 0 | AB61: 0 | AC61: 0 | AD61: 0 | AE61: 0 | AF61: 0 | AG61: =SUM(O61:X61) -> 3 | AJ61: 55.4 | AM61: Declarado afectado; sin lugar con nombre propio publicado en este registro. | AO61: =TRIM(SUBSTITUTE(SUBSTITUTE(SUBSTITUTE(SUBSTITUTE(SUBSTITUTE(SUBSTITUTE(SUBSTITUTE(SUBSTITUTE(SUBSTITUTE(LOWER(G61),"á","a"),"é","e"),"í","i"),"ó","o"),"ú","u"),"ñ","n"),"-"," "),","," "),"."," ")) -> planadas | AP61: =TRIM(SUBSTITUTE(SUBSTITUTE(SUBSTITUTE(SUBSTITUTE(SUBSTITUTE(SUBSTITUTE(SUBSTITUTE(SUBSTITUTE(SUBSTITUTE(LOWER(B61),"á","a"),"é","e"),"í","i"),"ó","o"),"ú","u"),"ñ","n"),"-"," "),","," "),"."," ")) -> tolima | AQ61: =COUNTIF($AO$2:$AO$433,AO61)>COUNTIFS($AO$2:$AO$433,AO61,$AP$2:$AP$433,AP61) -> FALSE | AR61: =IF(AQ61,AO61&"|"&AP61,AO61) -> planadas | AS61: =(I61<>"#N/D")+(J61<>"#N/D")+(L61<>"#N/D") -> 1 | AT61: =SUM(O61:X61) -> 3 | AU61: =IF(AT61<=$AY$2,0,IF(AT61<=$AY$3,1,IF(AT61<=$AY$4,2,3))) -> 3 | AV61: =IF(Y61<=$AY$7,3,IF(Y61<=$AY$8,2,IF(Y61<=$AY$9,1,0))) -> 3 | AZ61: =IF(Y61=0,3,0) -> 3 | BA61: =AS61+AU61+AZ61 -> 7 | BB61: =IFERROR(INDEX('Análisis general'!$E$4:$E$28,MATCH($B61,'Análisis general'!$B$4:$B$28,0)),"") -> 12.2 | BC61: =IF(BB61="","",IF(BB61<=$BG$2,0,IF(BB61<=$BG$3,1,IF(BB61<=$BG$4,2,3)))) -> 3 | BD61: =(AS61+AU61+AZ61+(BC61/2))*(9/10.5) -> 7.2857143 | BE61: =(AU61+AZ61+(BC61/2))*(9/7.5) -> 9
A62: 73585 | B62: Tolima | C62: Sin clasificación oficial | D62: =AS62+AU62+AV62 -> 7 | E62: =BD62 -> 7.2857143 | F62: =BE62 -> 9 | G62: Purificación | H62: Institucion Educativa Santa Teresita | I62: Purificación | J62: #N/D | K62: =IF($AQ62,"#N/D",IFERROR(INDEX(Olimpiadas!$A$2:$A$61,MATCH($AO62,Olimpiadas!$C$2:$C$61,0)),"#N/D")) -> #N/D | L62: =IF($AQ62,"#N/D",IFERROR(INDEX(Minculturas!$A$2:$A$48,MATCH($AO62,Minculturas!$C$2:$C$48,0)),"#N/D")) -> #N/D | M62: =IF($AQ62,"#N/D",IFERROR(INDEX(Minculturas!$B$2:$B$48,MATCH($AO62,Minculturas!$C$2:$C$48,0)),"#N/D")) -> #N/D | N62: 3 | O62: 0 | P62: 2 | Q62: 0 | R62: 1 | S62: 0 | T62: 0 | U62: 0 | V62: 0 | W62: 0 | X62: 0 | Y62: 0 | Z62: 0 | AA62: 0 | AB62: 0 | AC62: 0 | AD62: 0 | AE62: 0 | AF62: 0 | AG62: =SUM(O62:X62) -> 3 | AJ62: 32.6 | AM62: Declarado afectado; sin lugar con nombre propio publicado en este registro. | AO62: =TRIM(SUBSTITUTE(SUBSTITUTE(SUBSTITUTE(SUBSTITUTE(SUBSTITUTE(SUBSTITUTE(SUBSTITUTE(SUBSTITUTE(SUBSTITUTE(LOWER(G62),"á","a"),"é","e"),"í","i"),"ó","o"),"ú","u"),"ñ","n"),"-"," "),","," "),"."," ")) -> purificacion | AP62: =TRIM(SUBSTITUTE(SUBSTITUTE(SUBSTITUTE(SUBSTITUTE(SUBSTITUTE(SUBSTITUTE(SUBSTITUTE(SUBSTITUTE(SUBSTITUTE(LOWER(B62),"á","a"),"é","e"),"í","i"),"ó","o"),"ú","u"),"ñ","n"),"-"," "),","," "),"."," ")) -> tolima | AQ62: =COUNTIF($AO$2:$AO$433,AO62)>COUNTIFS($AO$2:$AO$433,AO62,$AP$2:$AP$433,AP62) -> FALSE | AR62: =IF(AQ62,AO62&"|"&AP62,AO62) -> purificacion | AS62: =(I62<>"#N/D")+(J62<>"#N/D")+(L62<>"#N/D") -> 1 | AT62: =SUM(O62:X62) -> 3 | AU62: =IF(AT62<=$AY$2,0,IF(AT62<=$AY$3,1,IF(AT62<=$AY$4,2,3))) -> 3 | AV62: =IF(Y62<=$AY$7,3,IF(Y62<=$AY$8,2,IF(Y62<=$AY$9,1,0))) -> 3 | AZ62: =IF(Y62=0,3,0) -> 3 | BA62: =AS62+AU62+AZ62 -> 7 | BB62: =IFERROR(INDEX('Análisis general'!$E$4:$E$28,MATCH($B62,'Análisis general'!$B$4:$B$28,0)),"") -> 12.2 | BC62: =IF(BB62="","",IF(BB62<=$BG$2,0,IF(BB62<=$BG$3,1,IF(BB62<=$BG$4,2,3)))) -> 3 | BD62: =(AS62+AU62+AZ62+(BC62/2))*(9/10.5) -> 7.2857143 | BE62: =(AU62+AZ62+(BC62/2))*(9/7.5) -> 9
A63: 41006 | B63: Huila | C63: Sin clasificación oficial | D63: =AS63+AU63+AV63 -> 7 | E63: =BD63 -> 7.2857143 | F63: =BE63 -> 9 | G63: Acevedo | H63: =IFERROR(IF($AQ63,INDEX(cpe!$C$2:$C$307,MATCH($AR63,cpe!$F$2:$F$307,0)),INDEX(cpe!$C$2:$C$307,MATCH($AR63,cpe!$D$2:$D$307,0))),"#N/D") -> Institucion Educativa Villalosada | I63: =IFERROR(IF($AQ63,INDEX(cpe!$B$2:$B$307,MATCH($AR63,cpe!$F$2:$F$307,0)),INDEX(cpe!$B$2:$B$307,MATCH($AR63,cpe!$D$2:$D$307,0))),"#N/D") -> Acevedo | J63: =IF($AQ63,"#N/D",IFERROR(INDEX(Olimpiadas!$B$2:$B$61,MATCH($AO63,Olimpiadas!$C$2:$C$61,0)),"#N/D")) -> #N/D | K63: =IF($AQ63,"#N/D",IFERROR(INDEX(Olimpiadas!$A$2:$A$61,MATCH($AO63,Olimpiadas!$C$2:$C$61,0)),"#N/D")) -> #N/D | L63: =IF($AQ63,"#N/D",IFERROR(INDEX(Minculturas!$A$2:$A$48,MATCH($AO63,Minculturas!$C$2:$C$48,0)),"#N/D")) -> #N/D | M63: =IF($AQ63,"#N/D",IFERROR(INDEX(Minculturas!$B$2:$B$48,MATCH($AO63,Minculturas!$C$2:$C$48,0)),"#N/D")) -> #N/D | N63: 2 | O63: 0 | P63: 0 | Q63: 1 | R63: 0 | S63: 1 | T63: 0 | U63: 0 | V63: 0 | W63: 0 | X63: 0 | Y63: 0 | Z63: 0 | AA63: 0 | AB63: 0 | AC63: 0 | AD63: 0 | AE63: 0 | AF63: 0 | AG63: =SUM(O63:X63) -> 2 | AJ63: 51 | AM63: Declarado afectado; sin lugar con nombre propio publicado en este registro. | AO63: =TRIM(SUBSTITUTE(SUBSTITUTE(SUBSTITUTE(SUBSTITUTE(SUBSTITUTE(SUBSTITUTE(SUBSTITUTE(SUBSTITUTE(SUBSTITUTE(LOWER(G63),"á","a"),"é","e"),"í","i"),"ó","o"),"ú","u"),"ñ","n"),"-"," "),","," "),"."," ")) -> acevedo | AP63: =TRIM(SUBSTITUTE(SUBSTITUTE(SUBSTITUTE(SUBSTITUTE(SUBSTITUTE(SUBSTITUTE(SUBSTITUTE(SUBSTITUTE(SUBSTITUTE(LOWER(B63),"á","a"),"é","e"),"í","i"),"ó","o"),"ú","u"),"ñ","n"),"-"," "),","," "),"."," ")) -> huila | AQ63: =COUNTIF($AO$2:$AO$433,AO63)>COUNTIFS($AO$2:$AO$433,AO63,$AP$2:$AP$433,AP63) -> FALSE | AR63: =IF(AQ63,AO63&"|"&AP63,AO63) -> acevedo | AS63: =(I63<>"#N/D")+(J63<>"#N/D")+(L63<>"#N/D") -> 1 | AT63: =SUM(O63:X63) -> 2 | AU63: =IF(AT63<=$AY$2,0,IF(AT63<=$AY$3,1,IF(AT63<=$AY$4,2,3))) -> 3 | AV63: =IF(Y63<=$AY$7,3,IF(Y63<=$AY$8,2,IF(Y63<=$AY$9,1,0))) -> 3 | AZ63: =IF(Y63=0,3,0) -> 3 | BA63: =AS63+AU63+AZ63 -> 7 | BB63: =IFERROR(INDEX('Análisis general'!$E$4:$E$28,MATCH($B63,'Análisis general'!$B$4:$B$28,0)),"") -> 9.7 | BC63: =IF(BB63="","",IF(BB63<=$BG$2,0,IF(BB63<=$BG$3,1,IF(BB63<=$BG$4,2,3)))) -> 3 | BD63: =(AS63+AU63+AZ63+(BC63/2))*(9/10.5) -> 7.2857143 | BE63: =(AU63+AZ63+(BC63/2))*(9/7.5) -> 9
A64: 73200 | B64: Tolima | C64: Sin clasificación oficial | D64: =AS64+AU64+AV64 -> 7 | E64: =BD64 -> 7.2857143 | F64: =BE64 -> 9 | G64: Coello | H64: =IFERROR(IF($AQ64,INDEX(cpe!$C$2:$C$307,MATCH($AR64,cpe!$F$2:$F$307,0)),INDEX(cpe!$C$2:$C$307,MATCH($AR64,cpe!$D$2:$D$307,0))),"#N/D") -> Institucion Educativa Tulio Enrique Tascon Chambimbal | I64: =IFERROR(IF($AQ64,INDEX(cpe!$B$2:$B$307,MATCH($AR64,cpe!$F$2:$F$307,0)),INDEX(cpe!$B$2:$B$307,MATCH($AR64,cpe!$D$2:$D$307,0))),"#N/D") -> Coello | J64: =IF($AQ64,"#N/D",IFERROR(INDEX(Olimpiadas!$B$2:$B$61,MATCH($AO64,Olimpiadas!$C$2:$C$61,0)),"#N/D")) -> #N/D | K64: =IF($AQ64,"#N/D",IFERROR(INDEX(Olimpiadas!$A$2:$A$61,MATCH($AO64,Olimpiadas!$C$2:$C$61,0)),"#N/D")) -> #N/D | L64: =IF($AQ64,"#N/D",IFERROR(INDEX(Minculturas!$A$2:$A$48,MATCH($AO64,Minculturas!$C$2:$C$48,0)),"#N/D")) -> #N/D | M64: =IF($AQ64,"#N/D",IFERROR(INDEX(Minculturas!$B$2:$B$48,MATCH($AO64,Minculturas!$C$2:$C$48,0)),"#N/D")) -> #N/D | N64: 2 | O64: 0 | P64: 1 | Q64: 0 | R64: 0 | S64: 0 | T64: 0 | U64: 0 | V64: 0 | W64: 1 | X64: 0 | Y64: 0 | Z64: 0 | AA64: 0 | AB64: 0 | AC64: 0 | AD64: 0 | AE64: 0 | AF64: 0 | AG64: =SUM(O64:X64) -> 2 | AJ64: 35.8 | AM64: Declarado afectado; sin lugar con nombre propio publicado en este registro. | AO64: =TRIM(SUBSTITUTE(SUBSTITUTE(SUBSTITUTE(SUBSTITUTE(SUBSTITUTE(SUBSTITUTE(SUBSTITUTE(SUBSTITUTE(SUBSTITUTE(LOWER(G64),"á","a"),"é","e"),"í","i"),"ó","o"),"ú","u"),"ñ","n"),"-"," "),","," "),"."," ")) -> coello | AP64: =TRIM(SUBSTITUTE(SUBSTITUTE(SUBSTITUTE(SUBSTITUTE(SUBSTITUTE(SUBSTITUTE(SUBSTITUTE(SUBSTITUTE(SUBSTITUTE(LOWER(B64),"á","a"),"é","e"),"í","i"),"ó","o"),"ú","u"),"ñ","n"),"-"," "),","," "),"."," ")) -> tolima | AQ64: =COUNTIF($AO$2:$AO$433,AO64)>COUNTIFS($AO$2:$AO$433,AO64,$AP$2:$AP$433,AP64) -> FALSE | AR64: =IF(AQ64,AO64&"|"&AP64,AO64) -> coello | AS64: =(I64<>"#N/D")+(J64<>"#N/D")+(L64<>"#N/D") -> 1 | AT64: =SUM(O64:X64) -> 2 | AU64: =IF(AT64<=$AY$2,0,IF(AT64<=$AY$3,1,IF(AT64<=$AY$4,2,3))) -> 3 | AV64: =IF(Y64<=$AY$7,3,IF(Y64<=$AY$8,2,IF(Y64<=$AY$9,1,0))) -> 3 | AZ64: =IF(Y64=0,3,0) -> 3 | BA64: =AS64+AU64+AZ64 -> 7 | BB64: =IFERROR(INDEX('Análisis general'!$E$4:$E$28,MATCH($B64,'Análisis general'!$B$4:$B$28,0)),"") -> 12.2 | BC64: =IF(BB64="","",IF(BB64<=$BG$2,0,IF(BB64<=$BG$3,1,IF(BB64<=$BG$4,2,3)))) -> 3 | BD64: =(AS64+AU64+AZ64+(BC64/2))*(9/10.5) -> 7.2857143 | BE64: =(AU64+AZ64+(BC64/2))*(9/7.5) -> 9
A65: 73504 | B65: Tolima | C65: Sin clasificación oficial | D65: =AS65+AU65+AV65 -> 7 | E65: =BD65 -> 7.2857143 | F65: =BE65 -> 9 | G65: Ortega | H65: =IFERROR(IF($AQ65,INDEX(cpe!$C$2:$C$307,MATCH($AR65,cpe!$F$2:$F$307,0)),INDEX(cpe!$C$2:$C$307,MATCH($AR65,cpe!$D$2:$D$307,0))),"#N/D") -> IE. Tecnica Agropecuaria Nuestra Senora del Carmen de Espriella | I65: =IFERROR(IF($AQ65,INDEX(cpe!$B$2:$B$307,MATCH($AR65,cpe!$F$2:$F$307,0)),INDEX(cpe!$B$2:$B$307,MATCH($AR65,cpe!$D$2:$D$307,0))),"#N/D") -> Ortega | J65: =IF($AQ65,"#N/D",IFERROR(INDEX(Olimpiadas!$B$2:$B$61,MATCH($AO65,Olimpiadas!$C$2:$C$61,0)),"#N/D")) -> #N/D | K65: =IF($AQ65,"#N/D",IFERROR(INDEX(Olimpiadas!$A$2:$A$61,MATCH($AO65,Olimpiadas!$C$2:$C$61,0)),"#N/D")) -> #N/D | L65: =IF($AQ65,"#N/D",IFERROR(INDEX(Minculturas!$A$2:$A$48,MATCH($AO65,Minculturas!$C$2:$C$48,0)),"#N/D")) -> #N/D | M65: =IF($AQ65,"#N/D",IFERROR(INDEX(Minculturas!$B$2:$B$48,MATCH($AO65,Minculturas!$C$2:$C$48,0)),"#N/D")) -> #N/D | N65: 2 | O65: 0 | P65: 0 | Q65: 0 | R65: 1 | S65: 0 | T65: 0 | U65: 1 | V65: 0 | W65: 0 | X65: 0 | Y65: 0 | Z65: 0 | AA65: 0 | AB65: 0 | AC65: 0 | AD65: 0 | AE65: 0 | AF65: 0 | AG65: =SUM(O65:X65) -> 2 | AJ65: 51.3 | AM65: Declarado afectado; sin lugar con nombre propio publicado en este registro. | AO65: =TRIM(SUBSTITUTE(SUBSTITUTE(SUBSTITUTE(SUBSTITUTE(SUBSTITUTE(SUBSTITUTE(SUBSTITUTE(SUBSTITUTE(SUBSTITUTE(LOWER(G65),"á","a"),"é","e"),"í","i"),"ó","o"),"ú","u"),"ñ","n"),"-"," "),","," "),"."," ")) -> ortega | AP65: =TRIM(SUBSTITUTE(SUBSTITUTE(SUBSTITUTE(SUBSTITUTE(SUBSTITUTE(SUBSTITUTE(SUBSTITUTE(SUBSTITUTE(SUBSTITUTE(LOWER(B65),"á","a"),"é","e"),"í","i"),"ó","o"),"ú","u"),"ñ","n"),"-"," "),","," "),"."," ")) -> tolima | AQ65: =COUNTIF($AO$2:$AO$433,AO65)>COUNTIFS($AO$2:$AO$433,AO65,$AP$2:$AP$433,AP65) -> FALSE | AR65: =IF(AQ65,AO65&"|"&AP65,AO65) -> ortega | AS65: =(I65<>"#N/D")+(J65<>"#N/D")+(L65<>"#N/D") -> 1 | AT65: =SUM(O65:X65) -> 2 | AU65: =IF(AT65<=$AY$2,0,IF(AT65<=$AY$3,1,IF(AT65<=$AY$4,2,3))) -> 3 | AV65: =IF(Y65<=$AY$7,3,IF(Y65<=$AY$8,2,IF(Y65<=$AY$9,1,0))) -> 3 | AZ65: =IF(Y65=0,3,0) -> 3 | BA65: =AS65+AU65+AZ65 -> 7 | BB65: =IFERROR(INDEX('Análisis general'!$E$4:$E$28,MATCH($B65,'Análisis general'!$B$4:$B$28,0)),"") -> 12.2 | BC65: =IF(BB65="","",IF(BB65<=$BG$2,0,IF(BB65<=$BG$3,1,IF(BB65<=$BG$4,2,3)))) -> 3 | BD65: =(AS65+AU65+AZ65+(BC65/2))*(9/10.5) -> 7.2857143 | BE65: =(AU65+AZ65+(BC65/2))*(9/7.5) -> 9
A66: 41615 | B66: Huila | C66: Sin clasificación oficial | D66: =AS66+AU66+AV66 -> 7 | E66: =BD66 -> 7.2857143 | F66: =BE66 -> 9 | G66: Rivera | H66: Centro Etnoeducativo Pooloshi | I66: Rivera | J66: #N/D | K66: =IF($AQ66,"#N/D",IFERROR(INDEX(Olimpiadas!$A$2:$A$61,MATCH($AO66,Olimpiadas!$C$2:$C$61,0)),"#N/D")) -> #N/D | L66: =IF($AQ66,"#N/D",IFERROR(INDEX(Minculturas!$A$2:$A$48,MATCH($AO66,Minculturas!$C$2:$C$48,0)),"#N/D")) -> #N/D | M66: =IF($AQ66,"#N/D",IFERROR(INDEX(Minculturas!$B$2:$B$48,MATCH($AO66,Minculturas!$C$2:$C$48,0)),"#N/D")) -> #N/D | N66: 2 | O66: 0 | P66: 0 | Q66: 0 | R66: 0 | S66: 2 | T66: 0 | U66: 0 | V66: 0 | W66: 0 | X66: 0 | Y66: 0 | Z66: 0 | AA66: 0 | AB66: 0 | AC66: 0 | AD66: 0 | AE66: 0 | AF66: 0 | AG66: =SUM(O66:X66) -> 2 | AJ66: 27.4 | AM66: Declarado afectado; sin lugar con nombre propio publicado en este registro. | AO66: =TRIM(SUBSTITUTE(SUBSTITUTE(SUBSTITUTE(SUBSTITUTE(SUBSTITUTE(SUBSTITUTE(SUBSTITUTE(SUBSTITUTE(SUBSTITUTE(LOWER(G66),"á","a"),"é","e"),"í","i"),"ó","o"),"ú","u"),"ñ","n"),"-"," "),","," "),"."," ")) -> rivera | AP66: =TRIM(SUBSTITUTE(SUBSTITUTE(SUBSTITUTE(SUBSTITUTE(SUBSTITUTE(SUBSTITUTE(SUBSTITUTE(SUBSTITUTE(SUBSTITUTE(LOWER(B66),"á","a"),"é","e"),"í","i"),"ó","o"),"ú","u"),"ñ","n"),"-"," "),","," "),"."," ")) -> huila | AQ66: =COUNTIF($AO$2:$AO$433,AO66)>COUNTIFS($AO$2:$AO$433,AO66,$AP$2:$AP$433,AP66) -> FALSE | AR66: =IF(AQ66,AO66&"|"&AP66,AO66) -> rivera | AS66: =(I66<>"#N/D")+(J66<>"#N/D")+(L66<>"#N/D") -> 1 | AT66: =SUM(O66:X66) -> 2 | AU66: =IF(AT66<=$AY$2,0,IF(AT66<=$AY$3,1,IF(AT66<=$AY$4,2,3))) -> 3 | AV66: =IF(Y66<=$AY$7,3,IF(Y66<=$AY$8,2,IF(Y66<=$AY$9,1,0))) -> 3 | AZ66: =IF(Y66=0,3,0) -> 3 | BA66: =AS66+AU66+AZ66 -> 7 | BB66: =IFERROR(INDEX('Análisis general'!$E$4:$E$28,MATCH($B66,'Análisis general'!$B$4:$B$28,0)),"") -> 9.7 | BC66: =IF(BB66="","",IF(BB66<=$BG$2,0,IF(BB66<=$BG$3,1,IF(BB66<=$BG$4,2,3)))) -> 3 | BD66: =(AS66+AU66+AZ66+(BC66/2))*(9/10.5) -> 7.2857143 | BE66: =(AU66+AZ66+(BC66/2))*(9/7.5) -> 9
A67: 41676 | B67: Huila | C67: Sin clasificación oficial | D67: =AS67+AU67+AV67 -> 7 | E67: =BD67 -> 7.2857143 | F67: =BE67 -> 9 | G67: Santa María | H67: Institucion Educativa el Limonar | I67: Santa María | J67: #N/D | K67: =IF($AQ67,"#N/D",IFERROR(INDEX(Olimpiadas!$A$2:$A$61,MATCH($AO67,Olimpiadas!$C$2:$C$61,0)),"#N/D")) -> #N/D | L67: =IF($AQ67,"#N/D",IFERROR(INDEX(Minculturas!$A$2:$A$48,MATCH($AO67,Minculturas!$C$2:$C$48,0)),"#N/D")) -> #N/D | M67: =IF($AQ67,"#N/D",IFERROR(INDEX(Minculturas!$B$2:$B$48,MATCH($AO67,Minculturas!$C$2:$C$48,0)),"#N/D")) -> #N/D | N67: 2 | O67: 0 | P67: 0 | Q67: 1 | R67: 0 | S67: 1 | T67: 0 | U67: 0 | V67: 0 | W67: 0 | X67: 0 | Y67: 0 | Z67: 0 | AA67: 0 | AB67: 0 | AC67: 0 | AD67: 0 | AE67: 0 | AF67: 0 | AG67: =SUM(O67:X67) -> 2 | AH67: 3 | AI67: 7 | AJ67: 51.5 | AM67: Declarado afectado; sin lugar con nombre propio publicado en este registro. | AO67: =TRIM(SUBSTITUTE(SUBSTITUTE(SUBSTITUTE(SUBSTITUTE(SUBSTITUTE(SUBSTITUTE(SUBSTITUTE(SUBSTITUTE(SUBSTITUTE(LOWER(G67),"á","a"),"é","e"),"í","i"),"ó","o"),"ú","u"),"ñ","n"),"-"," "),","," "),"."," ")) -> santa maria | AP67: =TRIM(SUBSTITUTE(SUBSTITUTE(SUBSTITUTE(SUBSTITUTE(SUBSTITUTE(SUBSTITUTE(SUBSTITUTE(SUBSTITUTE(SUBSTITUTE(LOWER(B67),"á","a"),"é","e"),"í","i"),"ó","o"),"ú","u"),"ñ","n"),"-"," "),","," "),"."," ")) -> huila | AQ67: =COUNTIF($AO$2:$AO$433,AO67)>COUNTIFS($AO$2:$AO$433,AO67,$AP$2:$AP$433,AP67) -> FALSE | AR67: =IF(AQ67,AO67&"|"&AP67,AO67) -> santa maria | AS67: =(I67<>"#N/D")+(J67<>"#N/D")+(L67<>"#N/D") -> 1 | AT67: =SUM(O67:X67) -> 2 | AU67: =IF(AT67<=$AY$2,0,IF(AT67<=$AY$3,1,IF(AT67<=$AY$4,2,3))) -> 3 | AV67: =IF(Y67<=$AY$7,3,IF(Y67<=$AY$8,2,IF(Y67<=$AY$9,1,0))) -> 3 | AZ67: =IF(Y67=0,3,0) -> 3 | BA67: =AS67+AU67+AZ67 -> 7 | BB67: =IFERROR(INDEX('Análisis general'!$E$4:$E$28,MATCH($B67,'Análisis general'!$B$4:$B$28,0)),"") -> 9.7 | BC67: =IF(BB67="","",IF(BB67<=$BG$2,0,IF(BB67<=$BG$3,1,IF(BB67<=$BG$4,2,3)))) -> 3 | BD67: =(AS67+AU67+AZ67+(BC67/2))*(9/10.5) -> 7.2857143 | BE67: =(AU67+AZ67+(BC67/2))*(9/7.5) -> 9
A68: 41807 | B68: Huila | C68: Sin clasificación oficial | D68: =AS68+AU68+AV68 -> 7 | E68: =BD68 -> 7.2857143 | F68: =BE68 -> 9 | G68: Timaná | H68: #N/D | I68: #N/D | J68: Timaná | K68: =IF($AQ68,"#N/D",IFERROR(INDEX(Olimpiadas!$A$2:$A$61,MATCH($AO68,Olimpiadas!$C$2:$C$61,0)),"#N/D")) -> INSTITUCIÓN EDUCATIVA CASCAJAL | L68: =IF($AQ68,"#N/D",IFERROR(INDEX(Minculturas!$A$2:$A$48,MATCH($AO68,Minculturas!$C$2:$C$48,0)),"#N/D")) -> #N/D | M68: =IF($AQ68,"#N/D",IFERROR(INDEX(Minculturas!$B$2:$B$48,MATCH($AO68,Minculturas!$C$2:$C$48,0)),"#N/D")) -> #N/D | N68: 2 | O68: 0 | P68: 0 | Q68: 0 | R68: 0 | S68: 1 | T68: 0 | U68: 0 | V68: 1 | W68: 0 | X68: 0 | Y68: 0 | Z68: 0 | AA68: 0 | AB68: 0 | AC68: 0 | AD68: 0 | AE68: 0 | AF68: 0 | AG68: =SUM(O68:X68) -> 2 | AJ68: 40.8 | AM68: Declarado afectado; sin lugar con nombre propio publicado en este registro. | AO68: =TRIM(SUBSTITUTE(SUBSTITUTE(SUBSTITUTE(SUBSTITUTE(SUBSTITUTE(SUBSTITUTE(SUBSTITUTE(SUBSTITUTE(SUBSTITUTE(LOWER(G68),"á","a"),"é","e"),"í","i"),"ó","o"),"ú","u"),"ñ","n"),"-"," "),","," "),"."," ")) -> timana | AP68: =TRIM(SUBSTITUTE(SUBSTITUTE(SUBSTITUTE(SUBSTITUTE(SUBSTITUTE(SUBSTITUTE(SUBSTITUTE(SUBSTITUTE(SUBSTITUTE(LOWER(B68),"á","a"),"é","e"),"í","i"),"ó","o"),"ú","u"),"ñ","n"),"-"," "),","," "),"."," ")) -> huila | AQ68: =COUNTIF($AO$2:$AO$433,AO68)>COUNTIFS($AO$2:$AO$433,AO68,$AP$2:$AP$433,AP68) -> FALSE | AR68: =IF(AQ68,AO68&"|"&AP68,AO68) -> timana | AS68: =(I68<>"#N/D")+(J68<>"#N/D")+(L68<>"#N/D") -> 1 | AT68: =SUM(O68:X68) -> 2 | AU68: =IF(AT68<=$AY$2,0,IF(AT68<=$AY$3,1,IF(AT68<=$AY$4,2,3))) -> 3 | AV68: =IF(Y68<=$AY$7,3,IF(Y68<=$AY$8,2,IF(Y68<=$AY$9,1,0))) -> 3 | AZ68: =IF(Y68=0,3,0) -> 3 | BA68: =AS68+AU68+AZ68 -> 7 | BB68: =IFERROR(INDEX('Análisis general'!$E$4:$E$28,MATCH($B68,'Análisis general'!$B$4:$B$28,0)),"") -> 9.7 | BC68: =IF(BB68="","",IF(BB68<=$BG$2,0,IF(BB68<=$BG$3,1,IF(BB68<=$BG$4,2,3)))) -> 3 | BD68: =(AS68+AU68+AZ68+(BC68/2))*(9/10.5) -> 7.2857143 | BE68: =(AU68+AZ68+(BC68/2))*(9/7.5) -> 9
A69: 76863 | B69: Valle del Cauca | C69: Sin clasificación oficial | D69: =AS69+AU69+AV69 -> 6 | E69: =BD69 -> 6.4285714 | F69: =BE69 -> 9 | G69: Versalles | H69: #N/D | I69: #N/D | J69: #N/D | K69: =IF($AQ69,"#N/D",IFERROR(INDEX(Olimpiadas!$A$2:$A$61,MATCH($AO69,Olimpiadas!$C$2:$C$61,0)),"#N/D")) -> #N/D | L69: =IF($AQ69,"#N/D",IFERROR(INDEX(Minculturas!$A$2:$A$48,MATCH($AO69,Minculturas!$C$2:$C$48,0)),"#N/D")) -> #N/D | M69: =IF($AQ69,"#N/D",IFERROR(INDEX(Minculturas!$B$2:$B$48,MATCH($AO69,Minculturas!$C$2:$C$48,0)),"#N/D")) -> #N/D | N69: 45 | O69: 0 | P69: 5 | Q69: 30 | R69: 1 | S69: 5 | T69: 1 | U69: 0 | V69: 2 | W69: 0 | X69: 1 | Y69: 0 | Z69: 0 | AA69: 0 | AB69: 0 | AC69: 0 | AD69: 0 | AE69: 0 | AF69: 0 | AG69: =SUM(O69:X69) -> 45 | AH69: 951 | AI69: 2158 | AJ69: 30.6 | AM69: Declarado afectado; sin lugar con nombre propio publicado en este registro. | AO69: =TRIM(SUBSTITUTE(SUBSTITUTE(SUBSTITUTE(SUBSTITUTE(SUBSTITUTE(SUBSTITUTE(SUBSTITUTE(SUBSTITUTE(SUBSTITUTE(LOWER(G69),"á","a"),"é","e"),"í","i"),"ó","o"),"ú","u"),"ñ","n"),"-"," "),","," "),"."," ")) -> versalles | AP69: =TRIM(SUBSTITUTE(SUBSTITUTE(SUBSTITUTE(SUBSTITUTE(SUBSTITUTE(SUBSTITUTE(SUBSTITUTE(SUBSTITUTE(SUBSTITUTE(LOWER(B69),"á","a"),"é","e"),"í","i"),"ó","o"),"ú","u"),"ñ","n"),"-"," "),","," "),"."," ")) -> valle del cauca | AQ69: =COUNTIF($AO$2:$AO$433,AO69)>COUNTIFS($AO$2:$AO$433,AO69,$AP$2:$AP$433,AP69) -> FALSE | AR69: =IF(AQ69,AO69&"|"&AP69,AO69) -> versalles | AS69: =(I69<>"#N/D")+(J69<>"#N/D")+(L69<>"#N/D") -> 0 | AT69: =SUM(O69:X69) -> 45 | AU69: =IF(AT69<=$AY$2,0,IF(AT69<=$AY$3,1,IF(AT69<=$AY$4,2,3))) -> 3 | AV69: =IF(Y69<=$AY$7,3,IF(Y69<=$AY$8,2,IF(Y69<=$AY$9,1,0))) -> 3 | AZ69: =IF(Y69=0,3,0) -> 3 | BA69: =AS69+AU69+AZ69 -> 6 | BB69: =IFERROR(INDEX('Análisis general'!$E$4:$E$28,MATCH($B69,'Análisis general'!$B$4:$B$28,0)),"") -> 4.9 | BC69: =IF(BB69="","",IF(BB69<=$BG$2,0,IF(BB69<=$BG$3,1,IF(BB69<=$BG$4,2,3)))) -> 3 | BD69: =(AS69+AU69+AZ69+(BC69/2))*(9/10.5) -> 6.4285714 | BE69: =(AU69+AZ69+(BC69/2))*(9/7.5) -> 9
A70: 76233 | B70: Valle del Cauca | C70: Sin clasificación oficial | D70: =AS70+AU70+AV70 -> 6 | E70: =BD70 -> 6.4285714 | F70: =BE70 -> 9 | G70: Dagua | H70: =IFERROR(IF($AQ70,INDEX(cpe!$C$2:$C$307,MATCH($AR70,cpe!$F$2:$F$307,0)),INDEX(cpe!$C$2:$C$307,MATCH($AR70,cpe!$D$2:$D$307,0))),"#N/D") -> #N/D | I70: =IFERROR(IF($AQ70,INDEX(cpe!$B$2:$B$307,MATCH($AR70,cpe!$F$2:$F$307,0)),INDEX(cpe!$B$2:$B$307,MATCH($AR70,cpe!$D$2:$D$307,0))),"#N/D") -> #N/D | J70: =IF($AQ70,"#N/D",IFERROR(INDEX(Olimpiadas!$B$2:$B$61,MATCH($AO70,Olimpiadas!$C$2:$C$61,0)),"#N/D")) -> #N/D | K70: =IF($AQ70,"#N/D",IFERROR(INDEX(Olimpiadas!$A$2:$A$61,MATCH($AO70,Olimpiadas!$C$2:$C$61,0)),"#N/D")) -> #N/D | L70: =IF($AQ70,"#N/D",IFERROR(INDEX(Minculturas!$A$2:$A$48,MATCH($AO70,Minculturas!$C$2:$C$48,0)),"#N/D")) -> #N/D | M70: =IF($AQ70,"#N/D",IFERROR(INDEX(Minculturas!$B$2:$B$48,MATCH($AO70,Minculturas!$C$2:$C$48,0)),"#N/D")) -> #N/D | N70: 12 | O70: 0 | P70: 1 | Q70: 1 | R70: 1 | S70: 1 | T70: 1 | U70: 0 | V70: 4 | W70: 3 | X70: 0 | Y70: 0 | Z70: 0 | AA70: 0 | AB70: 0 | AC70: 0 | AD70: 0 | AE70: 0 | AF70: 0 | AG70: =SUM(O70:X70) -> 12 | AJ70: 28.4 | AM70: Declarado afectado; sin lugar con nombre propio publicado en este registro. | AO70: =TRIM(SUBSTITUTE(SUBSTITUTE(SUBSTITUTE(SUBSTITUTE(SUBSTITUTE(SUBSTITUTE(SUBSTITUTE(SUBSTITUTE(SUBSTITUTE(LOWER(G70),"á","a"),"é","e"),"í","i"),"ó","o"),"ú","u"),"ñ","n"),"-"," "),","," "),"."," ")) -> dagua | AP70: =TRIM(SUBSTITUTE(SUBSTITUTE(SUBSTITUTE(SUBSTITUTE(SUBSTITUTE(SUBSTITUTE(SUBSTITUTE(SUBSTITUTE(SUBSTITUTE(LOWER(B70),"á","a"),"é","e"),"í","i"),"ó","o"),"ú","u"),"ñ","n"),"-"," "),","," "),"."," ")) -> valle del cauca | AQ70: =COUNTIF($AO$2:$AO$433,AO70)>COUNTIFS($AO$2:$AO$433,AO70,$AP$2:$AP$433,AP70) -> FALSE | AR70: =IF(AQ70,AO70&"|"&AP70,AO70) -> dagua | AS70: =(I70<>"#N/D")+(J70<>"#N/D")+(L70<>"#N/D") -> 0 | AT70: =SUM(O70:X70) -> 12 | AU70: =IF(AT70<=$AY$2,0,IF(AT70<=$AY$3,1,IF(AT70<=$AY$4,2,3))) -> 3 | AV70: =IF(Y70<=$AY$7,3,IF(Y70<=$AY$8,2,IF(Y70<=$AY$9,1,0))) -> 3 | AZ70: =IF(Y70=0,3,0) -> 3 | BA70: =AS70+AU70+AZ70 -> 6 | BB70: =IFERROR(INDEX('Análisis general'!$E$4:$E$28,MATCH($B70,'Análisis general'!$B$4:$B$28,0)),"") -> 4.9 | BC70: =IF(BB70="","",IF(BB70<=$BG$2,0,IF(BB70<=$BG$3,1,IF(BB70<=$BG$4,2,3)))) -> 3 | BD70: =(AS70+AU70+AZ70+(BC70/2))*(9/10.5) -> 6.4285714 | BE70: =(AU70+AZ70+(BC70/2))*(9/7.5) -> 9
A71: 76895 | B71: Valle del Cauca | C71: Afectación muy alta | D71: =AS71+AU71+AV71 -> 6 | E71: =BD71 -> 6.4285714 | F71: =BE71 -> 9 | G71: Zarzal | H71: #N/D | I71: #N/D | J71: #N/D | K71: =IF($AQ71,"#N/D",IFERROR(INDEX(Olimpiadas!$A$2:$A$61,MATCH($AO71,Olimpiadas!$C$2:$C$61,0)),"#N/D")) -> #N/D | L71: =IF($AQ71,"#N/D",IFERROR(INDEX(Minculturas!$A$2:$A$48,MATCH($AO71,Minculturas!$C$2:$C$48,0)),"#N/D")) -> #N/D | M71: =IF($AQ71,"#N/D",IFERROR(INDEX(Minculturas!$B$2:$B$48,MATCH($AO71,Minculturas!$C$2:$C$48,0)),"#N/D")) -> #N/D | N71: 11 | O71: 0 | P71: 2 | Q71: 4 | R71: 1 | S71: 0 | T71: 0 | U71: 1 | V71: 0 | W71: 0 | X71: 0 | Y71: 0 | Z71: 1 | AA71: 0 | AB71: 1 | AC71: 1 | AD71: 0 | AE71: 0 | AF71: 0 | AG71: =SUM(O71:X71) -> 8 | AH71: 1006 | AI71: 2255 | AJ71: 17.2 | AM71: Fallecidos, numerosos heridos y hospital municipal colapsado/saturado. | AO71: =TRIM(SUBSTITUTE(SUBSTITUTE(SUBSTITUTE(SUBSTITUTE(SUBSTITUTE(SUBSTITUTE(SUBSTITUTE(SUBSTITUTE(SUBSTITUTE(LOWER(G71),"á","a"),"é","e"),"í","i"),"ó","o"),"ú","u"),"ñ","n"),"-"," "),","," "),"."," ")) -> zarzal | AP71: =TRIM(SUBSTITUTE(SUBSTITUTE(SUBSTITUTE(SUBSTITUTE(SUBSTITUTE(SUBSTITUTE(SUBSTITUTE(SUBSTITUTE(SUBSTITUTE(LOWER(B71),"á","a"),"é","e"),"í","i"),"ó","o"),"ú","u"),"ñ","n"),"-"," "),","," "),"."," ")) -> valle del cauca | AQ71: =COUNTIF($AO$2:$AO$433,AO71)>COUNTIFS($AO$2:$AO$433,AO71,$AP$2:$AP$433,AP71) -> FALSE | AR71: =IF(AQ71,AO71&"|"&AP71,AO71) -> zarzal | AS71: =(I71<>"#N/D")+(J71<>"#N/D")+(L71<>"#N/D") -> 0 | AT71: =SUM(O71:X71) -> 8 | AU71: =IF(AT71<=$AY$2,0,IF(AT71<=$AY$3,1,IF(AT71<=$AY$4,2,3))) -> 3 | AV71: =IF(Y71<=$AY$7,3,IF(Y71<=$AY$8,2,IF(Y71<=$AY$9,1,0))) -> 3 | AZ71: =IF(Y71=0,3,0) -> 3 | BA71: =AS71+AU71+AZ71 -> 6 | BB71: =IFERROR(INDEX('Análisis general'!$E$4:$E$28,MATCH($B71,'Análisis general'!$B$4:$B$28,0)),"") -> 4.9 | BC71: =IF(BB71="","",IF(BB71<=$BG$2,0,IF(BB71<=$BG$3,1,IF(BB71<=$BG$4,2,3)))) -> 3 | BD71: =(AS71+AU71+AZ71+(BC71/2))*(9/10.5) -> 6.4285714 | BE71: =(AU71+AZ71+(BC71/2))*(9/7.5) -> 9
A72: 25286 | B72: Cundinamarca | C72: Afectación media | D72: =AS72+AU72+AV72 -> 6 | E72: =BD72 -> 6.4285714 | F72: =BE72 -> 9 | G72: Funza | H72: =IFERROR(IF($AQ72,INDEX(cpe!$C$2:$C$307,MATCH($AR72,cpe!$F$2:$F$307,0)),INDEX(cpe!$C$2:$C$307,MATCH($AR72,cpe!$D$2:$D$307,0))),"#N/D") -> #N/D | I72: =IFERROR(IF($AQ72,INDEX(cpe!$B$2:$B$307,MATCH($AR72,cpe!$F$2:$F$307,0)),INDEX(cpe!$B$2:$B$307,MATCH($AR72,cpe!$D$2:$D$307,0))),"#N/D") -> #N/D | J72: =IF($AQ72,"#N/D",IFERROR(INDEX(Olimpiadas!$B$2:$B$61,MATCH($AO72,Olimpiadas!$C$2:$C$61,0)),"#N/D")) -> #N/D | K72: =IF($AQ72,"#N/D",IFERROR(INDEX(Olimpiadas!$A$2:$A$61,MATCH($AO72,Olimpiadas!$C$2:$C$61,0)),"#N/D")) -> #N/D | L72: =IF($AQ72,"#N/D",IFERROR(INDEX(Minculturas!$A$2:$A$48,MATCH($AO72,Minculturas!$C$2:$C$48,0)),"#N/D")) -> #N/D | M72: =IF($AQ72,"#N/D",IFERROR(INDEX(Minculturas!$B$2:$B$48,MATCH($AO72,Minculturas!$C$2:$C$48,0)),"#N/D")) -> #N/D | N72: 6 | O72: 0 | P72: 4 | Q72: 0 | R72: 0 | S72: 0 | T72: 0 | U72: 2 | V72: 0 | W72: 0 | X72: 0 | Y72: 0 | Z72: 0 | AA72: 0 | AB72: 0 | AC72: 0 | AD72: 0 | AE72: 0 | AF72: 0 | AG72: =SUM(O72:X72) -> 6 | AJ72: 7.8 | AM72: Incidentes en bodegas con sustancias químicas y fuga de gas controlada. | AO72: =TRIM(SUBSTITUTE(SUBSTITUTE(SUBSTITUTE(SUBSTITUTE(SUBSTITUTE(SUBSTITUTE(SUBSTITUTE(SUBSTITUTE(SUBSTITUTE(LOWER(G72),"á","a"),"é","e"),"í","i"),"ó","o"),"ú","u"),"ñ","n"),"-"," "),","," "),"."," ")) -> funza | AP72: =TRIM(SUBSTITUTE(SUBSTITUTE(SUBSTITUTE(SUBSTITUTE(SUBSTITUTE(SUBSTITUTE(SUBSTITUTE(SUBSTITUTE(SUBSTITUTE(LOWER(B72),"á","a"),"é","e"),"í","i"),"ó","o"),"ú","u"),"ñ","n"),"-"," "),","," "),"."," ")) -> cundinamarca | AQ72: =COUNTIF($AO$2:$AO$433,AO72)>COUNTIFS($AO$2:$AO$433,AO72,$AP$2:$AP$433,AP72) -> FALSE | AR72: =IF(AQ72,AO72&"|"&AP72,AO72) -> funza | AS72: =(I72<>"#N/D")+(J72<>"#N/D")+(L72<>"#N/D") -> 0 | AT72: =SUM(O72:X72) -> 6 | AU72: =IF(AT72<=$AY$2,0,IF(AT72<=$AY$3,1,IF(AT72<=$AY$4,2,3))) -> 3 | AV72: =IF(Y72<=$AY$7,3,IF(Y72<=$AY$8,2,IF(Y72<=$AY$9,1,0))) -> 3 | AZ72: =IF(Y72=0,3,0) -> 3 | BA72: =AS72+AU72+AZ72 -> 6 | BB72: =IFERROR(INDEX('Análisis general'!$E$4:$E$28,MATCH($B72,'Análisis general'!$B$4:$B$28,0)),"") -> 4.1 | BC72: =IF(BB72="","",IF(BB72<=$BG$2,0,IF(BB72<=$BG$3,1,IF(BB72<=$BG$4,2,3)))) -> 3 | BD72: =(AS72+AU72+AZ72+(BC72/2))*(9/10.5) -> 6.4285714 | BE72: =(AU72+AZ72+(BC72/2))*(9/7.5) -> 9
A73: 76020 | B73: Valle del Cauca | C73: Sin clasificación oficial | D73: =AS73+AU73+AV73 -> 6 | E73: =BD73 -> 6.4285714 | F73: =BE73 -> 9 | G73: Alcalá | H73: =IFERROR(IF($AQ73,INDEX(cpe!$C$2:$C$307,MATCH($AR73,cpe!$F$2:$F$307,0)),INDEX(cpe!$C$2:$C$307,MATCH($AR73,cpe!$D$2:$D$307,0))),"#N/D") -> #N/D | I73: =IFERROR(IF($AQ73,INDEX(cpe!$B$2:$B$307,MATCH($AR73,cpe!$F$2:$F$307,0)),INDEX(cpe!$B$2:$B$307,MATCH($AR73,cpe!$D$2:$D$307,0))),"#N/D") -> #N/D | J73: =IF($AQ73,"#N/D",IFERROR(INDEX(Olimpiadas!$B$2:$B$61,MATCH($AO73,Olimpiadas!$C$2:$C$61,0)),"#N/D")) -> #N/D | K73: =IF($AQ73,"#N/D",IFERROR(INDEX(Olimpiadas!$A$2:$A$61,MATCH($AO73,Olimpiadas!$C$2:$C$61,0)),"#N/D")) -> #N/D | L73: =IF($AQ73,"#N/D",IFERROR(INDEX(Minculturas!$A$2:$A$48,MATCH($AO73,Minculturas!$C$2:$C$48,0)),"#N/D")) -> #N/D | M73: =IF($AQ73,"#N/D",IFERROR(INDEX(Minculturas!$B$2:$B$48,MATCH($AO73,Minculturas!$C$2:$C$48,0)),"#N/D")) -> #N/D | N73: 6 | O73: 0 | P73: 1 | Q73: 0 | R73: 1 | S73: 0 | T73: 1 | U73: 1 | V73: 1 | W73: 0 | X73: 1 | Y73: 0 | Z73: 0 | AA73: 0 | AB73: 0 | AC73: 0 | AD73: 0 | AE73: 0 | AF73: 0 | AG73: =SUM(O73:X73) -> 6 | AH73: 361 | AI73: 649 | AJ73: 31.9 | AM73: Declarado afectado; sin lugar con nombre propio publicado en este registro. | AO73: =TRIM(SUBSTITUTE(SUBSTITUTE(SUBSTITUTE(SUBSTITUTE(SUBSTITUTE(SUBSTITUTE(SUBSTITUTE(SUBSTITUTE(SUBSTITUTE(LOWER(G73),"á","a"),"é","e"),"í","i"),"ó","o"),"ú","u"),"ñ","n"),"-"," "),","," "),"."," ")) -> alcala | AP73: =TRIM(SUBSTITUTE(SUBSTITUTE(SUBSTITUTE(SUBSTITUTE(SUBSTITUTE(SUBSTITUTE(SUBSTITUTE(SUBSTITUTE(SUBSTITUTE(LOWER(B73),"á","a"),"é","e"),"í","i"),"ó","o"),"ú","u"),"ñ","n"),"-"," "),","," "),"."," ")) -> valle del cauca | AQ73: =COUNTIF($AO$2:$AO$433,AO73)>COUNTIFS($AO$2:$AO$433,AO73,$AP$2:$AP$433,AP73) -> FALSE | AR73: =IF(AQ73,AO73&"|"&AP73,AO73) -> alcala | AS73: =(I73<>"#N/D")+(J73<>"#N/D")+(L73<>"#N/D") -> 0 | AT73: =SUM(O73:X73) -> 6 | AU73: =IF(AT73<=$AY$2,0,IF(AT73<=$AY$3,1,IF(AT73<=$AY$4,2,3))) -> 3 | AV73: =IF(Y73<=$AY$7,3,IF(Y73<=$AY$8,2,IF(Y73<=$AY$9,1,0))) -> 3 | AZ73: =IF(Y73=0,3,0) -> 3 | BA73: =AS73+AU73+AZ73 -> 6 | BB73: =IFERROR(INDEX('Análisis general'!$E$4:$E$28,MATCH($B73,'Análisis general'!$B$4:$B$28,0)),"") -> 4.9 | BC73: =IF(BB73="","",IF(BB73<=$BG$2,0,IF(BB73<=$BG$3,1,IF(BB73<=$BG$4,2,3)))) -> 3 | BD73: =(AS73+AU73+AZ73+(BC73/2))*(9/10.5) -> 6.4285714 | BE73: =(AU73+AZ73+(BC73/2))*(9/7.5) -> 9
A74: 76036 | B74: Valle del Cauca | C74: Sin clasificación oficial | D74: =AS74+AU74+AV74 -> 6 | E74: =BD74 -> 6.4285714 | F74: =BE74 -> 9 | G74: Andalucía | H74: =IFERROR(IF($AQ74,INDEX(cpe!$C$2:$C$307,MATCH($AR74,cpe!$F$2:$F$307,0)),INDEX(cpe!$C$2:$C$307,MATCH($AR74,cpe!$D$2:$D$307,0))),"#N/D") -> #N/D | I74: =IFERROR(IF($AQ74,INDEX(cpe!$B$2:$B$307,MATCH($AR74,cpe!$F$2:$F$307,0)),INDEX(cpe!$B$2:$B$307,MATCH($AR74,cpe!$D$2:$D$307,0))),"#N/D") -> #N/D | J74: =IF($AQ74,"#N/D",IFERROR(INDEX(Olimpiadas!$B$2:$B$61,MATCH($AO74,Olimpiadas!$C$2:$C$61,0)),"#N/D")) -> #N/D | K74: =IF($AQ74,"#N/D",IFERROR(INDEX(Olimpiadas!$A$2:$A$61,MATCH($AO74,Olimpiadas!$C$2:$C$61,0)),"#N/D")) -> #N/D | L74: =IF($AQ74,"#N/D",IFERROR(INDEX(Minculturas!$A$2:$A$48,MATCH($AO74,Minculturas!$C$2:$C$48,0)),"#N/D")) -> #N/D | M74: =IF($AQ74,"#N/D",IFERROR(INDEX(Minculturas!$B$2:$B$48,MATCH($AO74,Minculturas!$C$2:$C$48,0)),"#N/D")) -> #N/D | N74: 5 | O74: 0 | P74: 2 | Q74: 0 | R74: 1 | S74: 1 | T74: 1 | U74: 0 | V74: 0 | W74: 0 | X74: 0 | Y74: 0 | Z74: 0 | AA74: 0 | AB74: 0 | AC74: 0 | AD74: 0 | AE74: 0 | AF74: 0 | AG74: =SUM(O74:X74) -> 5 | AH74: 387 | AI74: 905 | AJ74: 15.3 | AM74: Declarado afectado; sin lugar con nombre propio publicado en este registro. | AO74: =TRIM(SUBSTITUTE(SUBSTITUTE(SUBSTITUTE(SUBSTITUTE(SUBSTITUTE(SUBSTITUTE(SUBSTITUTE(SUBSTITUTE(SUBSTITUTE(LOWER(G74),"á","a"),"é","e"),"í","i"),"ó","o"),"ú","u"),"ñ","n"),"-"," "),","," "),"."," ")) -> andalucia | AP74: =TRIM(SUBSTITUTE(SUBSTITUTE(SUBSTITUTE(SUBSTITUTE(SUBSTITUTE(SUBSTITUTE(SUBSTITUTE(SUBSTITUTE(SUBSTITUTE(LOWER(B74),"á","a"),"é","e"),"í","i"),"ó","o"),"ú","u"),"ñ","n"),"-"," "),","," "),"."," ")) -> valle del cauca | AQ74: =COUNTIF($AO$2:$AO$433,AO74)>COUNTIFS($AO$2:$AO$433,AO74,$AP$2:$AP$433,AP74) -> FALSE | AR74: =IF(AQ74,AO74&"|"&AP74,AO74) -> andalucia | AS74: =(I74<>"#N/D")+(J74<>"#N/D")+(L74<>"#N/D") -> 0 | AT74: =SUM(O74:X74) -> 5 | AU74: =IF(AT74<=$AY$2,0,IF(AT74<=$AY$3,1,IF(AT74<=$AY$4,2,3))) -> 3 | AV74: =IF(Y74<=$AY$7,3,IF(Y74<=$AY$8,2,IF(Y74<=$AY$9,1,0))) -> 3 | AZ74: =IF(Y74=0,3,0) -> 3 | BA74: =AS74+AU74+AZ74 -> 6 | BB74: =IFERROR(INDEX('Análisis general'!$E$4:$E$28,MATCH($B74,'Análisis general'!$B$4:$B$28,0)),"") -> 4.9 | BC74: =IF(BB74="","",IF(BB74<=$BG$2,0,IF(BB74<=$BG$3,1,IF(BB74<=$BG$4,2,3)))) -> 3 | BD74: =(AS74+AU74+AZ74+(BC74/2))*(9/10.5) -> 6.4285714 | BE74: =(AU74+AZ74+(BC74/2))*(9/7.5) -> 9
A75: 76890 | B75: Valle del Cauca | C75: Sin clasificación oficial | D75: =AS75+AU75+AV75 -> 6 | E75: =BD75 -> 6.4285714 | F75: =BE75 -> 9 | G75: Yotoco | H75: #N/D | I75: #N/D | J75: #N/D | K75: =IF($AQ75,"#N/D",IFERROR(INDEX(Olimpiadas!$A$2:$A$61,MATCH($AO75,Olimpiadas!$C$2:$C$61,0)),"#N/D")) -> #N/D | L75: =IF($AQ75,"#N/D",IFERROR(INDEX(Minculturas!$A$2:$A$48,MATCH($AO75,Minculturas!$C$2:$C$48,0)),"#N/D")) -> #N/D | M75: =IF($AQ75,"#N/D",IFERROR(INDEX(Minculturas!$B$2:$B$48,MATCH($AO75,Minculturas!$C$2:$C$48,0)),"#N/D")) -> #N/D | N75: 5 | O75: 0 | P75: 1 | Q75: 2 | R75: 0 | S75: 0 | T75: 0 | U75: 1 | V75: 0 | W75: 0 | X75: 1 | Y75: 0 | Z75: 0 | AA75: 0 | AB75: 0 | AC75: 0 | AD75: 0 | AE75: 0 | AF75: 0 | AG75: =SUM(O75:X75) -> 5 | AH75: 770 | AI75: 1970 | AJ75: 20.8 | AM75: Declarado afectado en el reparto municipal del EDAN de viviendas de la UNGRD (capa 3iS/iMMAP para OCHA, 12-08-2026). Sin ningún lugar con nombre propio publicado. | AO75: =TRIM(SUBSTITUTE(SUBSTITUTE(SUBSTITUTE(SUBSTITUTE(SUBSTITUTE(SUBSTITUTE(SUBSTITUTE(SUBSTITUTE(SUBSTITUTE(LOWER(G75),"á","a"),"é","e"),"í","i"),"ó","o"),"ú","u"),"ñ","n"),"-"," "),","," "),"."," ")) -> yotoco | AP75: =TRIM(SUBSTITUTE(SUBSTITUTE(SUBSTITUTE(SUBSTITUTE(SUBSTITUTE(SUBSTITUTE(SUBSTITUTE(SUBSTITUTE(SUBSTITUTE(LOWER(B75),"á","a"),"é","e"),"í","i"),"ó","o"),"ú","u"),"ñ","n"),"-"," "),","," "),"."," ")) -> valle del cauca | AQ75: =COUNTIF($AO$2:$AO$433,AO75)>COUNTIFS($AO$2:$AO$433,AO75,$AP$2:$AP$433,AP75) -> FALSE | AR75: =IF(AQ75,AO75&"|"&AP75,AO75) -> yotoco | AS75: =(I75<>"#N/D")+(J75<>"#N/D")+(L75<>"#N/D") -> 0 | AT75: =SUM(O75:X75) -> 5 | AU75: =IF(AT75<=$AY$2,0,IF(AT75<=$AY$3,1,IF(AT75<=$AY$4,2,3))) -> 3 | AV75: =IF(Y75<=$AY$7,3,IF(Y75<=$AY$8,2,IF(Y75<=$AY$9,1,0))) -> 3 | AZ75: =IF(Y75=0,3,0) -> 3 | BA75: =AS75+AU75+AZ75 -> 6 | BB75: =IFERROR(INDEX('Análisis general'!$E$4:$E$28,MATCH($B75,'Análisis general'!$B$4:$B$28,0)),"") -> 4.9 | BC75: =IF(BB75="","",IF(BB75<=$BG$2,0,IF(BB75<=$BG$3,1,IF(BB75<=$BG$4,2,3)))) -> 3 | BD75: =(AS75+AU75+AZ75+(BC75/2))*(9/10.5) -> 6.4285714 | BE75: =(AU75+AZ75+(BC75/2))*(9/7.5) -> 9
A76: 41244 | B76: Huila | C76: Sin clasificación oficial | D76: =AS76+AU76+AV76 -> 6 | E76: =BD76 -> 6.4285714 | F76: =BE76 -> 9 | G76: Elías | H76: =IFERROR(IF($AQ76,INDEX(cpe!$C$2:$C$307,MATCH($AR76,cpe!$F$2:$F$307,0)),INDEX(cpe!$C$2:$C$307,MATCH($AR76,cpe!$D$2:$D$307,0))),"#N/D") -> #N/D | I76: =IFERROR(IF($AQ76,INDEX(cpe!$B$2:$B$307,MATCH($AR76,cpe!$F$2:$F$307,0)),INDEX(cpe!$B$2:$B$307,MATCH($AR76,cpe!$D$2:$D$307,0))),"#N/D") -> #N/D | J76: =IF($AQ76,"#N/D",IFERROR(INDEX(Olimpiadas!$B$2:$B$61,MATCH($AO76,Olimpiadas!$C$2:$C$61,0)),"#N/D")) -> #N/D | K76: =IF($AQ76,"#N/D",IFERROR(INDEX(Olimpiadas!$A$2:$A$61,MATCH($AO76,Olimpiadas!$C$2:$C$61,0)),"#N/D")) -> #N/D | L76: =IF($AQ76,"#N/D",IFERROR(INDEX(Minculturas!$A$2:$A$48,MATCH($AO76,Minculturas!$C$2:$C$48,0)),"#N/D")) -> #N/D | M76: =IF($AQ76,"#N/D",IFERROR(INDEX(Minculturas!$B$2:$B$48,MATCH($AO76,Minculturas!$C$2:$C$48,0)),"#N/D")) -> #N/D | N76: 4 | O76: 0 | P76: 0 | Q76: 0 | R76: 0 | S76: 3 | T76: 1 | U76: 0 | V76: 0 | W76: 0 | X76: 0 | Y76: 0 | Z76: 0 | AA76: 0 | AB76: 0 | AC76: 0 | AD76: 0 | AE76: 0 | AF76: 0 | AG76: =SUM(O76:X76) -> 4 | AH76: 1 | AI76: 1 | AJ76: 32.3 | AM76: Declarado afectado; sin lugar con nombre propio publicado en este registro. | AO76: =TRIM(SUBSTITUTE(SUBSTITUTE(SUBSTITUTE(SUBSTITUTE(SUBSTITUTE(SUBSTITUTE(SUBSTITUTE(SUBSTITUTE(SUBSTITUTE(LOWER(G76),"á","a"),"é","e"),"í","i"),"ó","o"),"ú","u"),"ñ","n"),"-"," "),","," "),"."," ")) -> elias | AP76: =TRIM(SUBSTITUTE(SUBSTITUTE(SUBSTITUTE(SUBSTITUTE(SUBSTITUTE(SUBSTITUTE(SUBSTITUTE(SUBSTITUTE(SUBSTITUTE(LOWER(B76),"á","a"),"é","e"),"í","i"),"ó","o"),"ú","u"),"ñ","n"),"-"," "),","," "),"."," ")) -> huila | AQ76: =COUNTIF($AO$2:$AO$433,AO76)>COUNTIFS($AO$2:$AO$433,AO76,$AP$2:$AP$433,AP76) -> FALSE | AR76: =IF(AQ76,AO76&"|"&AP76,AO76) -> elias | AS76: =(I76<>"#N/D")+(J76<>"#N/D")+(L76<>"#N/D") -> 0 | AT76: =SUM(O76:X76) -> 4 | AU76: =IF(AT76<=$AY$2,0,IF(AT76<=$AY$3,1,IF(AT76<=$AY$4,2,3))) -> 3 | AV76: =IF(Y76<=$AY$7,3,IF(Y76<=$AY$8,2,IF(Y76<=$AY$9,1,0))) -> 3 | AZ76: =IF(Y76=0,3,0) -> 3 | BA76: =AS76+AU76+AZ76 -> 6 | BB76: =IFERROR(INDEX('Análisis general'!$E$4:$E$28,MATCH($B76,'Análisis general'!$B$4:$B$28,0)),"") -> 9.7 | BC76: =IF(BB76="","",IF(BB76<=$BG$2,0,IF(BB76<=$BG$3,1,IF(BB76<=$BG$4,2,3)))) -> 3 | BD76: =(AS76+AU76+AZ76+(BC76/2))*(9/10.5) -> 6.4285714 | BE76: =(AU76+AZ76+(BC76/2))*(9/7.5) -> 9
A77: 41872 | B77: Huila | C77: Sin clasificación oficial | D77: =AS77+AU77+AV77 -> 6 | E77: =BD77 -> 6.4285714 | F77: =BE77 -> 9 | G77: Villavieja | H77: #N/D | I77: #N/D | J77: #N/D | K77: =IF($AQ77,"#N/D",IFERROR(INDEX(Olimpiadas!$A$2:$A$61,MATCH($AO77,Olimpiadas!$C$2:$C$61,0)),"#N/D")) -> #N/D | L77: =IF($AQ77,"#N/D",IFERROR(INDEX(Minculturas!$A$2:$A$48,MATCH($AO77,Minculturas!$C$2:$C$48,0)),"#N/D")) -> #N/D | M77: =IF($AQ77,"#N/D",IFERROR(INDEX(Minculturas!$B$2:$B$48,MATCH($AO77,Minculturas!$C$2:$C$48,0)),"#N/D")) -> #N/D | N77: 4 | O77: 0 | P77: 1 | Q77: 0 | R77: 0 | S77: 2 | T77: 1 | U77: 0 | V77: 0 | W77: 0 | X77: 0 | Y77: 0 | Z77: 0 | AA77: 0 | AB77: 0 | AC77: 0 | AD77: 0 | AE77: 0 | AF77: 0 | AG77: =SUM(O77:X77) -> 4 | AJ77: 37.9 | AM77: Declarado afectado; sin lugar con nombre propio publicado en este registro. | AO77: =TRIM(SUBSTITUTE(SUBSTITUTE(SUBSTITUTE(SUBSTITUTE(SUBSTITUTE(SUBSTITUTE(SUBSTITUTE(SUBSTITUTE(SUBSTITUTE(LOWER(G77),"á","a"),"é","e"),"í","i"),"ó","o"),"ú","u"),"ñ","n"),"-"," "),","," "),"."," ")) -> villavieja | AP77: =TRIM(SUBSTITUTE(SUBSTITUTE(SUBSTITUTE(SUBSTITUTE(SUBSTITUTE(SUBSTITUTE(SUBSTITUTE(SUBSTITUTE(SUBSTITUTE(LOWER(B77),"á","a"),"é","e"),"í","i"),"ó","o"),"ú","u"),"ñ","n"),"-"," "),","," "),"."," ")) -> huila | AQ77: =COUNTIF($AO$2:$AO$433,AO77)>COUNTIFS($AO$2:$AO$433,AO77,$AP$2:$AP$433,AP77) -> FALSE | AR77: =IF(AQ77,AO77&"|"&AP77,AO77) -> villavieja | AS77: =(I77<>"#N/D")+(J77<>"#N/D")+(L77<>"#N/D") -> 0 | AT77: =SUM(O77:X77) -> 4 | AU77: =IF(AT77<=$AY$2,0,IF(AT77<=$AY$3,1,IF(AT77<=$AY$4,2,3))) -> 3 | AV77: =IF(Y77<=$AY$7,3,IF(Y77<=$AY$8,2,IF(Y77<=$AY$9,1,0))) -> 3 | AZ77: =IF(Y77=0,3,0) -> 3 | BA77: =AS77+AU77+AZ77 -> 6 | BB77: =IFERROR(INDEX('Análisis general'!$E$4:$E$28,MATCH($B77,'Análisis general'!$B$4:$B$28,0)),"") -> 9.7 | BC77: =IF(BB77="","",IF(BB77<=$BG$2,0,IF(BB77<=$BG$3,1,IF(BB77<=$BG$4,2,3)))) -> 3 | BD77: =(AS77+AU77+AZ77+(BC77/2))*(9/10.5) -> 6.4285714 | BE77: =(AU77+AZ77+(BC77/2))*(9/7.5) -> 9
A78: 41132 | B78: Huila | C78: Sin clasificación oficial | D78: =AS78+AU78+AV78 -> 6 | E78: =BD78 -> 6.4285714 | F78: =BE78 -> 9 | G78: Campoalegre | H78: =IFERROR(IF($AQ78,INDEX(cpe!$C$2:$C$307,MATCH($AR78,cpe!$F$2:$F$307,0)),INDEX(cpe!$C$2:$C$307,MATCH($AR78,cpe!$D$2:$D$307,0))),"#N/D") -> #N/D | I78: =IFERROR(IF($AQ78,INDEX(cpe!$B$2:$B$307,MATCH($AR78,cpe!$F$2:$F$307,0)),INDEX(cpe!$B$2:$B$307,MATCH($AR78,cpe!$D$2:$D$307,0))),"#N/D") -> #N/D | J78: =IF($AQ78,"#N/D",IFERROR(INDEX(Olimpiadas!$B$2:$B$61,MATCH($AO78,Olimpiadas!$C$2:$C$61,0)),"#N/D")) -> #N/D | K78: =IF($AQ78,"#N/D",IFERROR(INDEX(Olimpiadas!$A$2:$A$61,MATCH($AO78,Olimpiadas!$C$2:$C$61,0)),"#N/D")) -> #N/D | L78: =IF($AQ78,"#N/D",IFERROR(INDEX(Minculturas!$A$2:$A$48,MATCH($AO78,Minculturas!$C$2:$C$48,0)),"#N/D")) -> #N/D | M78: =IF($AQ78,"#N/D",IFERROR(INDEX(Minculturas!$B$2:$B$48,MATCH($AO78,Minculturas!$C$2:$C$48,0)),"#N/D")) -> #N/D | N78: 3 | O78: 0 | P78: 1 | Q78: 0 | R78: 0 | S78: 2 | T78: 0 | U78: 0 | V78: 0 | W78: 0 | X78: 0 | Y78: 0 | Z78: 0 | AA78: 0 | AB78: 0 | AC78: 0 | AD78: 0 | AE78: 0 | AF78: 0 | AG78: =SUM(O78:X78) -> 3 | AJ78: 31.1 | AM78: Declarado afectado; sin lugar con nombre propio publicado en este registro. | AO78: =TRIM(SUBSTITUTE(SUBSTITUTE(SUBSTITUTE(SUBSTITUTE(SUBSTITUTE(SUBSTITUTE(SUBSTITUTE(SUBSTITUTE(SUBSTITUTE(LOWER(G78),"á","a"),"é","e"),"í","i"),"ó","o"),"ú","u"),"ñ","n"),"-"," "),","," "),"."," ")) -> campoalegre | AP78: =TRIM(SUBSTITUTE(SUBSTITUTE(SUBSTITUTE(SUBSTITUTE(SUBSTITUTE(SUBSTITUTE(SUBSTITUTE(SUBSTITUTE(SUBSTITUTE(LOWER(B78),"á","a"),"é","e"),"í","i"),"ó","o"),"ú","u"),"ñ","n"),"-"," "),","," "),"."," ")) -> huila | AQ78: =COUNTIF($AO$2:$AO$433,AO78)>COUNTIFS($AO$2:$AO$433,AO78,$AP$2:$AP$433,AP78) -> FALSE | AR78: =IF(AQ78,AO78&"|"&AP78,AO78) -> campoalegre | AS78: =(I78<>"#N/D")+(J78<>"#N/D")+(L78<>"#N/D") -> 0 | AT78: =SUM(O78:X78) -> 3 | AU78: =IF(AT78<=$AY$2,0,IF(AT78<=$AY$3,1,IF(AT78<=$AY$4,2,3))) -> 3 | AV78: =IF(Y78<=$AY$7,3,IF(Y78<=$AY$8,2,IF(Y78<=$AY$9,1,0))) -> 3 | AZ78: =IF(Y78=0,3,0) -> 3 | BA78: =AS78+AU78+AZ78 -> 6 | BB78: =IFERROR(INDEX('Análisis general'!$E$4:$E$28,MATCH($B78,'Análisis general'!$B$4:$B$28,0)),"") -> 9.7 | BC78: =IF(BB78="","",IF(BB78<=$BG$2,0,IF(BB78<=$BG$3,1,IF(BB78<=$BG$4,2,3)))) -> 3 | BD78: =(AS78+AU78+AZ78+(BC78/2))*(9/10.5) -> 6.4285714 | BE78: =(AU78+AZ78+(BC78/2))*(9/7.5) -> 9
A79: 73168 | B79: Tolima | C79: Sin clasificación oficial | D79: =AS79+AU79+AV79 -> 6 | E79: =BD79 -> 6.4285714 | F79: =BE79 -> 9 | G79: Chaparral | H79: =IFERROR(IF($AQ79,INDEX(cpe!$C$2:$C$307,MATCH($AR79,cpe!$F$2:$F$307,0)),INDEX(cpe!$C$2:$C$307,MATCH($AR79,cpe!$D$2:$D$307,0))),"#N/D") -> #N/D | I79: =IFERROR(IF($AQ79,INDEX(cpe!$B$2:$B$307,MATCH($AR79,cpe!$F$2:$F$307,0)),INDEX(cpe!$B$2:$B$307,MATCH($AR79,cpe!$D$2:$D$307,0))),"#N/D") -> #N/D | J79: =IF($AQ79,"#N/D",IFERROR(INDEX(Olimpiadas!$B$2:$B$61,MATCH($AO79,Olimpiadas!$C$2:$C$61,0)),"#N/D")) -> #N/D | K79: =IF($AQ79,"#N/D",IFERROR(INDEX(Olimpiadas!$A$2:$A$61,MATCH($AO79,Olimpiadas!$C$2:$C$61,0)),"#N/D")) -> #N/D | L79: =IF($AQ79,"#N/D",IFERROR(INDEX(Minculturas!$A$2:$A$48,MATCH($AO79,Minculturas!$C$2:$C$48,0)),"#N/D")) -> #N/D | M79: =IF($AQ79,"#N/D",IFERROR(INDEX(Minculturas!$B$2:$B$48,MATCH($AO79,Minculturas!$C$2:$C$48,0)),"#N/D")) -> #N/D | N79: 4 | O79: 0 | P79: 1 | Q79: 0 | R79: 1 | S79: 0 | T79: 1 | U79: 0 | V79: 0 | W79: 0 | X79: 0 | Y79: 0 | Z79: 0 | AA79: 1 | AB79: 0 | AC79: 0 | AD79: 0 | AE79: 0 | AF79: 0 | AG79: =SUM(O79:X79) -> 3 | AJ79: 39.7 | AM79: Declarado afectado; sin lugar con nombre propio publicado en este registro. | AO79: =TRIM(SUBSTITUTE(SUBSTITUTE(SUBSTITUTE(SUBSTITUTE(SUBSTITUTE(SUBSTITUTE(SUBSTITUTE(SUBSTITUTE(SUBSTITUTE(LOWER(G79),"á","a"),"é","e"),"í","i"),"ó","o"),"ú","u"),"ñ","n"),"-"," "),","," "),"."," ")) -> chaparral | AP79: =TRIM(SUBSTITUTE(SUBSTITUTE(SUBSTITUTE(SUBSTITUTE(SUBSTITUTE(SUBSTITUTE(SUBSTITUTE(SUBSTITUTE(SUBSTITUTE(LOWER(B79),"á","a"),"é","e"),"í","i"),"ó","o"),"ú","u"),"ñ","n"),"-"," "),","," "),"."," ")) -> tolima | AQ79: =COUNTIF($AO$2:$AO$433,AO79)>COUNTIFS($AO$2:$AO$433,AO79,$AP$2:$AP$433,AP79) -> FALSE | AR79: =IF(AQ79,AO79&"|"&AP79,AO79) -> chaparral | AS79: =(I79<>"#N/D")+(J79<>"#N/D")+(L79<>"#N/D") -> 0 | AT79: =SUM(O79:X79) -> 3 | AU79: =IF(AT79<=$AY$2,0,IF(AT79<=$AY$3,1,IF(AT79<=$AY$4,2,3))) -> 3 | AV79: =IF(Y79<=$AY$7,3,IF(Y79<=$AY$8,2,IF(Y79<=$AY$9,1,0))) -> 3 | AZ79: =IF(Y79=0,3,0) -> 3 | BA79: =AS79+AU79+AZ79 -> 6 | BB79: =IFERROR(INDEX('Análisis general'!$E$4:$E$28,MATCH($B79,'Análisis general'!$B$4:$B$28,0)),"") -> 12.2 | BC79: =IF(BB79="","",IF(BB79<=$BG$2,0,IF(BB79<=$BG$3,1,IF(BB79<=$BG$4,2,3)))) -> 3 | BD79: =(AS79+AU79+AZ79+(BC79/2))*(9/10.5) -> 6.4285714 | BE79: =(AU79+AZ79+(BC79/2))*(9/7.5) -> 9
A80: 41524 | B80: Huila | C80: Sin clasificación oficial | D80: =AS80+AU80+AV80 -> 6 | E80: =BD80 -> 6.4285714 | F80: =BE80 -> 9 | G80: Palermo | H80: =IFERROR(IF($AQ80,INDEX(cpe!$C$2:$C$307,MATCH($AR80,cpe!$F$2:$F$307,0)),INDEX(cpe!$C$2:$C$307,MATCH($AR80,cpe!$D$2:$D$307,0))),"#N/D") -> #N/D | I80: =IFERROR(IF($AQ80,INDEX(cpe!$B$2:$B$307,MATCH($AR80,cpe!$F$2:$F$307,0)),INDEX(cpe!$B$2:$B$307,MATCH($AR80,cpe!$D$2:$D$307,0))),"#N/D") -> #N/D | J80: =IF($AQ80,"#N/D",IFERROR(INDEX(Olimpiadas!$B$2:$B$61,MATCH($AO80,Olimpiadas!$C$2:$C$61,0)),"#N/D")) -> #N/D | K80: =IF($AQ80,"#N/D",IFERROR(INDEX(Olimpiadas!$A$2:$A$61,MATCH($AO80,Olimpiadas!$C$2:$C$61,0)),"#N/D")) -> #N/D | L80: =IF($AQ80,"#N/D",IFERROR(INDEX(Minculturas!$A$2:$A$48,MATCH($AO80,Minculturas!$C$2:$C$48,0)),"#N/D")) -> #N/D | M80: =IF($AQ80,"#N/D",IFERROR(INDEX(Minculturas!$B$2:$B$48,MATCH($AO80,Minculturas!$C$2:$C$48,0)),"#N/D")) -> #N/D | N80: 3 | O80: 0 | P80: 0 | Q80: 2 | R80: 0 | S80: 1 | T80: 0 | U80: 0 | V80: 0 | W80: 0 | X80: 0 | Y80: 0 | Z80: 0 | AA80: 0 | AB80: 0 | AC80: 0 | AD80: 0 | AE80: 0 | AF80: 0 | AG80: =SUM(O80:X80) -> 3 | AJ80: 32.6 | AM80: Declarado afectado; sin lugar con nombre propio publicado en este registro. | AO80: =TRIM(SUBSTITUTE(SUBSTITUTE(SUBSTITUTE(SUBSTITUTE(SUBSTITUTE(SUBSTITUTE(SUBSTITUTE(SUBSTITUTE(SUBSTITUTE(LOWER(G80),"á","a"),"é","e"),"í","i"),"ó","o"),"ú","u"),"ñ","n"),"-"," "),","," "),"."," ")) -> palermo | AP80: =TRIM(SUBSTITUTE(SUBSTITUTE(SUBSTITUTE(SUBSTITUTE(SUBSTITUTE(SUBSTITUTE(SUBSTITUTE(SUBSTITUTE(SUBSTITUTE(LOWER(B80),"á","a"),"é","e"),"í","i"),"ó","o"),"ú","u"),"ñ","n"),"-"," "),","," "),"."," ")) -> huila | AQ80: =COUNTIF($AO$2:$AO$433,AO80)>COUNTIFS($AO$2:$AO$433,AO80,$AP$2:$AP$433,AP80) -> FALSE | AR80: =IF(AQ80,AO80&"|"&AP80,AO80) -> palermo | AS80: =(I80<>"#N/D")+(J80<>"#N/D")+(L80<>"#N/D") -> 0 | AT80: =SUM(O80:X80) -> 3 | AU80: =IF(AT80<=$AY$2,0,IF(AT80<=$AY$3,1,IF(AT80<=$AY$4,2,3))) -> 3 | AV80: =IF(Y80<=$AY$7,3,IF(Y80<=$AY$8,2,IF(Y80<=$AY$9,1,0))) -> 3 | AZ80: =IF(Y80=0,3,0) -> 3 | BA80: =AS80+AU80+AZ80 -> 6 | BB80: =IFERROR(INDEX('Análisis general'!$E$4:$E$28,MATCH($B80,'Análisis general'!$B$4:$B$28,0)),"") -> 9.7 | BC80: =IF(BB80="","",IF(BB80<=$BG$2,0,IF(BB80<=$BG$3,1,IF(BB80<=$BG$4,2,3)))) -> 3 | BD80: =(AS80+AU80+AZ80+(BC80/2))*(9/10.5) -> 6.4285714 | BE80: =(AU80+AZ80+(BC80/2))*(9/7.5) -> 9
A81: 41548 | B81: Huila | C81: Sin clasificación oficial | D81: =AS81+AU81+AV81 -> 6 | E81: =BD81 -> 6.4285714 | F81: =BE81 -> 9 | G81: El Pital | H81: =IFERROR(IF($AQ81,INDEX(cpe!$C$2:$C$307,MATCH($AR81,cpe!$F$2:$F$307,0)),INDEX(cpe!$C$2:$C$307,MATCH($AR81,cpe!$D$2:$D$307,0))),"#N/D") -> #N/D | I81: =IFERROR(IF($AQ81,INDEX(cpe!$B$2:$B$307,MATCH($AR81,cpe!$F$2:$F$307,0)),INDEX(cpe!$B$2:$B$307,MATCH($AR81,cpe!$D$2:$D$307,0))),"#N/D") -> #N/D | J81: =IF($AQ81,"#N/D",IFERROR(INDEX(Olimpiadas!$B$2:$B$61,MATCH($AO81,Olimpiadas!$C$2:$C$61,0)),"#N/D")) -> #N/D | K81: =IF($AQ81,"#N/D",IFERROR(INDEX(Olimpiadas!$A$2:$A$61,MATCH($AO81,Olimpiadas!$C$2:$C$61,0)),"#N/D")) -> #N/D | L81: =IF($AQ81,"#N/D",IFERROR(INDEX(Minculturas!$A$2:$A$48,MATCH($AO81,Minculturas!$C$2:$C$48,0)),"#N/D")) -> #N/D | M81: =IF($AQ81,"#N/D",IFERROR(INDEX(Minculturas!$B$2:$B$48,MATCH($AO81,Minculturas!$C$2:$C$48,0)),"#N/D")) -> #N/D | N81: 2 | O81: 0 | P81: 0 | Q81: 1 | R81: 0 | S81: 1 | T81: 0 | U81: 0 | V81: 0 | W81: 0 | X81: 0 | Y81: 0 | Z81: 0 | AA81: 0 | AB81: 0 | AC81: 0 | AD81: 0 | AE81: 0 | AF81: 0 | AG81: =SUM(O81:X81) -> 2 | AJ81: 43.9 | AM81: Declarado afectado; sin lugar con nombre propio publicado en este registro. | AO81: =TRIM(SUBSTITUTE(SUBSTITUTE(SUBSTITUTE(SUBSTITUTE(SUBSTITUTE(SUBSTITUTE(SUBSTITUTE(SUBSTITUTE(SUBSTITUTE(LOWER(G81),"á","a"),"é","e"),"í","i"),"ó","o"),"ú","u"),"ñ","n"),"-"," "),","," "),"."," ")) -> el pital | AP81: =TRIM(SUBSTITUTE(SUBSTITUTE(SUBSTITUTE(SUBSTITUTE(SUBSTITUTE(SUBSTITUTE(SUBSTITUTE(SUBSTITUTE(SUBSTITUTE(LOWER(B81),"á","a"),"é","e"),"í","i"),"ó","o"),"ú","u"),"ñ","n"),"-"," "),","," "),"."," ")) -> huila | AQ81: =COUNTIF($AO$2:$AO$433,AO81)>COUNTIFS($AO$2:$AO$433,AO81,$AP$2:$AP$433,AP81) -> FALSE | AR81: =IF(AQ81,AO81&"|"&AP81,AO81) -> el pital | AS81: =(I81<>"#N/D")+(J81<>"#N/D")+(L81<>"#N/D") -> 0 | AT81: =SUM(O81:X81) -> 2 | AU81: =IF(AT81<=$AY$2,0,IF(AT81<=$AY$3,1,IF(AT81<=$AY$4,2,3))) -> 3 | AV81: =IF(Y81<=$AY$7,3,IF(Y81<=$AY$8,2,IF(Y81<=$AY$9,1,0))) -> 3 | AZ81: =IF(Y81=0,3,0) -> 3 | BA81: =AS81+AU81+AZ81 -> 6 | BB81: =IFERROR(INDEX('Análisis general'!$E$4:$E$28,MATCH($B81,'Análisis general'!$B$4:$B$28,0)),"") -> 9.7 | BC81: =IF(BB81="","",IF(BB81<=$BG$2,0,IF(BB81<=$BG$3,1,IF(BB81<=$BG$4,2,3)))) -> 3 | BD81: =(AS81+AU81+AZ81+(BC81/2))*(9/10.5) -> 6.4285714 | BE81: =(AU81+AZ81+(BC81/2))*(9/7.5) -> 9
A82: 73268 | B82: Tolima | C82: Sin clasificación oficial | D82: =AS82+AU82+AV82 -> 6 | E82: =BD82 -> 6.4285714 | F82: =BE82 -> 9 | G82: Espinal | H82: =IFERROR(IF($AQ82,INDEX(cpe!$C$2:$C$307,MATCH($AR82,cpe!$F$2:$F$307,0)),INDEX(cpe!$C$2:$C$307,MATCH($AR82,cpe!$D$2:$D$307,0))),"#N/D") -> #N/D | I82: =IFERROR(IF($AQ82,INDEX(cpe!$B$2:$B$307,MATCH($AR82,cpe!$F$2:$F$307,0)),INDEX(cpe!$B$2:$B$307,MATCH($AR82,cpe!$D$2:$D$307,0))),"#N/D") -> #N/D | J82: =IF($AQ82,"#N/D",IFERROR(INDEX(Olimpiadas!$B$2:$B$61,MATCH($AO82,Olimpiadas!$C$2:$C$61,0)),"#N/D")) -> #N/D | K82: =IF($AQ82,"#N/D",IFERROR(INDEX(Olimpiadas!$A$2:$A$61,MATCH($AO82,Olimpiadas!$C$2:$C$61,0)),"#N/D")) -> #N/D | L82: =IF($AQ82,"#N/D",IFERROR(INDEX(Minculturas!$A$2:$A$48,MATCH($AO82,Minculturas!$C$2:$C$48,0)),"#N/D")) -> #N/D | M82: =IF($AQ82,"#N/D",IFERROR(INDEX(Minculturas!$B$2:$B$48,MATCH($AO82,Minculturas!$C$2:$C$48,0)),"#N/D")) -> #N/D | N82: 3 | O82: 0 | P82: 1 | Q82: 0 | R82: 0 | S82: 0 | T82: 0 | U82: 0 | V82: 1 | W82: 0 | X82: 0 | Y82: 0 | Z82: 0 | AA82: 0 | AB82: 1 | AC82: 0 | AD82: 0 | AE82: 0 | AF82: 0 | AG82: =SUM(O82:X82) -> 2 | AJ82: 19.2 | AM82: Declarado afectado; sin lugar con nombre propio publicado en este registro. | AO82: =TRIM(SUBSTITUTE(SUBSTITUTE(SUBSTITUTE(SUBSTITUTE(SUBSTITUTE(SUBSTITUTE(SUBSTITUTE(SUBSTITUTE(SUBSTITUTE(LOWER(G82),"á","a"),"é","e"),"í","i"),"ó","o"),"ú","u"),"ñ","n"),"-"," "),","," "),"."," ")) -> espinal | AP82: =TRIM(SUBSTITUTE(SUBSTITUTE(SUBSTITUTE(SUBSTITUTE(SUBSTITUTE(SUBSTITUTE(SUBSTITUTE(SUBSTITUTE(SUBSTITUTE(LOWER(B82),"á","a"),"é","e"),"í","i"),"ó","o"),"ú","u"),"ñ","n"),"-"," "),","," "),"."," ")) -> tolima | AQ82: =COUNTIF($AO$2:$AO$433,AO82)>COUNTIFS($AO$2:$AO$433,AO82,$AP$2:$AP$433,AP82) -> FALSE | AR82: =IF(AQ82,AO82&"|"&AP82,AO82) -> espinal | AS82: =(I82<>"#N/D")+(J82<>"#N/D")+(L82<>"#N/D") -> 0 | AT82: =SUM(O82:X82) -> 2 | AU82: =IF(AT82<=$AY$2,0,IF(AT82<=$AY$3,1,IF(AT82<=$AY$4,2,3))) -> 3 | AV82: =IF(Y82<=$AY$7,3,IF(Y82<=$AY$8,2,IF(Y82<=$AY$9,1,0))) -> 3 | AZ82: =IF(Y82=0,3,0) -> 3 | BA82: =AS82+AU82+AZ82 -> 6 | BB82: =IFERROR(INDEX('Análisis general'!$E$4:$E$28,MATCH($B82,'Análisis general'!$B$4:$B$28,0)),"") -> 12.2 | BC82: =IF(BB82="","",IF(BB82<=$BG$2,0,IF(BB82<=$BG$3,1,IF(BB82<=$BG$4,2,3)))) -> 3 | BD82: =(AS82+AU82+AZ82+(BC82/2))*(9/10.5) -> 6.4285714 | BE82: =(AU82+AZ82+(BC82/2))*(9/7.5) -> 9
A83: 41357 | B83: Huila | C83: Sin clasificación oficial | D83: =AS83+AU83+AV83 -> 6 | E83: =BD83 -> 6.4285714 | F83: =BE83 -> 9 | G83: Íquira | H83: =IFERROR(IF($AQ83,INDEX(cpe!$C$2:$C$307,MATCH($AR83,cpe!$F$2:$F$307,0)),INDEX(cpe!$C$2:$C$307,MATCH($AR83,cpe!$D$2:$D$307,0))),"#N/D") -> #N/D | I83: =IFERROR(IF($AQ83,INDEX(cpe!$B$2:$B$307,MATCH($AR83,cpe!$F$2:$F$307,0)),INDEX(cpe!$B$2:$B$307,MATCH($AR83,cpe!$D$2:$D$307,0))),"#N/D") -> #N/D | J83: =IF($AQ83,"#N/D",IFERROR(INDEX(Olimpiadas!$B$2:$B$61,MATCH($AO83,Olimpiadas!$C$2:$C$61,0)),"#N/D")) -> #N/D | K83: =IF($AQ83,"#N/D",IFERROR(INDEX(Olimpiadas!$A$2:$A$61,MATCH($AO83,Olimpiadas!$C$2:$C$61,0)),"#N/D")) -> #N/D | L83: =IF($AQ83,"#N/D",IFERROR(INDEX(Minculturas!$A$2:$A$48,MATCH($AO83,Minculturas!$C$2:$C$48,0)),"#N/D")) -> #N/D | M83: =IF($AQ83,"#N/D",IFERROR(INDEX(Minculturas!$B$2:$B$48,MATCH($AO83,Minculturas!$C$2:$C$48,0)),"#N/D")) -> #N/D | N83: 2 | O83: 0 | P83: 0 | Q83: 0 | R83: 0 | S83: 1 | T83: 1 | U83: 0 | V83: 0 | W83: 0 | X83: 0 | Y83: 0 | Z83: 0 | AA83: 0 | AB83: 0 | AC83: 0 | AD83: 0 | AE83: 0 | AF83: 0 | AG83: =SUM(O83:X83) -> 2 | AJ83: 49.6 | AM83: Declarado afectado; sin lugar con nombre propio publicado en este registro. | AO83: =TRIM(SUBSTITUTE(SUBSTITUTE(SUBSTITUTE(SUBSTITUTE(SUBSTITUTE(SUBSTITUTE(SUBSTITUTE(SUBSTITUTE(SUBSTITUTE(LOWER(G83),"á","a"),"é","e"),"í","i"),"ó","o"),"ú","u"),"ñ","n"),"-"," "),","," "),"."," ")) -> iquira | AP83: =TRIM(SUBSTITUTE(SUBSTITUTE(SUBSTITUTE(SUBSTITUTE(SUBSTITUTE(SUBSTITUTE(SUBSTITUTE(SUBSTITUTE(SUBSTITUTE(LOWER(B83),"á","a"),"é","e"),"í","i"),"ó","o"),"ú","u"),"ñ","n"),"-"," "),","," "),"."," ")) -> huila | AQ83: =COUNTIF($AO$2:$AO$433,AO83)>COUNTIFS($AO$2:$AO$433,AO83,$AP$2:$AP$433,AP83) -> FALSE | AR83: =IF(AQ83,AO83&"|"&AP83,AO83) -> iquira | AS83: =(I83<>"#N/D")+(J83<>"#N/D")+(L83<>"#N/D") -> 0 | AT83: =SUM(O83:X83) -> 2 | AU83: =IF(AT83<=$AY$2,0,IF(AT83<=$AY$3,1,IF(AT83<=$AY$4,2,3))) -> 3 | AV83: =IF(Y83<=$AY$7,3,IF(Y83<=$AY$8,2,IF(Y83<=$AY$9,1,0))) -> 3 | AZ83: =IF(Y83=0,3,0) -> 3 | BA83: =AS83+AU83+AZ83 -> 6 | BB83: =IFERROR(INDEX('Análisis general'!$E$4:$E$28,MATCH($B83,'Análisis general'!$B$4:$B$28,0)),"") -> 9.7 | BC83: =IF(BB83="","",IF(BB83<=$BG$2,0,IF(BB83<=$BG$3,1,IF(BB83<=$BG$4,2,3)))) -> 3 | BD83: =(AS83+AU83+AZ83+(BC83/2))*(9/10.5) -> 6.4285714 | BE83: =(AU83+AZ83+(BC83/2))*(9/7.5) -> 9
A84: 73675 | B84: Tolima | C84: Sin clasificación oficial | D84: =AS84+AU84+AV84 -> 6 | E84: =BD84 -> 6.4285714 | F84: =BE84 -> 9 | G84: San Antonio | H84: #N/D | I84: #N/D | J84: #N/D | K84: =IF($AQ84,"#N/D",IFERROR(INDEX(Olimpiadas!$A$2:$A$61,MATCH($AO84,Olimpiadas!$C$2:$C$61,0)),"#N/D")) -> #N/D | L84: =IF($AQ84,"#N/D",IFERROR(INDEX(Minculturas!$A$2:$A$48,MATCH($AO84,Minculturas!$C$2:$C$48,0)),"#N/D")) -> #N/D | M84: =IF($AQ84,"#N/D",IFERROR(INDEX(Minculturas!$B$2:$B$48,MATCH($AO84,Minculturas!$C$2:$C$48,0)),"#N/D")) -> #N/D | N84: 2 | O84: 0 | P84: 1 | Q84: 0 | R84: 0 | S84: 0 | T84: 0 | U84: 1 | V84: 0 | W84: 0 | X84: 0 | Y84: 0 | Z84: 0 | AA84: 0 | AB84: 0 | AC84: 0 | AD84: 0 | AE84: 0 | AF84: 0 | AG84: =SUM(O84:X84) -> 2 | AJ84: 53.7 | AM84: Declarado afectado; sin lugar con nombre propio publicado en este registro. | AO84: =TRIM(SUBSTITUTE(SUBSTITUTE(SUBSTITUTE(SUBSTITUTE(SUBSTITUTE(SUBSTITUTE(SUBSTITUTE(SUBSTITUTE(SUBSTITUTE(LOWER(G84),"á","a"),"é","e"),"í","i"),"ó","o"),"ú","u"),"ñ","n"),"-"," "),","," "),"."," ")) -> san antonio | AP84: =TRIM(SUBSTITUTE(SUBSTITUTE(SUBSTITUTE(SUBSTITUTE(SUBSTITUTE(SUBSTITUTE(SUBSTITUTE(SUBSTITUTE(SUBSTITUTE(LOWER(B84),"á","a"),"é","e"),"í","i"),"ó","o"),"ú","u"),"ñ","n"),"-"," "),","," "),"."," ")) -> tolima | AQ84: =COUNTIF($AO$2:$AO$433,AO84)>COUNTIFS($AO$2:$AO$433,AO84,$AP$2:$AP$433,AP84) -> FALSE | AR84: =IF(AQ84,AO84&"|"&AP84,AO84) -> san antonio | AS84: =(I84<>"#N/D")+(J84<>"#N/D")+(L84<>"#N/D") -> 0 | AT84: =SUM(O84:X84) -> 2 | AU84: =IF(AT84<=$AY$2,0,IF(AT84<=$AY$3,1,IF(AT84<=$AY$4,2,3))) -> 3 | AV84: =IF(Y84<=$AY$7,3,IF(Y84<=$AY$8,2,IF(Y84<=$AY$9,1,0))) -> 3 | AZ84: =IF(Y84=0,3,0) -> 3 | BA84: =AS84+AU84+AZ84 -> 6 | BB84: =IFERROR(INDEX('Análisis general'!$E$4:$E$28,MATCH($B84,'Análisis general'!$B$4:$B$28,0)),"") -> 12.2 | BC84: =IF(BB84="","",IF(BB84<=$BG$2,0,IF(BB84<=$BG$3,1,IF(BB84<=$BG$4,2,3)))) -> 3 | BD84: =(AS84+AU84+AZ84+(BC84/2))*(9/10.5) -> 6.4285714 | BE84: =(AU84+AZ84+(BC84/2))*(9/7.5) -> 9
A85: 05154 | B85: Antioquia | C85: Sin clasificación oficial | D85: =AS85+AU85+AV85 -> 7 | E85: =BD85 -> 7.2857143 | F85: =BE85 -> 9 | G85: Caucasia | H85: =IFERROR(IF($AQ85,INDEX(cpe!$C$2:$C$307,MATCH($AR85,cpe!$F$2:$F$307,0)),INDEX(cpe!$C$2:$C$307,MATCH($AR85,cpe!$D$2:$D$307,0))),"#N/D") -> #N/D | I85: =IFERROR(IF($AQ85,INDEX(cpe!$B$2:$B$307,MATCH($AR85,cpe!$F$2:$F$307,0)),INDEX(cpe!$B$2:$B$307,MATCH($AR85,cpe!$D$2:$D$307,0))),"#N/D") -> #N/D | J85: =IF($AQ85,"#N/D",IFERROR(INDEX(Olimpiadas!$B$2:$B$61,MATCH($AO85,Olimpiadas!$C$2:$C$61,0)),"#N/D")) -> Caucasia | K85: =IF($AQ85,"#N/D",IFERROR(INDEX(Olimpiadas!$A$2:$A$61,MATCH($AO85,Olimpiadas!$C$2:$C$61,0)),"#N/D")) -> INSTITUCIÓN EDUCATIVA RURAL CACERÍ | L85: =IF($AQ85,"#N/D",IFERROR(INDEX(Minculturas!$A$2:$A$48,MATCH($AO85,Minculturas!$C$2:$C$48,0)),"#N/D")) -> #N/D | M85: =IF($AQ85,"#N/D",IFERROR(INDEX(Minculturas!$B$2:$B$48,MATCH($AO85,Minculturas!$C$2:$C$48,0)),"#N/D")) -> #N/D | N85: 2 | O85: 0 | P85: 0 | Q85: 0 | R85: 1 | S85: 0 | T85: 1 | U85: 0 | V85: 0 | W85: 0 | X85: 0 | Y85: 0 | Z85: 0 | AA85: 0 | AB85: 0 | AC85: 0 | AD85: 0 | AE85: 0 | AF85: 0 | AG85: =SUM(O85:X85) -> 2 | AJ85: 36 | AM85: Declarado afectado; sin lugar con nombre propio publicado en este registro. | AO85: =TRIM(SUBSTITUTE(SUBSTITUTE(SUBSTITUTE(SUBSTITUTE(SUBSTITUTE(SUBSTITUTE(SUBSTITUTE(SUBSTITUTE(SUBSTITUTE(LOWER(G85),"á","a"),"é","e"),"í","i"),"ó","o"),"ú","u"),"ñ","n"),"-"," "),","," "),"."," ")) -> caucasia | AP85: =TRIM(SUBSTITUTE(SUBSTITUTE(SUBSTITUTE(SUBSTITUTE(SUBSTITUTE(SUBSTITUTE(SUBSTITUTE(SUBSTITUTE(SUBSTITUTE(LOWER(B85),"á","a"),"é","e"),"í","i"),"ó","o"),"ú","u"),"ñ","n"),"-"," "),","," "),"."," ")) -> antioquia | AQ85: =COUNTIF($AO$2:$AO$433,AO85)>COUNTIFS($AO$2:$AO$433,AO85,$AP$2:$AP$433,AP85) -> FALSE | AR85: =IF(AQ85,AO85&"|"&AP85,AO85) -> caucasia | AS85: =(I85<>"#N/D")+(J85<>"#N/D")+(L85<>"#N/D") -> 1 | AT85: =SUM(O85:X85) -> 2 | AU85: =IF(AT85<=$AY$2,0,IF(AT85<=$AY$3,1,IF(AT85<=$AY$4,2,3))) -> 3 | AV85: =IF(Y85<=$AY$7,3,IF(Y85<=$AY$8,2,IF(Y85<=$AY$9,1,0))) -> 3 | AZ85: =IF(Y85=0,3,0) -> 3 | BA85: =AS85+AU85+AZ85 -> 7 | BB85: =IFERROR(INDEX('Análisis general'!$E$4:$E$28,MATCH($B85,'Análisis general'!$B$4:$B$28,0)),"") -> 9.5 | BC85: =IF(BB85="","",IF(BB85<=$BG$2,0,IF(BB85<=$BG$3,1,IF(BB85<=$BG$4,2,3)))) -> 3 | BD85: =(AS85+AU85+AZ85+(BC85/2))*(9/10.5) -> 7.2857143 | BE85: =(AU85+AZ85+(BC85/2))*(9/7.5) -> 9
A86: 27073 | B86: Chocó | C86: Sin clasificación oficial | D86: =AS86+AU86+AV86 -> 7 | E86: =BD86 -> 7.2857143 | F86: =BE86 -> 9 | G86: Bagadó | H86: =IFERROR(IF($AQ86,INDEX(cpe!$C$2:$C$307,MATCH($AR86,cpe!$F$2:$F$307,0)),INDEX(cpe!$C$2:$C$307,MATCH($AR86,cpe!$D$2:$D$307,0))),"#N/D") -> Institucion Educativa el Quebradon | I86: =IFERROR(IF($AQ86,INDEX(cpe!$B$2:$B$307,MATCH($AR86,cpe!$F$2:$F$307,0)),INDEX(cpe!$B$2:$B$307,MATCH($AR86,cpe!$D$2:$D$307,0))),"#N/D") -> Bagadó | J86: =IF($AQ86,"#N/D",IFERROR(INDEX(Olimpiadas!$B$2:$B$61,MATCH($AO86,Olimpiadas!$C$2:$C$61,0)),"#N/D")) -> #N/D | K86: =IF($AQ86,"#N/D",IFERROR(INDEX(Olimpiadas!$A$2:$A$61,MATCH($AO86,Olimpiadas!$C$2:$C$61,0)),"#N/D")) -> #N/D | L86: =IF($AQ86,"#N/D",IFERROR(INDEX(Minculturas!$A$2:$A$48,MATCH($AO86,Minculturas!$C$2:$C$48,0)),"#N/D")) -> #N/D | M86: =IF($AQ86,"#N/D",IFERROR(INDEX(Minculturas!$B$2:$B$48,MATCH($AO86,Minculturas!$C$2:$C$48,0)),"#N/D")) -> #N/D | N86: 2 | O86: 0 | P86: 0 | Q86: 1 | R86: 0 | S86: 0 | T86: 0 | U86: 0 | V86: 0 | W86: 0 | X86: 0 | Y86: 0 | Z86: 1 | AA86: 0 | AB86: 0 | AC86: 0 | AD86: 0 | AE86: 0 | AF86: 0 | AG86: =SUM(O86:X86) -> 1 | AH86: 482 | AI86: 1024 | AJ86: 81 | AM86: Declarado afectado; sin lugar con nombre propio publicado en este registro. | AO86: =TRIM(SUBSTITUTE(SUBSTITUTE(SUBSTITUTE(SUBSTITUTE(SUBSTITUTE(SUBSTITUTE(SUBSTITUTE(SUBSTITUTE(SUBSTITUTE(LOWER(G86),"á","a"),"é","e"),"í","i"),"ó","o"),"ú","u"),"ñ","n"),"-"," "),","," "),"."," ")) -> bagado | AP86: =TRIM(SUBSTITUTE(SUBSTITUTE(SUBSTITUTE(SUBSTITUTE(SUBSTITUTE(SUBSTITUTE(SUBSTITUTE(SUBSTITUTE(SUBSTITUTE(LOWER(B86),"á","a"),"é","e"),"í","i"),"ó","o"),"ú","u"),"ñ","n"),"-"," "),","," "),"."," ")) -> choco | AQ86: =COUNTIF($AO$2:$AO$433,AO86)>COUNTIFS($AO$2:$AO$433,AO86,$AP$2:$AP$433,AP86) -> FALSE | AR86: =IF(AQ86,AO86&"|"&AP86,AO86) -> bagado | AS86: =(I86<>"#N/D")+(J86<>"#N/D")+(L86<>"#N/D") -> 1 | AT86: =SUM(O86:X86) -> 1 | AU86: =IF(AT86<=$AY$2,0,IF(AT86<=$AY$3,1,IF(AT86<=$AY$4,2,3))) -> 3 | AV86: =IF(Y86<=$AY$7,3,IF(Y86<=$AY$8,2,IF(Y86<=$AY$9,1,0))) -> 3 | AZ86: =IF(Y86=0,3,0) -> 3 | BA86: =AS86+AU86+AZ86 -> 7 | BB86: =IFERROR(INDEX('Análisis general'!$E$4:$E$28,MATCH($B86,'Análisis general'!$B$4:$B$28,0)),"") -> 30.8 | BC86: =IF(BB86="","",IF(BB86<=$BG$2,0,IF(BB86<=$BG$3,1,IF(BB86<=$BG$4,2,3)))) -> 3 | BD86: =(AS86+AU86+AZ86+(BC86/2))*(9/10.5) -> 7.2857143 | BE86: =(AU86+AZ86+(BC86/2))*(9/7.5) -> 9
A87: 52079 | B87: Nariño | C87: Sin clasificación oficial | D87: =AS87+AU87+AV87 -> 7 | E87: =BD87 -> 7.2857143 | F87: =BE87 -> 9 | G87: Barbacoas | H87: =IFERROR(IF($AQ87,INDEX(cpe!$C$2:$C$307,MATCH($AR87,cpe!$F$2:$F$307,0)),INDEX(cpe!$C$2:$C$307,MATCH($AR87,cpe!$D$2:$D$307,0))),"#N/D") -> IE Hernando Palacios | I87: =IFERROR(IF($AQ87,INDEX(cpe!$B$2:$B$307,MATCH($AR87,cpe!$F$2:$F$307,0)),INDEX(cpe!$B$2:$B$307,MATCH($AR87,cpe!$D$2:$D$307,0))),"#N/D") -> Barbacoas | J87: =IF($AQ87,"#N/D",IFERROR(INDEX(Olimpiadas!$B$2:$B$61,MATCH($AO87,Olimpiadas!$C$2:$C$61,0)),"#N/D")) -> #N/D | K87: =IF($AQ87,"#N/D",IFERROR(INDEX(Olimpiadas!$A$2:$A$61,MATCH($AO87,Olimpiadas!$C$2:$C$61,0)),"#N/D")) -> #N/D | L87: =IF($AQ87,"#N/D",IFERROR(INDEX(Minculturas!$A$2:$A$48,MATCH($AO87,Minculturas!$C$2:$C$48,0)),"#N/D")) -> #N/D | M87: =IF($AQ87,"#N/D",IFERROR(INDEX(Minculturas!$B$2:$B$48,MATCH($AO87,Minculturas!$C$2:$C$48,0)),"#N/D")) -> #N/D | N87: 1 | O87: 0 | P87: 0 | Q87: 0 | R87: 0 | S87: 1 | T87: 0 | U87: 0 | V87: 0 | W87: 0 | X87: 0 | Y87: 0 | Z87: 0 | AA87: 0 | AB87: 0 | AC87: 0 | AD87: 0 | AE87: 0 | AF87: 0 | AG87: =SUM(O87:X87) -> 1 | AJ87: 76.1 | AM87: Declarado afectado; sin lugar con nombre propio publicado en este registro. | AO87: =TRIM(SUBSTITUTE(SUBSTITUTE(SUBSTITUTE(SUBSTITUTE(SUBSTITUTE(SUBSTITUTE(SUBSTITUTE(SUBSTITUTE(SUBSTITUTE(LOWER(G87),"á","a"),"é","e"),"í","i"),"ó","o"),"ú","u"),"ñ","n"),"-"," "),","," "),"."," ")) -> barbacoas | AP87: =TRIM(SUBSTITUTE(SUBSTITUTE(SUBSTITUTE(SUBSTITUTE(SUBSTITUTE(SUBSTITUTE(SUBSTITUTE(SUBSTITUTE(SUBSTITUTE(LOWER(B87),"á","a"),"é","e"),"í","i"),"ó","o"),"ú","u"),"ñ","n"),"-"," "),","," "),"."," ")) -> narino | AQ87: =COUNTIF($AO$2:$AO$433,AO87)>COUNTIFS($AO$2:$AO$433,AO87,$AP$2:$AP$433,AP87) -> FALSE | AR87: =IF(AQ87,AO87&"|"&AP87,AO87) -> barbacoas | AS87: =(I87<>"#N/D")+(J87<>"#N/D")+(L87<>"#N/D") -> 1 | AT87: =SUM(O87:X87) -> 1 | AU87: =IF(AT87<=$AY$2,0,IF(AT87<=$AY$3,1,IF(AT87<=$AY$4,2,3))) -> 3 | AV87: =IF(Y87<=$AY$7,3,IF(Y87<=$AY$8,2,IF(Y87<=$AY$9,1,0))) -> 3 | AZ87: =IF(Y87=0,3,0) -> 3 | BA87: =AS87+AU87+AZ87 -> 7 | BB87: =IFERROR(INDEX('Análisis general'!$E$4:$E$28,MATCH($B87,'Análisis general'!$B$4:$B$28,0)),"") -> 13.2 | BC87: =IF(BB87="","",IF(BB87<=$BG$2,0,IF(BB87<=$BG$3,1,IF(BB87<=$BG$4,2,3)))) -> 3 | BD87: =(AS87+AU87+AZ87+(BC87/2))*(9/10.5) -> 7.2857143 | BE87: =(AU87+AZ87+(BC87/2))*(9/7.5) -> 9
A88: 05353 | B88: Antioquia | C88: Sin clasificación oficial | D88: =AS88+AU88+AV88 -> 6 | E88: =BD88 -> 6.4285714 | F88: =BE88 -> 9 | G88: Hispania | H88: =IFERROR(IF($AQ88,INDEX(cpe!$C$2:$C$307,MATCH($AR88,cpe!$F$2:$F$307,0)),INDEX(cpe!$C$2:$C$307,MATCH($AR88,cpe!$D$2:$D$307,0))),"#N/D") -> #N/D | I88: =IFERROR(IF($AQ88,INDEX(cpe!$B$2:$B$307,MATCH($AR88,cpe!$F$2:$F$307,0)),INDEX(cpe!$B$2:$B$307,MATCH($AR88,cpe!$D$2:$D$307,0))),"#N/D") -> #N/D | J88: =IF($AQ88,"#N/D",IFERROR(INDEX(Olimpiadas!$B$2:$B$61,MATCH($AO88,Olimpiadas!$C$2:$C$61,0)),"#N/D")) -> #N/D | K88: =IF($AQ88,"#N/D",IFERROR(INDEX(Olimpiadas!$A$2:$A$61,MATCH($AO88,Olimpiadas!$C$2:$C$61,0)),"#N/D")) -> #N/D | L88: =IF($AQ88,"#N/D",IFERROR(INDEX(Minculturas!$A$2:$A$48,MATCH($AO88,Minculturas!$C$2:$C$48,0)),"#N/D")) -> #N/D | M88: =IF($AQ88,"#N/D",IFERROR(INDEX(Minculturas!$B$2:$B$48,MATCH($AO88,Minculturas!$C$2:$C$48,0)),"#N/D")) -> #N/D | N88: 4 | O88: 0 | P88: 2 | Q88: 0 | R88: 0 | S88: 1 | T88: 1 | U88: 0 | V88: 0 | W88: 0 | X88: 0 | Y88: 0 | Z88: 0 | AA88: 0 | AB88: 0 | AC88: 0 | AD88: 0 | AE88: 0 | AF88: 0 | AG88: =SUM(O88:X88) -> 4 | AJ88: 36.9 | AM88: Declarado afectado; sin lugar con nombre propio publicado en este registro. | AO88: =TRIM(SUBSTITUTE(SUBSTITUTE(SUBSTITUTE(SUBSTITUTE(SUBSTITUTE(SUBSTITUTE(SUBSTITUTE(SUBSTITUTE(SUBSTITUTE(LOWER(G88),"á","a"),"é","e"),"í","i"),"ó","o"),"ú","u"),"ñ","n"),"-"," "),","," "),"."," ")) -> hispania | AP88: =TRIM(SUBSTITUTE(SUBSTITUTE(SUBSTITUTE(SUBSTITUTE(SUBSTITUTE(SUBSTITUTE(SUBSTITUTE(SUBSTITUTE(SUBSTITUTE(LOWER(B88),"á","a"),"é","e"),"í","i"),"ó","o"),"ú","u"),"ñ","n"),"-"," "),","," "),"."," ")) -> antioquia | AQ88: =COUNTIF($AO$2:$AO$433,AO88)>COUNTIFS($AO$2:$AO$433,AO88,$AP$2:$AP$433,AP88) -> FALSE | AR88: =IF(AQ88,AO88&"|"&AP88,AO88) -> hispania | AS88: =(I88<>"#N/D")+(J88<>"#N/D")+(L88<>"#N/D") -> 0 | AT88: =SUM(O88:X88) -> 4 | AU88: =IF(AT88<=$AY$2,0,IF(AT88<=$AY$3,1,IF(AT88<=$AY$4,2,3))) -> 3 | AV88: =IF(Y88<=$AY$7,3,IF(Y88<=$AY$8,2,IF(Y88<=$AY$9,1,0))) -> 3 | AZ88: =IF(Y88=0,3,0) -> 3 | BA88: =AS88+AU88+AZ88 -> 6 | BB88: =IFERROR(INDEX('Análisis general'!$E$4:$E$28,MATCH($B88,'Análisis general'!$B$4:$B$28,0)),"") -> 9.5 | BC88: =IF(BB88="","",IF(BB88<=$BG$2,0,IF(BB88<=$BG$3,1,IF(BB88<=$BG$4,2,3)))) -> 3 | BD88: =(AS88+AU88+AZ88+(BC88/2))*(9/10.5) -> 6.4285714 | BE88: =(AU88+AZ88+(BC88/2))*(9/7.5) -> 9
